Workbook

Sheet Start Here
B1: Cleaning Business System - Start Here
B2: Clients, jobs, invoices, payments, expenses and a monthly profit report in one file. Type each thing once - the rest fills in for you.
B4: HOW THE COLORS WORK
B5: Teal column headers = you type here (many cells have dropdown lists).
B6: Dark gray headers and light gray cells = automatic. Please don't type over them.
B7: Yellow cells on the Settings tab = your business details and price list.
B9: SET UP IN 5 STEPS
B10: 1. Settings: enter your business name, sales tax rate (0% if you don't charge tax), payment terms and P&L year.
B11: 2. Settings: list your services and your standard price for each one (room for 15).
B12: 3. Clients: add each client once - name, address, usual service, and a custom price if they have one.
B13: 4. Jobs: add a row for every job. Pick the date, pick the client, and set Status to Completed when it's done.
B14: 5. Invoices: completed jobs show up as invoices. When a client pays, log it in the Payments Log on the same tab.
... B43: Room for 200 clients, 500 jobs, 500 expenses and 1,000 payments.

Sheet Settings
A1: Settings
A2: Yellow cells are yours to change. Everything else in the file reads from here.
A4: Setting | B4: Your value | D4: Service type | E4: ="Standard rate ("&Settings!$B$10&")" -> Standard rate ($) | F4: Rate basis / notes | H4: Expense categories | J4: Payment methods
A5: Business name | B5: Sparkle & Shine Cleaning Co. | D5: Standard Clean | E5: 120 | F5: per visit | H5: Cleaning Supplies | J5: Cash
A6: Owner / contact name | B6: Your Name | D6: Deep Clean | E6: 220 | F6: per visit | H6: Equipment | J6: Check
A7: Phone | B7: (555) 010-2040 | D7: Move-In / Move-Out | E7: 320 | F7: per visit | H7: Fuel & Mileage | J7: Card
A8: Email | B8: hello@example.com | D8: Recurring Weekly | E8: 95 | F8: per visit | H8: Wages & Contractors | J8: Bank Transfer
A9: Sales tax rate (0% if you don't charge tax) | B9: 0.06 | D9: Recurring Every 2 Weeks | E9: 110 | F9: per visit | H9: Insurance | J9: Payment App
A10: Currency symbol (shown in headers) | B10: $ | D10: Office Clean (hourly) | E10: 45 | F10: per hour - enter hours in Qty | H10: Marketing & Advertising | J10: Other
A11: Payment terms (days until an invoice is due) | B11: 14 | D11: Window Cleaning | E11: 85 | F11: per visit | H11: Phone & Software
A12: P&L year | B12: 2026 | D12: Post-Construction | E12: 400 | F12: per visit | H12: Vehicle Maintenance
A13: Invoice number prefix | B13: INV- | H13: Licenses & Fees
H14: Other
D21: Renaming a service? Update the jobs and clients that use the old name too.

Sheet Clients
A1: =Settings!$B$5&" - Clients" -> Sparkle & Shine Cleaning Co. - Clients
A2: One row per client. Jobs, invoices and balances look up this list - enter each client only once.
A4: Client name | B4: Phone | C4: Email | D4: Service address | E4: Usual service | F4: ="Custom rate (optional) ("&Settings!$B$10&")" -> Custom rate (optional) ($) | G4: Frequency | H4: Notes | I4: Completed jobs | J4: ="Total billed ("&Settings!$B$10&")" -> Total billed ($) | K4: ="Balance owed ("&Settings!$B$10&")" -> Balance owed ($)
A5: Hannah Whitfield | B5: (555) 201-3344 | C5: hannah.w@example.com | D5: 412 Maple Ridge Dr, Springfield | E5: Recurring Every 2 Weeks | G5: Every 2 weeks | H5: Gate code 4471. Two friendly dogs. | I5: =IF($A5="","",COUNTIFS(Jobs!$B$5:$B$504,$A5,Jobs!$G$5:$G$504,"Completed")) -> 5 | J5: =IF($A5="","",SUMIFS(Invoices!$E$5:$E$504,Invoices!$C$5:$C$504,$A5)) -> 583 | K5: =IF($A5="","",SUMIFS(Invoices!$G$5:$G$504,Invoices!$C$5:$C$504,$A5)) -> 116.6
A6: Marcus & Elena Ortiz | B6: (555) 318-7702 | C6: ortiz.home@example.com | D6: 88 Birchwood Ln, Springfield | E6: Recurring Weekly | F6: 90 | G6: Weekly | H6: Loyalty price. Key in lockbox. | I6: =IF($A6="","",COUNTIFS(Jobs!$B$5:$B$504,$A6,Jobs!$G$5:$G$504,"Completed")) -> 5 | J6: =IF($A6="","",SUMIFS(Invoices!$E$5:$E$504,Invoices!$C$5:$C$504,$A6)) -> 477 | K6: =IF($A6="","",SUMIFS(Invoices!$G$5:$G$504,Invoices!$C$5:$C$504,$A6)) -> 0
A7: Brightpath Dental Office | B7: (555) 440-1180 | C7: frontdesk@example.com | D7: 1500 Commerce Pkwy, Suite 210, Springfield | E7: Office Clean (hourly) | G7: Weekly | H7: After 6 pm only. | I7: =IF($A7="","",COUNTIFS(Jobs!$B$5:$B$504,$A7,Jobs!$G$5:$G$504,"Completed")) -> 4 | J7: =IF($A7="","",SUMIFS(Invoices!$E$5:$E$504,Invoices!$C$5:$C$504,$A7)) -> 596.25 | K7: =IF($A7="","",SUMIFS(Invoices!$G$5:$G$504,Invoices!$C$5:$C$504,$A7)) -> 0
A8: Priya Raman | B8: (555) 562-9015 | C8: priya.r@example.com | D8: 27 Lakeview Ct, Riverton | E8: Deep Clean | G8: Monthly | H8: Fragrance-free products only. | I8: =IF($A8="","",COUNTIFS(Jobs!$B$5:$B$504,$A8,Jobs!$G$5:$G$504,"Completed")) -> 3 | J8: =IF($A8="","",SUMIFS(Invoices!$E$5:$E$504,Invoices!$C$5:$C$504,$A8)) -> 620.1 | K8: =IF($A8="","",SUMIFS(Invoices!$G$5:$G$504,Invoices!$C$5:$C$504,$A8)) -> 233.2
A9: Tom Kessler | B9: (555) 673-2208 | C9: tkessler@example.com | D9: 9 Old Mill Rd, Riverton | E9: Standard Clean | G9: Monthly | I9: =IF($A9="","",COUNTIFS(Jobs!$B$5:$B$504,$A9,Jobs!$G$5:$G$504,"Completed")) -> 2 | J9: =IF($A9="","",SUMIFS(Invoices!$E$5:$E$504,Invoices!$C$5:$C$504,$A9)) -> 227.9 | K9: =IF($A9="","",SUMIFS(Invoices!$G$5:$G$504,Invoices!$C$5:$C$504,$A9)) -> 227.9
A10: Greenleaf Property Mgmt | B10: (555) 784-5530 | C10: units@example.com | D10: 300 Harbor St, Springfield | E10: Move-In / Move-Out | F10: 300 | G10: One-time | H10: Rental turnovers. Unit number goes in job notes. | I10: =IF($A10="","",COUNTIFS(Jobs!$B$5:$B$504,$A10,Jobs!$G$5:$G$504,"Completed")) -> 3 | J10: =IF($A10="","",SUMIFS(Invoices!$E$5:$E$504,Invoices!$C$5:$C$504,$A10)) -> 996.4 | K10: =IF($A10="","",SUMIFS(Invoices!$G$5:$G$504,Invoices!$C$5:$C$504,$A10)) -> 478.4
A11: Danielle Brooks | B11: (555) 895-6127 | C11: dani.brooks@example.com | D11: 1742 Sunset Ave, Springfield | E11: Standard Clean | G11: Every 2 weeks | H11: Prefers Friday mornings. | I11: =IF($A11="","",COUNTIFS(Jobs!$B$5:$B$504,$A11,Jobs!$G$5:$G$504,"Completed")) -> 2 | J11: =IF($A11="","",SUMIFS(Invoices!$E$5:$E$504,Invoices!$C$5:$C$504,$A11)) -> 360.4 | K11: =IF($A11="","",SUMIFS(Invoices!$G$5:$G$504,Invoices!$C$5:$C$504,$A11)) -> 0
A12: Riverside Yoga Studio | B12: (555) 906-3471 | C12: hello.riverside@example.com | D12: 55 River Rd, Riverton | E12: Office Clean (hourly) | F12: 40 | G12: Weekly | H12: Mop studio floors with water only. | I12: =IF($A12="","",COUNTIFS(Jobs!$B$5:$B$504,$A12,Jobs!$G$5:$G$504,"Completed")) -> 3 | J12: =IF($A12="","",SUMIFS(Invoices!$E$5:$E$504,Invoices!$C$5:$C$504,$A12)) -> 318 | K12: =IF($A12="","",SUMIFS(Invoices!$G$5:$G$504,Invoices!$C$5:$C$504,$A12)) -> 0
I13: =IF($A13="","",COUNTIFS(Jobs!$B$5:$B$504,$A13,Jobs!$G$5:$G$504,"Completed")) | J13: =IF($A13="","",SUMIFS(Invoices!$E$5:$E$504,Invoices!$C$5:$C$504,$A13)) | K13: =IF($A13="","",SUMIFS(Invoices!$G$5:$G$504,Invoices!$C$5:$C$504,$A13))
I14: =IF($A14="","",COUNTIFS(Jobs!$B$5:$B$504,$A14,Jobs!$G$5:$G$504,"Completed")) | J14: =IF($A14="","",SUMIFS(Invoices!$E$5:$E$504,Invoices!$C$5:$C$504,$A14)) | K14: =IF($A14="","",SUMIFS(Invoices!$G$5:$G$504,Invoices!$C$5:$C$504,$A14))
I15: =IF($A15="","",COUNTIFS(Jobs!$B$5:$B$504,$A15,Jobs!$G$5:$G$504,"Completed")) | J15: =IF($A15="","",SUMIFS(Invoices!$E$5:$E$504,Invoices!$C$5:$C$504,$A15)) | K15: =IF($A15="","",SUMIFS(Invoices!$G$5:$G$504,Invoices!$C$5:$C$504,$A15))
I16: =IF($A16="","",COUNTIFS(Jobs!$B$5:$B$504,$A16,Jobs!$G$5:$G$504,"Completed")) | J16: =IF($A16="","",SUMIFS(Invoices!$E$5:$E$504,Invoices!$C$5:$C$504,$A16)) | K16: =IF($A16="","",SUMIFS(Invoices!$G$5:$G$504,Invoices!$C$5:$C$504,$A16))
I17: =IF($A17="","",COUNTIFS(Jobs!$B$5:$B$504,$A17,Jobs!$G$5:$G$504,"Completed")) | J17: =IF($A17="","",SUMIFS(Invoices!$E$5:$E$504,Invoices!$C$5:$C$504,$A17)) | K17: =IF($A17="","",SUMIFS(Invoices!$G$5:$G$504,Invoices!$C$5:$C$504,$A17))
I18: =IF($A18="","",COUNTIFS(Jobs!$B$5:$B$504,$A18,Jobs!$G$5:$G$504,"Completed")) | J18: =IF($A18="","",SUMIFS(Invoices!$E$5:$E$504,Invoices!$C$5:$C$504,$A18)) | K18: =IF($A18="","",SUMIFS(Invoices!$G$5:$G$504,Invoices!$C$5:$C$504,$A18))
I19: =IF($A19="","",COUNTIFS(Jobs!$B$5:$B$504,$A19,Jobs!$G$5:$G$504,"Completed")) | J19: =IF($A19="","",SUMIFS(Invoices!$E$5:$E$504,Invoices!$C$5:$C$504,$A19)) | K19: =IF($A19="","",SUMIFS(Invoices!$G$5:$G$504,Invoices!$C$5:$C$504,$A19))
I20: =IF($A20="","",COUNTIFS(Jobs!$B$5:$B$504,$A20,Jobs!$G$5:$G$504,"Completed")) | J20: =IF($A20="","",SUMIFS(Invoices!$E$5:$E$504,Invoices!$C$5:$C$504,$A20)) | K20: =IF($A20="","",SUMIFS(Invoices!$G$5:$G$504,Invoices!$C$5:$C$504,$A20))
I21: =IF($A21="","",COUNTIFS(Jobs!$B$5:$B$504,$A21,Jobs!$G$5:$G$504,"Completed")) | J21: =IF($A21="","",SUMIFS(Invoices!$E$5:$E$504,Invoices!$C$5:$C$504,$A21)) | K21: =IF($A21="","",SUMIFS(Invoices!$G$5:$G$504,Invoices!$C$5:$C$504,$A21))
I22: =IF($A22="","",COUNTIFS(Jobs!$B$5:$B$504,$A22,Jobs!$G$5:$G$504,"Completed")) | J22: =IF($A22="","",SUMIFS(Invoices!$E$5:$E$504,Invoices!$C$5:$C$504,$A22)) | K22: =IF($A22="","",SUMIFS(Invoices!$G$5:$G$504,Invoices!$C$5:$C$504,$A22))
I23: =IF($A23="","",COUNTIFS(Jobs!$B$5:$B$504,$A23,Jobs!$G$5:$G$504,"Completed")) | J23: =IF($A23="","",SUMIFS(Invoices!$E$5:$E$504,Invoices!$C$5:$C$504,$A23)) | K23: =IF($A23="","",SUMIFS(Invoices!$G$5:$G$504,Invoices!$C$5:$C$504,$A23))
I24: =IF($A24="","",COUNTIFS(Jobs!$B$5:$B$504,$A24,Jobs!$G$5:$G$504,"Completed")) | J24: =IF($A24="","",SUMIFS(Invoices!$E$5:$E$504,Invoices!$C$5:$C$504,$A24)) | K24: =IF($A24="","",SUMIFS(Invoices!$G$5:$G$504,Invoices!$C$5:$C$504,$A24))
... I204: =IF($A204="","",COUNTIFS(Jobs!$B$5:$B$504,$A204,Jobs!$G$5:$G$504,"Completed")) | J204: =IF($A204="","",SUMIFS(Invoices!$E$5:$E$504,Invoices!$C$5:$C$504,$A204)) | K204: =IF($A204="","",SUMIFS(Invoices!$G$5:$G$504,Invoices!$C$5:$C$504,$A204))

Sheet Jobs
A1: =Settings!$B$5&" - Jobs" -> Sparkle & Shine Cleaning Co. - Jobs
A2: Type in the teal columns (A-H). Gray columns fill in by themselves. Only Completed jobs become invoices.
A4: Date | B4: Client | C4: Service (blank = usual) | D4: Qty / hours (blank = 1) | E4: ="Extras ("&Settings!$B$10&")" -> Extras ($) | F4: ="Rate override ("&Settings!$B$10&")" -> Rate override ($) | G4: Status | H4: Notes | I4: Address | J4: Service used | K4: ="Rate ("&Settings!$B$10&")" -> Rate ($) | L4: ="Subtotal ("&Settings!$B$10&")" -> Subtotal ($) | M4: ="Tax ("&Settings!$B$10&")" -> Tax ($) | N4: ="Total ("&Settings!$B$10&")" -> Total ($) | O4: Invoice # | P4: Payment status | Q4: Invoice line (helper)
A5: 46205 | B5: Hannah Whitfield | G5: Completed | I5: =IF($B5="","",IFERROR(INDEX(Clients!$D$5:$D$204,MATCH($B5,Clients!$A$5:$A$204,0))&"","")) -> 412 Maple Ridge Dr, Springfield | J5: =IF($B5="","",IF($C5<>"",$C5,IFERROR(INDEX(Clients!$E$5:$E$204,MATCH($B5,Clients!$A$5:$A$204,0))&"",""))) -> Recurring Every 2 Weeks | K5: =IF($B5="","",IF($F5<>"",$F5,IFERROR(IF(AND(INDEX(Clients!$F$5:$F$204,MATCH($B5,Clients!$A$5:$A$204,0))&""<>"",OR($C5="",$C5=INDEX(Clients!$E$5:$E$204,MATCH($B5,Clients!$A$5:$A$204,0)))),INDEX(Clients!$F$5:$F$204,MATCH($B5,Clients!$A$5:$A$204,0)),INDEX(Settings!$E$5:$E$19,MATCH($J5,Settings!$D$5:$D$19,0))),0))) -> 110 | L5: =IF($B5="","",$K5*IF($D5="",1,$D5)+$E5) -> 110 | M5: =IF($B5="","",ROUND($L5*Settings!$B$9,2)) -> 6.6 | N5: =IF($B5="","",$L5+$M5) -> 116.6 | O5: =IF($Q5="","",Settings!$B$13&TEXT(ROWS($A$5:$A5),"0000")) -> INV-0001 | P5: =IF($O5="","",IFERROR(INDEX(Invoices!$I$5:$I$504,MATCH($O5,Invoices!$A$5:$A$504,0)),"")) -> Paid | Q5: =IF(AND($A5<>"",$B5<>"",$G5="Completed"),COUNTIFS($A$5:$A5,"<>",$B$5:$B5,"<>",$G$5:$G5,"Completed"),"") -> 1
A6: 46206 | B6: Brightpath Dental Office | D6: 3 | G6: Completed | I6: =IF($B6="","",IFERROR(INDEX(Clients!$D$5:$D$204,MATCH($B6,Clients!$A$5:$A$204,0))&"","")) -> 1500 Commerce Pkwy, Suite 210, Springfield | J6: =IF($B6="","",IF($C6<>"",$C6,IFERROR(INDEX(Clients!$E$5:$E$204,MATCH($B6,Clients!$A$5:$A$204,0))&"",""))) -> Office Clean (hourly) | K6: =IF($B6="","",IF($F6<>"",$F6,IFERROR(IF(AND(INDEX(Clients!$F$5:$F$204,MATCH($B6,Clients!$A$5:$A$204,0))&""<>"",OR($C6="",$C6=INDEX(Clients!$E$5:$E$204,MATCH($B6,Clients!$A$5:$A$204,0)))),INDEX(Clients!$F$5:$F$204,MATCH($B6,Clients!$A$5:$A$204,0)),INDEX(Settings!$E$5:$E$19,MATCH($J6,Settings!$D$5:$D$19,0))),0))) -> 45 | L6: =IF($B6="","",$K6*IF($D6="",1,$D6)+$E6) -> 135 | M6: =IF($B6="","",ROUND($L6*Settings!$B$9,2)) -> 8.1 | N6: =IF($B6="","",$L6+$M6) -> 143.1 | O6: =IF($Q6="","",Settings!$B$13&TEXT(ROWS($A$5:$A6),"0000")) -> INV-0002 | P6: =IF($O6="","",IFERROR(INDEX(Invoices!$I$5:$I$504,MATCH($O6,Invoices!$A$5:$A$504,0)),"")) -> Paid | Q6: =IF(AND($A6<>"",$B6<>"",$G6="Completed"),COUNTIFS($A$5:$A6,"<>",$B$5:$B6,"<>",$G$5:$G6,"Completed"),"") -> 2
A7: 46209 | B7: Marcus & Elena Ortiz | G7: Completed | I7: =IF($B7="","",IFERROR(INDEX(Clients!$D$5:$D$204,MATCH($B7,Clients!$A$5:$A$204,0))&"","")) -> 88 Birchwood Ln, Springfield | J7: =IF($B7="","",IF($C7<>"",$C7,IFERROR(INDEX(Clients!$E$5:$E$204,MATCH($B7,Clients!$A$5:$A$204,0))&"",""))) -> Recurring Weekly | K7: =IF($B7="","",IF($F7<>"",$F7,IFERROR(IF(AND(INDEX(Clients!$F$5:$F$204,MATCH($B7,Clients!$A$5:$A$204,0))&""<>"",OR($C7="",$C7=INDEX(Clients!$E$5:$E$204,MATCH($B7,Clients!$A$5:$A$204,0)))),INDEX(Clients!$F$5:$F$204,MATCH($B7,Clients!$A$5:$A$204,0)),INDEX(Settings!$E$5:$E$19,MATCH($J7,Settings!$D$5:$D$19,0))),0))) -> 90 | L7: =IF($B7="","",$K7*IF($D7="",1,$D7)+$E7) -> 90 | M7: =IF($B7="","",ROUND($L7*Settings!$B$9,2)) -> 5.4 | N7: =IF($B7="","",$L7+$M7) -> 95.4 | O7: =IF($Q7="","",Settings!$B$13&TEXT(ROWS($A$5:$A7),"0000")) -> INV-0003 | P7: =IF($O7="","",IFERROR(INDEX(Invoices!$I$5:$I$504,MATCH($O7,Invoices!$A$5:$A$504,0)),"")) -> Paid | Q7: =IF(AND($A7<>"",$B7<>"",$G7="Completed"),COUNTIFS($A$5:$A7,"<>",$B$5:$B7,"<>",$G$5:$G7,"Completed"),"") -> 3
A8: 46211 | B8: Priya Raman | E8: 25 | G8: Completed | H8: Extra: inside fridge | I8: =IF($B8="","",IFERROR(INDEX(Clients!$D$5:$D$204,MATCH($B8,Clients!$A$5:$A$204,0))&"","")) -> 27 Lakeview Ct, Riverton | J8: =IF($B8="","",IF($C8<>"",$C8,IFERROR(INDEX(Clients!$E$5:$E$204,MATCH($B8,Clients!$A$5:$A$204,0))&"",""))) -> Deep Clean | K8: =IF($B8="","",IF($F8<>"",$F8,IFERROR(IF(AND(INDEX(Clients!$F$5:$F$204,MATCH($B8,Clients!$A$5:$A$204,0))&""<>"",OR($C8="",$C8=INDEX(Clients!$E$5:$E$204,MATCH($B8,Clients!$A$5:$A$204,0)))),INDEX(Clients!$F$5:$F$204,MATCH($B8,Clients!$A$5:$A$204,0)),INDEX(Settings!$E$5:$E$19,MATCH($J8,Settings!$D$5:$D$19,0))),0))) -> 220 | L8: =IF($B8="","",$K8*IF($D8="",1,$D8)+$E8) -> 245 | M8: =IF($B8="","",ROUND($L8*Settings!$B$9,2)) -> 14.7 | N8: =IF($B8="","",$L8+$M8) -> 259.7 | O8: =IF($Q8="","",Settings!$B$13&TEXT(ROWS($A$5:$A8),"0000")) -> INV-0004 | P8: =IF($O8="","",IFERROR(INDEX(Invoices!$I$5:$I$504,MATCH($O8,Invoices!$A$5:$A$504,0)),"")) -> Paid | Q8: =IF(AND($A8<>"",$B8<>"",$G8="Completed"),COUNTIFS($A$5:$A8,"<>",$B$5:$B8,"<>",$G$5:$G8,"Completed"),"") -> 4
A9: 46213 | B9: Brightpath Dental Office | D9: 3 | G9: Completed | I9: =IF($B9="","",IFERROR(INDEX(Clients!$D$5:$D$204,MATCH($B9,Clients!$A$5:$A$204,0))&"","")) -> 1500 Commerce Pkwy, Suite 210, Springfield | J9: =IF($B9="","",IF($C9<>"",$C9,IFERROR(INDEX(Clients!$E$5:$E$204,MATCH($B9,Clients!$A$5:$A$204,0))&"",""))) -> Office Clean (hourly) | K9: =IF($B9="","",IF($F9<>"",$F9,IFERROR(IF(AND(INDEX(Clients!$F$5:$F$204,MATCH($B9,Clients!$A$5:$A$204,0))&""<>"",OR($C9="",$C9=INDEX(Clients!$E$5:$E$204,MATCH($B9,Clients!$A$5:$A$204,0)))),INDEX(Clients!$F$5:$F$204,MATCH($B9,Clients!$A$5:$A$204,0)),INDEX(Settings!$E$5:$E$19,MATCH($J9,Settings!$D$5:$D$19,0))),0))) -> 45 | L9: =IF($B9="","",$K9*IF($D9="",1,$D9)+$E9) -> 135 | M9: =IF($B9="","",ROUND($L9*Settings!$B$9,2)) -> 8.1 | N9: =IF($B9="","",$L9+$M9) -> 143.1 | O9: =IF($Q9="","",Settings!$B$13&TEXT(ROWS($A$5:$A9),"0000")) -> INV-0005 | P9: =IF($O9="","",IFERROR(INDEX(Invoices!$I$5:$I$504,MATCH($O9,Invoices!$A$5:$A$504,0)),"")) -> Paid | Q9: =IF(AND($A9<>"",$B9<>"",$G9="Completed"),COUNTIFS($A$5:$A9,"<>",$B$5:$B9,"<>",$G$5:$G9,"Completed"),"") -> 5
A10: 46216 | B10: Marcus & Elena Ortiz | G10: Completed | I10: =IF($B10="","",IFERROR(INDEX(Clients!$D$5:$D$204,MATCH($B10,Clients!$A$5:$A$204,0))&"","")) -> 88 Birchwood Ln, Springfield | J10: =IF($B10="","",IF($C10<>"",$C10,IFERROR(INDEX(Clients!$E$5:$E$204,MATCH($B10,Clients!$A$5:$A$204,0))&"",""))) -> Recurring Weekly | K10: =IF($B10="","",IF($F10<>"",$F10,IFERROR(IF(AND(INDEX(Clients!$F$5:$F$204,MATCH($B10,Clients!$A$5:$A$204,0))&""<>"",OR($C10="",$C10=INDEX(Clients!$E$5:$E$204,MATCH($B10,Clients!$A$5:$A$204,0)))),INDEX(Clients!$F$5:$F$204,MATCH($B10,Clients!$A$5:$A$204,0)),INDEX(Settings!$E$5:$E$19,MATCH($J10,Settings!$D$5:$D$19,0))),0))) -> 90 | L10: =IF($B10="","",$K10*IF($D10="",1,$D10)+$E10) -> 90 | M10: =IF($B10="","",ROUND($L10*Settings!$B$9,2)) -> 5.4 | N10: =IF($B10="","",$L10+$M10) -> 95.4 | O10: =IF($Q10="","",Settings!$B$13&TEXT(ROWS($A$5:$A10),"0000")) -> INV-0006 | P10: =IF($O10="","",IFERROR(INDEX(Invoices!$I$5:$I$504,MATCH($O10,Invoices!$A$5:$A$504,0)),"")) -> Paid | Q10: =IF(AND($A10<>"",$B10<>"",$G10="Completed"),COUNTIFS($A$5:$A10,"<>",$B$5:$B10,"<>",$G$5:$G10,"Completed"),"") -> 6
A11: 46219 | B11: Hannah Whitfield | G11: Completed | I11: =IF($B11="","",IFERROR(INDEX(Clients!$D$5:$D$204,MATCH($B11,Clients!$A$5:$A$204,0))&"","")) -> 412 Maple Ridge Dr, Springfield | J11: =IF($B11="","",IF($C11<>"",$C11,IFERROR(INDEX(Clients!$E$5:$E$204,MATCH($B11,Clients!$A$5:$A$204,0))&"",""))) -> Recurring Every 2 Weeks | K11: =IF($B11="","",IF($F11<>"",$F11,IFERROR(IF(AND(INDEX(Clients!$F$5:$F$204,MATCH($B11,Clients!$A$5:$A$204,0))&""<>"",OR($C11="",$C11=INDEX(Clients!$E$5:$E$204,MATCH($B11,Clients!$A$5:$A$204,0)))),INDEX(Clients!$F$5:$F$204,MATCH($B11,Clients!$A$5:$A$204,0)),INDEX(Settings!$E$5:$E$19,MATCH($J11,Settings!$D$5:$D$19,0))),0))) -> 110 | L11: =IF($B11="","",$K11*IF($D11="",1,$D11)+$E11) -> 110 | M11: =IF($B11="","",ROUND($L11*Settings!$B$9,2)) -> 6.6 | N11: =IF($B11="","",$L11+$M11) -> 116.6 | O11: =IF($Q11="","",Settings!$B$13&TEXT(ROWS($A$5:$A11),"0000")) -> INV-0007 | P11: =IF($O11="","",IFERROR(INDEX(Invoices!$I$5:$I$504,MATCH($O11,Invoices!$A$5:$A$504,0)),"")) -> Paid | Q11: =IF(AND($A11<>"",$B11<>"",$G11="Completed"),COUNTIFS($A$5:$A11,"<>",$B$5:$B11,"<>",$G$5:$G11,"Completed"),"") -> 7
A12: 46223 | B12: Greenleaf Property Mgmt | G12: Completed | H12: Unit 4B move-out | I12: =IF($B12="","",IFERROR(INDEX(Clients!$D$5:$D$204,MATCH($B12,Clients!$A$5:$A$204,0))&"","")) -> 300 Harbor St, Springfield | J12: =IF($B12="","",IF($C12<>"",$C12,IFERROR(INDEX(Clients!$E$5:$E$204,MATCH($B12,Clients!$A$5:$A$204,0))&"",""))) -> Move-In / Move-Out | K12: =IF($B12="","",IF($F12<>"",$F12,IFERROR(IF(AND(INDEX(Clients!$F$5:$F$204,MATCH($B12,Clients!$A$5:$A$204,0))&""<>"",OR($C12="",$C12=INDEX(Clients!$E$5:$E$204,MATCH($B12,Clients!$A$5:$A$204,0)))),INDEX(Clients!$F$5:$F$204,MATCH($B12,Clients!$A$5:$A$204,0)),INDEX(Settings!$E$5:$E$19,MATCH($J12,Settings!$D$5:$D$19,0))),0))) -> 300 | L12: =IF($B12="","",$K12*IF($D12="",1,$D12)+$E12) -> 300 | M12: =IF($B12="","",ROUND($L12*Settings!$B$9,2)) -> 18 | N12: =IF($B12="","",$L12+$M12) -> 318 | O12: =IF($Q12="","",Settings!$B$13&TEXT(ROWS($A$5:$A12),"0000")) -> INV-0008 | P12: =IF($O12="","",IFERROR(INDEX(Invoices!$I$5:$I$504,MATCH($O12,Invoices!$A$5:$A$504,0)),"")) -> Paid | Q12: =IF(AND($A12<>"",$B12<>"",$G12="Completed"),COUNTIFS($A$5:$A12,"<>",$B$5:$B12,"<>",$G$5:$G12,"Completed"),"") -> 8
A13: 46227 | B13: Tom Kessler | G13: Completed | I13: =IF($B13="","",IFERROR(INDEX(Clients!$D$5:$D$204,MATCH($B13,Clients!$A$5:$A$204,0))&"","")) -> 9 Old Mill Rd, Riverton | J13: =IF($B13="","",IF($C13<>"",$C13,IFERROR(INDEX(Clients!$E$5:$E$204,MATCH($B13,Clients!$A$5:$A$204,0))&"",""))) -> Standard Clean | K13: =IF($B13="","",IF($F13<>"",$F13,IFERROR(IF(AND(INDEX(Clients!$F$5:$F$204,MATCH($B13,Clients!$A$5:$A$204,0))&""<>"",OR($C13="",$C13=INDEX(Clients!$E$5:$E$204,MATCH($B13,Clients!$A$5:$A$204,0)))),INDEX(Clients!$F$5:$F$204,MATCH($B13,Clients!$A$5:$A$204,0)),INDEX(Settings!$E$5:$E$19,MATCH($J13,Settings!$D$5:$D$19,0))),0))) -> 120 | L13: =IF($B13="","",$K13*IF($D13="",1,$D13)+$E13) -> 120 | M13: =IF($B13="","",ROUND($L13*Settings!$B$9,2)) -> 7.2 | N13: =IF($B13="","",$L13+$M13) -> 127.2 | O13: =IF($Q13="","",Settings!$B$13&TEXT(ROWS($A$5:$A13),"0000")) -> INV-0009 | P13: =IF($O13="","",IFERROR(INDEX(Invoices!$I$5:$I$504,MATCH($O13,Invoices!$A$5:$A$504,0)),"")) -> Overdue | Q13: =IF(AND($A13<>"",$B13<>"",$G13="Completed"),COUNTIFS($A$5:$A13,"<>",$B$5:$B13,"<>",$G$5:$G13,"Completed"),"") -> 9
A14: 46231 | B14: Riverside Yoga Studio | D14: 2.5 | G14: Completed | I14: =IF($B14="","",IFERROR(INDEX(Clients!$D$5:$D$204,MATCH($B14,Clients!$A$5:$A$204,0))&"","")) -> 55 River Rd, Riverton | J14: =IF($B14="","",IF($C14<>"",$C14,IFERROR(INDEX(Clients!$E$5:$E$204,MATCH($B14,Clients!$A$5:$A$204,0))&"",""))) -> Office Clean (hourly) | K14: =IF($B14="","",IF($F14<>"",$F14,IFERROR(IF(AND(INDEX(Clients!$F$5:$F$204,MATCH($B14,Clients!$A$5:$A$204,0))&""<>"",OR($C14="",$C14=INDEX(Clients!$E$5:$E$204,MATCH($B14,Clients!$A$5:$A$204,0)))),INDEX(Clients!$F$5:$F$204,MATCH($B14,Clients!$A$5:$A$204,0)),INDEX(Settings!$E$5:$E$19,MATCH($J14,Settings!$D$5:$D$19,0))),0))) -> 40 | L14: =IF($B14="","",$K14*IF($D14="",1,$D14)+$E14) -> 100 | M14: =IF($B14="","",ROUND($L14*Settings!$B$9,2)) -> 6 | N14: =IF($B14="","",$L14+$M14) -> 106 | O14: =IF($Q14="","",Settings!$B$13&TEXT(ROWS($A$5:$A14),"0000")) -> INV-0010 | P14: =IF($O14="","",IFERROR(INDEX(Invoices!$I$5:$I$504,MATCH($O14,Invoices!$A$5:$A$504,0)),"")) -> Paid | Q14: =IF(AND($A14<>"",$B14<>"",$G14="Completed"),COUNTIFS($A$5:$A14,"<>",$B$5:$B14,"<>",$G$5:$G14,"Completed"),"") -> 10
A15: 46237 | B15: Marcus & Elena Ortiz | G15: Completed | I15: =IF($B15="","",IFERROR(INDEX(Clients!$D$5:$D$204,MATCH($B15,Clients!$A$5:$A$204,0))&"","")) -> 88 Birchwood Ln, Springfield | J15: =IF($B15="","",IF($C15<>"",$C15,IFERROR(INDEX(Clients!$E$5:$E$204,MATCH($B15,Clients!$A$5:$A$204,0))&"",""))) -> Recurring Weekly | K15: =IF($B15="","",IF($F15<>"",$F15,IFERROR(IF(AND(INDEX(Clients!$F$5:$F$204,MATCH($B15,Clients!$A$5:$A$204,0))&""<>"",OR($C15="",$C15=INDEX(Clients!$E$5:$E$204,MATCH($B15,Clients!$A$5:$A$204,0)))),INDEX(Clients!$F$5:$F$204,MATCH($B15,Clients!$A$5:$A$204,0)),INDEX(Settings!$E$5:$E$19,MATCH($J15,Settings!$D$5:$D$19,0))),0))) -> 90 | L15: =IF($B15="","",$K15*IF($D15="",1,$D15)+$E15) -> 90 | M15: =IF($B15="","",ROUND($L15*Settings!$B$9,2)) -> 5.4 | N15: =IF($B15="","",$L15+$M15) -> 95.4 | O15: =IF($Q15="","",Settings!$B$13&TEXT(ROWS($A$5:$A15),"0000")) -> INV-0011 | P15: =IF($O15="","",IFERROR(INDEX(Invoices!$I$5:$I$504,MATCH($O15,Invoices!$A$5:$A$504,0)),"")) -> Paid | Q15: =IF(AND($A15<>"",$B15<>"",$G15="Completed"),COUNTIFS($A$5:$A15,"<>",$B$5:$B15,"<>",$G$5:$G15,"Completed"),"") -> 11
A16: 46238 | B16: Riverside Yoga Studio | D16: 2.5 | G16: Completed | I16: =IF($B16="","",IFERROR(INDEX(Clients!$D$5:$D$204,MATCH($B16,Clients!$A$5:$A$204,0))&"","")) -> 55 River Rd, Riverton | J16: =IF($B16="","",IF($C16<>"",$C16,IFERROR(INDEX(Clients!$E$5:$E$204,MATCH($B16,Clients!$A$5:$A$204,0))&"",""))) -> Office Clean (hourly) | K16: =IF($B16="","",IF($F16<>"",$F16,IFERROR(IF(AND(INDEX(Clients!$F$5:$F$204,MATCH($B16,Clients!$A$5:$A$204,0))&""<>"",OR($C16="",$C16=INDEX(Clients!$E$5:$E$204,MATCH($B16,Clients!$A$5:$A$204,0)))),INDEX(Clients!$F$5:$F$204,MATCH($B16,Clients!$A$5:$A$204,0)),INDEX(Settings!$E$5:$E$19,MATCH($J16,Settings!$D$5:$D$19,0))),0))) -> 40 | L16: =IF($B16="","",$K16*IF($D16="",1,$D16)+$E16) -> 100 | M16: =IF($B16="","",ROUND($L16*Settings!$B$9,2)) -> 6 | N16: =IF($B16="","",$L16+$M16) -> 106 | O16: =IF($Q16="","",Settings!$B$13&TEXT(ROWS($A$5:$A16),"0000")) -> INV-0012 | P16: =IF($O16="","",IFERROR(INDEX(Invoices!$I$5:$I$504,MATCH($O16,Invoices!$A$5:$A$504,0)),"")) -> Paid | Q16: =IF(AND($A16<>"",$B16<>"",$G16="Completed"),COUNTIFS($A$5:$A16,"<>",$B$5:$B16,"<>",$G$5:$G16,"Completed"),"") -> 12
A17: 46240 | B17: Danielle Brooks | C17: Deep Clean | G17: Completed | H17: First visit - deep clean | I17: =IF($B17="","",IFERROR(INDEX(Clients!$D$5:$D$204,MATCH($B17,Clients!$A$5:$A$204,0))&"","")) -> 1742 Sunset Ave, Springfield | J17: =IF($B17="","",IF($C17<>"",$C17,IFERROR(INDEX(Clients!$E$5:$E$204,MATCH($B17,Clients!$A$5:$A$204,0))&"",""))) -> Deep Clean | K17: =IF($B17="","",IF($F17<>"",$F17,IFERROR(IF(AND(INDEX(Clients!$F$5:$F$204,MATCH($B17,Clients!$A$5:$A$204,0))&""<>"",OR($C17="",$C17=INDEX(Clients!$E$5:$E$204,MATCH($B17,Clients!$A$5:$A$204,0)))),INDEX(Clients!$F$5:$F$204,MATCH($B17,Clients!$A$5:$A$204,0)),INDEX(Settings!$E$5:$E$19,MATCH($J17,Settings!$D$5:$D$19,0))),0))) -> 220 | L17: =IF($B17="","",$K17*IF($D17="",1,$D17)+$E17) -> 220 | M17: =IF($B17="","",ROUND($L17*Settings!$B$9,2)) -> 13.2 | N17: =IF($B17="","",$L17+$M17) -> 233.2 | O17: =IF($Q17="","",Settings!$B$13&TEXT(ROWS($A$5:$A17),"0000")) -> INV-0013 | P17: =IF($O17="","",IFERROR(INDEX(Invoices!$I$5:$I$504,MATCH($O17,Invoices!$A$5:$A$504,0)),"")) -> Paid | Q17: =IF(AND($A17<>"",$B17<>"",$G17="Completed"),COUNTIFS($A$5:$A17,"<>",$B$5:$B17,"<>",$G$5:$G17,"Completed"),"") -> 13
A18: 46241 | B18: Brightpath Dental Office | D18: 3 | G18: Completed | I18: =IF($B18="","",IFERROR(INDEX(Clients!$D$5:$D$204,MATCH($B18,Clients!$A$5:$A$204,0))&"","")) -> 1500 Commerce Pkwy, Suite 210, Springfield | J18: =IF($B18="","",IF($C18<>"",$C18,IFERROR(INDEX(Clients!$E$5:$E$204,MATCH($B18,Clients!$A$5:$A$204,0))&"",""))) -> Office Clean (hourly) | K18: =IF($B18="","",IF($F18<>"",$F18,IFERROR(IF(AND(INDEX(Clients!$F$5:$F$204,MATCH($B18,Clients!$A$5:$A$204,0))&""<>"",OR($C18="",$C18=INDEX(Clients!$E$5:$E$204,MATCH($B18,Clients!$A$5:$A$204,0)))),INDEX(Clients!$F$5:$F$204,MATCH($B18,Clients!$A$5:$A$204,0)),INDEX(Settings!$E$5:$E$19,MATCH($J18,Settings!$D$5:$D$19,0))),0))) -> 45 | L18: =IF($B18="","",$K18*IF($D18="",1,$D18)+$E18) -> 135 | M18: =IF($B18="","",ROUND($L18*Settings!$B$9,2)) -> 8.1 | N18: =IF($B18="","",$L18+$M18) -> 143.1 | O18: =IF($Q18="","",Settings!$B$13&TEXT(ROWS($A$5:$A18),"0000")) -> INV-0014 | P18: =IF($O18="","",IFERROR(INDEX(Invoices!$I$5:$I$504,MATCH($O18,Invoices!$A$5:$A$504,0)),"")) -> Paid | Q18: =IF(AND($A18<>"",$B18<>"",$G18="Completed"),COUNTIFS($A$5:$A18,"<>",$B$5:$B18,"<>",$G$5:$G18,"Completed"),"") -> 14
A19: 46244 | B19: Marcus & Elena Ortiz | G19: Completed | I19: =IF($B19="","",IFERROR(INDEX(Clients!$D$5:$D$204,MATCH($B19,Clients!$A$5:$A$204,0))&"","")) -> 88 Birchwood Ln, Springfield | J19: =IF($B19="","",IF($C19<>"",$C19,IFERROR(INDEX(Clients!$E$5:$E$204,MATCH($B19,Clients!$A$5:$A$204,0))&"",""))) -> Recurring Weekly | K19: =IF($B19="","",IF($F19<>"",$F19,IFERROR(IF(AND(INDEX(Clients!$F$5:$F$204,MATCH($B19,Clients!$A$5:$A$204,0))&""<>"",OR($C19="",$C19=INDEX(Clients!$E$5:$E$204,MATCH($B19,Clients!$A$5:$A$204,0)))),INDEX(Clients!$F$5:$F$204,MATCH($B19,Clients!$A$5:$A$204,0)),INDEX(Settings!$E$5:$E$19,MATCH($J19,Settings!$D$5:$D$19,0))),0))) -> 90 | L19: =IF($B19="","",$K19*IF($D19="",1,$D19)+$E19) -> 90 | M19: =IF($B19="","",ROUND($L19*Settings!$B$9,2)) -> 5.4 | N19: =IF($B19="","",$L19+$M19) -> 95.4 | O19: =IF($Q19="","",Settings!$B$13&TEXT(ROWS($A$5:$A19),"0000")) -> INV-0015 | P19: =IF($O19="","",IFERROR(INDEX(Invoices!$I$5:$I$504,MATCH($O19,Invoices!$A$5:$A$504,0)),"")) -> Paid | Q19: =IF(AND($A19<>"",$B19<>"",$G19="Completed"),COUNTIFS($A$5:$A19,"<>",$B$5:$B19,"<>",$G$5:$G19,"Completed"),"") -> 15
A20: 46247 | B20: Hannah Whitfield | G20: Completed | I20: =IF($B20="","",IFERROR(INDEX(Clients!$D$5:$D$204,MATCH($B20,Clients!$A$5:$A$204,0))&"","")) -> 412 Maple Ridge Dr, Springfield | J20: =IF($B20="","",IF($C20<>"",$C20,IFERROR(INDEX(Clients!$E$5:$E$204,MATCH($B20,Clients!$A$5:$A$204,0))&"",""))) -> Recurring Every 2 Weeks | K20: =IF($B20="","",IF($F20<>"",$F20,IFERROR(IF(AND(INDEX(Clients!$F$5:$F$204,MATCH($B20,Clients!$A$5:$A$204,0))&""<>"",OR($C20="",$C20=INDEX(Clients!$E$5:$E$204,MATCH($B20,Clients!$A$5:$A$204,0)))),INDEX(Clients!$F$5:$F$204,MATCH($B20,Clients!$A$5:$A$204,0)),INDEX(Settings!$E$5:$E$19,MATCH($J20,Settings!$D$5:$D$19,0))),0))) -> 110 | L20: =IF($B20="","",$K20*IF($D20="",1,$D20)+$E20) -> 110 | M20: =IF($B20="","",ROUND($L20*Settings!$B$9,2)) -> 6.6 | N20: =IF($B20="","",$L20+$M20) -> 116.6 | O20: =IF($Q20="","",Settings!$B$13&TEXT(ROWS($A$5:$A20),"0000")) -> INV-0016 | P20: =IF($O20="","",IFERROR(INDEX(Invoices!$I$5:$I$504,MATCH($O20,Invoices!$A$5:$A$504,0)),"")) -> Paid | Q20: =IF(AND($A20<>"",$B20<>"",$G20="Completed"),COUNTIFS($A$5:$A20,"<>",$B$5:$B20,"<>",$G$5:$G20,"Completed"),"") -> 16
A21: 46248 | B21: Greenleaf Property Mgmt | C21: Move-In / Move-Out | E21: 40 | G21: Completed | H21: Unit 2A move-in. Extra: carpet spot treatment | I21: =IF($B21="","",IFERROR(INDEX(Clients!$D$5:$D$204,MATCH($B21,Clients!$A$5:$A$204,0))&"","")) -> 300 Harbor St, Springfield | J21: =IF($B21="","",IF($C21<>"",$C21,IFERROR(INDEX(Clients!$E$5:$E$204,MATCH($B21,Clients!$A$5:$A$204,0))&"",""))) -> Move-In / Move-Out | K21: =IF($B21="","",IF($F21<>"",$F21,IFERROR(IF(AND(INDEX(Clients!$F$5:$F$204,MATCH($B21,Clients!$A$5:$A$204,0))&""<>"",OR($C21="",$C21=INDEX(Clients!$E$5:$E$204,MATCH($B21,Clients!$A$5:$A$204,0)))),INDEX(Clients!$F$5:$F$204,MATCH($B21,Clients!$A$5:$A$204,0)),INDEX(Settings!$E$5:$E$19,MATCH($J21,Settings!$D$5:$D$19,0))),0))) -> 300 | L21: =IF($B21="","",$K21*IF($D21="",1,$D21)+$E21) -> 340 | M21: =IF($B21="","",ROUND($L21*Settings!$B$9,2)) -> 20.4 | N21: =IF($B21="","",$L21+$M21) -> 360.4 | O21: =IF($Q21="","",Settings!$B$13&TEXT(ROWS($A$5:$A21),"0000")) -> INV-0017 | P21: =IF($O21="","",IFERROR(INDEX(Invoices!$I$5:$I$504,MATCH($O21,Invoices!$A$5:$A$504,0)),"")) -> Overdue | Q21: =IF(AND($A21<>"",$B21<>"",$G21="Completed"),COUNTIFS($A$5:$A21,"<>",$B$5:$B21,"<>",$G$5:$G21,"Completed"),"") -> 17
A22: 46252 | B22: Priya Raman | C22: Standard Clean | G22: Completed | H22: Lighter clean this month | I22: =IF($B22="","",IFERROR(INDEX(Clients!$D$5:$D$204,MATCH($B22,Clients!$A$5:$A$204,0))&"","")) -> 27 Lakeview Ct, Riverton | J22: =IF($B22="","",IF($C22<>"",$C22,IFERROR(INDEX(Clients!$E$5:$E$204,MATCH($B22,Clients!$A$5:$A$204,0))&"",""))) -> Standard Clean | K22: =IF($B22="","",IF($F22<>"",$F22,IFERROR(IF(AND(INDEX(Clients!$F$5:$F$204,MATCH($B22,Clients!$A$5:$A$204,0))&""<>"",OR($C22="",$C22=INDEX(Clients!$E$5:$E$204,MATCH($B22,Clients!$A$5:$A$204,0)))),INDEX(Clients!$F$5:$F$204,MATCH($B22,Clients!$A$5:$A$204,0)),INDEX(Settings!$E$5:$E$19,MATCH($J22,Settings!$D$5:$D$19,0))),0))) -> 120 | L22: =IF($B22="","",$K22*IF($D22="",1,$D22)+$E22) -> 120 | M22: =IF($B22="","",ROUND($L22*Settings!$B$9,2)) -> 7.2 | N22: =IF($B22="","",$L22+$M22) -> 127.2 | O22: =IF($Q22="","",Settings!$B$13&TEXT(ROWS($A$5:$A22),"0000")) -> INV-0018 | P22: =IF($O22="","",IFERROR(INDEX(Invoices!$I$5:$I$504,MATCH($O22,Invoices!$A$5:$A$504,0)),"")) -> Paid | Q22: =IF(AND($A22<>"",$B22<>"",$G22="Completed"),COUNTIFS($A$5:$A22,"<>",$B$5:$B22,"<>",$G$5:$G22,"Completed"),"") -> 18
A23: 46255 | B23: Tom Kessler | G23: Cancelled | H23: Client rescheduled | I23: =IF($B23="","",IFERROR(INDEX(Clients!$D$5:$D$204,MATCH($B23,Clients!$A$5:$A$204,0))&"","")) -> 9 Old Mill Rd, Riverton | J23: =IF($B23="","",IF($C23<>"",$C23,IFERROR(INDEX(Clients!$E$5:$E$204,MATCH($B23,Clients!$A$5:$A$204,0))&"",""))) -> Standard Clean | K23: =IF($B23="","",IF($F23<>"",$F23,IFERROR(IF(AND(INDEX(Clients!$F$5:$F$204,MATCH($B23,Clients!$A$5:$A$204,0))&""<>"",OR($C23="",$C23=INDEX(Clients!$E$5:$E$204,MATCH($B23,Clients!$A$5:$A$204,0)))),INDEX(Clients!$F$5:$F$204,MATCH($B23,Clients!$A$5:$A$204,0)),INDEX(Settings!$E$5:$E$19,MATCH($J23,Settings!$D$5:$D$19,0))),0))) -> 120 | L23: =IF($B23="","",$K23*IF($D23="",1,$D23)+$E23) -> 120 | M23: =IF($B23="","",ROUND($L23*Settings!$B$9,2)) -> 7.2 | N23: =IF($B23="","",$L23+$M23) -> 127.2 | O23: =IF($Q23="","",Settings!$B$13&TEXT(ROWS($A$5:$A23),"0000")) | P23: =IF($O23="","",IFERROR(INDEX(Invoices!$I$5:$I$504,MATCH($O23,Invoices!$A$5:$A$504,0)),"")) | Q23: =IF(AND($A23<>"",$B23<>"",$G23="Completed"),COUNTIFS($A$5:$A23,"<>",$B$5:$B23,"<>",$G$5:$G23,"Completed"),"")
A24: 46261 | B24: Danielle Brooks | G24: Completed | I24: =IF($B24="","",IFERROR(INDEX(Clients!$D$5:$D$204,MATCH($B24,Clients!$A$5:$A$204,0))&"","")) -> 1742 Sunset Ave, Springfield | J24: =IF($B24="","",IF($C24<>"",$C24,IFERROR(INDEX(Clients!$E$5:$E$204,MATCH($B24,Clients!$A$5:$A$204,0))&"",""))) -> Standard Clean | K24: =IF($B24="","",IF($F24<>"",$F24,IFERROR(IF(AND(INDEX(Clients!$F$5:$F$204,MATCH($B24,Clients!$A$5:$A$204,0))&""<>"",OR($C24="",$C24=INDEX(Clients!$E$5:$E$204,MATCH($B24,Clients!$A$5:$A$204,0)))),INDEX(Clients!$F$5:$F$204,MATCH($B24,Clients!$A$5:$A$204,0)),INDEX(Settings!$E$5:$E$19,MATCH($J24,Settings!$D$5:$D$19,0))),0))) -> 120 | L24: =IF($B24="","",$K24*IF($D24="",1,$D24)+$E24) -> 120 | M24: =IF($B24="","",ROUND($L24*Settings!$B$9,2)) -> 7.2 | N24: =IF($B24="","",$L24+$M24) -> 127.2 | O24: =IF($Q24="","",Settings!$B$13&TEXT(ROWS($A$5:$A24),"0000")) -> INV-0020 | P24: =IF($O24="","",IFERROR(INDEX(Invoices!$I$5:$I$504,MATCH($O24,Invoices!$A$5:$A$504,0)),"")) -> Paid | Q24: =IF(AND($A24<>"",$B24<>"",$G24="Completed"),COUNTIFS($A$5:$A24,"<>",$B$5:$B24,"<>",$G$5:$G24,"Completed"),"") -> 19
A25: 46266 | B25: Marcus & Elena Ortiz | G25: Completed | I25: =IF($B25="","",IFERROR(INDEX(Clients!$D$5:$D$204,MATCH($B25,Clients!$A$5:$A$204,0))&"","")) -> 88 Birchwood Ln, Springfield | J25: =IF($B25="","",IF($C25<>"",$C25,IFERROR(INDEX(Clients!$E$5:$E$204,MATCH($B25,Clients!$A$5:$A$204,0))&"",""))) -> Recurring Weekly | K25: =IF($B25="","",IF($F25<>"",$F25,IFERROR(IF(AND(INDEX(Clients!$F$5:$F$204,MATCH($B25,Clients!$A$5:$A$204,0))&""<>"",OR($C25="",$C25=INDEX(Clients!$E$5:$E$204,MATCH($B25,Clients!$A$5:$A$204,0)))),INDEX(Clients!$F$5:$F$204,MATCH($B25,Clients!$A$5:$A$204,0)),INDEX(Settings!$E$5:$E$19,MATCH($J25,Settings!$D$5:$D$19,0))),0))) -> 90 | L25: =IF($B25="","",$K25*IF($D25="",1,$D25)+$E25) -> 90 | M25: =IF($B25="","",ROUND($L25*Settings!$B$9,2)) -> 5.4 | N25: =IF($B25="","",$L25+$M25) -> 95.4 | O25: =IF($Q25="","",Settings!$B$13&TEXT(ROWS($A$5:$A25),"0000")) -> INV-0021 | P25: =IF($O25="","",IFERROR(INDEX(Invoices!$I$5:$I$504,MATCH($O25,Invoices!$A$5:$A$504,0)),"")) -> Paid | Q25: =IF(AND($A25<>"",$B25<>"",$G25="Completed"),COUNTIFS($A$5:$A25,"<>",$B$5:$B25,"<>",$G$5:$G25,"Completed"),"") -> 20
A26: 46268 | B26: Brightpath Dental Office | D26: 3.5 | G26: Completed | I26: =IF($B26="","",IFERROR(INDEX(Clients!$D$5:$D$204,MATCH($B26,Clients!$A$5:$A$204,0))&"","")) -> 1500 Commerce Pkwy, Suite 210, Springfield | J26: =IF($B26="","",IF($C26<>"",$C26,IFERROR(INDEX(Clients!$E$5:$E$204,MATCH($B26,Clients!$A$5:$A$204,0))&"",""))) -> Office Clean (hourly) | K26: =IF($B26="","",IF($F26<>"",$F26,IFERROR(IF(AND(INDEX(Clients!$F$5:$F$204,MATCH($B26,Clients!$A$5:$A$204,0))&""<>"",OR($C26="",$C26=INDEX(Clients!$E$5:$E$204,MATCH($B26,Clients!$A$5:$A$204,0)))),INDEX(Clients!$F$5:$F$204,MATCH($B26,Clients!$A$5:$A$204,0)),INDEX(Settings!$E$5:$E$19,MATCH($J26,Settings!$D$5:$D$19,0))),0))) -> 45 | L26: =IF($B26="","",$K26*IF($D26="",1,$D26)+$E26) -> 157.5 | M26: =IF($B26="","",ROUND($L26*Settings!$B$9,2)) -> 9.45 | N26: =IF($B26="","",$L26+$M26) -> 166.95 | O26: =IF($Q26="","",Settings!$B$13&TEXT(ROWS($A$5:$A26),"0000")) -> INV-0022 | P26: =IF($O26="","",IFERROR(INDEX(Invoices!$I$5:$I$504,MATCH($O26,Invoices!$A$5:$A$504,0)),"")) -> Paid | Q26: =IF(AND($A26<>"",$B26<>"",$G26="Completed"),COUNTIFS($A$5:$A26,"<>",$B$5:$B26,"<>",$G$5:$G26,"Completed"),"") -> 21
A27: 46273 | B27: Hannah Whitfield | G27: Completed | I27: =IF($B27="","",IFERROR(INDEX(Clients!$D$5:$D$204,MATCH($B27,Clients!$A$5:$A$204,0))&"","")) -> 412 Maple Ridge Dr, Springfield | J27: =IF($B27="","",IF($C27<>"",$C27,IFERROR(INDEX(Clients!$E$5:$E$204,MATCH($B27,Clients!$A$5:$A$204,0))&"",""))) -> Recurring Every 2 Weeks | K27: =IF($B27="","",IF($F27<>"",$F27,IFERROR(IF(AND(INDEX(Clients!$F$5:$F$204,MATCH($B27,Clients!$A$5:$A$204,0))&""<>"",OR($C27="",$C27=INDEX(Clients!$E$5:$E$204,MATCH($B27,Clients!$A$5:$A$204,0)))),INDEX(Clients!$F$5:$F$204,MATCH($B27,Clients!$A$5:$A$204,0)),INDEX(Settings!$E$5:$E$19,MATCH($J27,Settings!$D$5:$D$19,0))),0))) -> 110 | L27: =IF($B27="","",$K27*IF($D27="",1,$D27)+$E27) -> 110 | M27: =IF($B27="","",ROUND($L27*Settings!$B$9,2)) -> 6.6 | N27: =IF($B27="","",$L27+$M27) -> 116.6 | O27: =IF($Q27="","",Settings!$B$13&TEXT(ROWS($A$5:$A27),"0000")) -> INV-0023 | P27: =IF($O27="","",IFERROR(INDEX(Invoices!$I$5:$I$504,MATCH($O27,Invoices!$A$5:$A$504,0)),"")) -> Paid | Q27: =IF(AND($A27<>"",$B27<>"",$G27="Completed"),COUNTIFS($A$5:$A27,"<>",$B$5:$B27,"<>",$G$5:$G27,"Completed"),"") -> 22
A28: 46275 | B28: Riverside Yoga Studio | D28: 2.5 | G28: Completed | I28: =IF($B28="","",IFERROR(INDEX(Clients!$D$5:$D$204,MATCH($B28,Clients!$A$5:$A$204,0))&"","")) -> 55 River Rd, Riverton | J28: =IF($B28="","",IF($C28<>"",$C28,IFERROR(INDEX(Clients!$E$5:$E$204,MATCH($B28,Clients!$A$5:$A$204,0))&"",""))) -> Office Clean (hourly) | K28: =IF($B28="","",IF($F28<>"",$F28,IFERROR(IF(AND(INDEX(Clients!$F$5:$F$204,MATCH($B28,Clients!$A$5:$A$204,0))&""<>"",OR($C28="",$C28=INDEX(Clients!$E$5:$E$204,MATCH($B28,Clients!$A$5:$A$204,0)))),INDEX(Clients!$F$5:$F$204,MATCH($B28,Clients!$A$5:$A$204,0)),INDEX(Settings!$E$5:$E$19,MATCH($J28,Settings!$D$5:$D$19,0))),0))) -> 40 | L28: =IF($B28="","",$K28*IF($D28="",1,$D28)+$E28) -> 100 | M28: =IF($B28="","",ROUND($L28*Settings!$B$9,2)) -> 6 | N28: =IF($B28="","",$L28+$M28) -> 106 | O28: =IF($Q28="","",Settings!$B$13&TEXT(ROWS($A$5:$A28),"0000")) -> INV-0024 | P28: =IF($O28="","",IFERROR(INDEX(Invoices!$I$5:$I$504,MATCH($O28,Invoices!$A$5:$A$504,0)),"")) -> Paid | Q28: =IF(AND($A28<>"",$B28<>"",$G28="Completed"),COUNTIFS($A$5:$A28,"<>",$B$5:$B28,"<>",$G$5:$G28,"Completed"),"") -> 23
A29: 46277 | B29: Greenleaf Property Mgmt | G29: Completed | H29: Unit 7C move-out | I29: =IF($B29="","",IFERROR(INDEX(Clients!$D$5:$D$204,MATCH($B29,Clients!$A$5:$A$204,0))&"","")) -> 300 Harbor St, Springfield | J29: =IF($B29="","",IF($C29<>"",$C29,IFERROR(INDEX(Clients!$E$5:$E$204,MATCH($B29,Clients!$A$5:$A$204,0))&"",""))) -> Move-In / Move-Out | K29: =IF($B29="","",IF($F29<>"",$F29,IFERROR(IF(AND(INDEX(Clients!$F$5:$F$204,MATCH($B29,Clients!$A$5:$A$204,0))&""<>"",OR($C29="",$C29=INDEX(Clients!$E$5:$E$204,MATCH($B29,Clients!$A$5:$A$204,0)))),INDEX(Clients!$F$5:$F$204,MATCH($B29,Clients!$A$5:$A$204,0)),INDEX(Settings!$E$5:$E$19,MATCH($J29,Settings!$D$5:$D$19,0))),0))) -> 300 | L29: =IF($B29="","",$K29*IF($D29="",1,$D29)+$E29) -> 300 | M29: =IF($B29="","",ROUND($L29*Settings!$B$9,2)) -> 18 | N29: =IF($B29="","",$L29+$M29) -> 318 | O29: =IF($Q29="","",Settings!$B$13&TEXT(ROWS($A$5:$A29),"0000")) -> INV-0025 | P29: =IF($O29="","",IFERROR(INDEX(Invoices!$I$5:$I$504,MATCH($O29,Invoices!$A$5:$A$504,0)),"")) -> Overdue | Q29: =IF(AND($A29<>"",$B29<>"",$G29="Completed"),COUNTIFS($A$5:$A29,"<>",$B$5:$B29,"<>",$G$5:$G29,"Completed"),"") -> 24
A30: 46280 | B30: Priya Raman | G30: Completed | I30: =IF($B30="","",IFERROR(INDEX(Clients!$D$5:$D$204,MATCH($B30,Clients!$A$5:$A$204,0))&"","")) -> 27 Lakeview Ct, Riverton | J30: =IF($B30="","",IF($C30<>"",$C30,IFERROR(INDEX(Clients!$E$5:$E$204,MATCH($B30,Clients!$A$5:$A$204,0))&"",""))) -> Deep Clean | K30: =IF($B30="","",IF($F30<>"",$F30,IFERROR(IF(AND(INDEX(Clients!$F$5:$F$204,MATCH($B30,Clients!$A$5:$A$204,0))&""<>"",OR($C30="",$C30=INDEX(Clients!$E$5:$E$204,MATCH($B30,Clients!$A$5:$A$204,0)))),INDEX(Clients!$F$5:$F$204,MATCH($B30,Clients!$A$5:$A$204,0)),INDEX(Settings!$E$5:$E$19,MATCH($J30,Settings!$D$5:$D$19,0))),0))) -> 220 | L30: =IF($B30="","",$K30*IF($D30="",1,$D30)+$E30) -> 220 | M30: =IF($B30="","",ROUND($L30*Settings!$B$9,2)) -> 13.2 | N30: =IF($B30="","",$L30+$M30) -> 233.2 | O30: =IF($Q30="","",Settings!$B$13&TEXT(ROWS($A$5:$A30),"0000")) -> INV-0026 | P30: =IF($O30="","",IFERROR(INDEX(Invoices!$I$5:$I$504,MATCH($O30,Invoices!$A$5:$A$504,0)),"")) -> Overdue | Q30: =IF(AND($A30<>"",$B30<>"",$G30="Completed"),COUNTIFS($A$5:$A30,"<>",$B$5:$B30,"<>",$G$5:$G30,"Completed"),"") -> 25
A31: 46282 | B31: Tom Kessler | C31: Window Cleaning | F31: 95 | G31: Completed | H31: Second-story windows | I31: =IF($B31="","",IFERROR(INDEX(Clients!$D$5:$D$204,MATCH($B31,Clients!$A$5:$A$204,0))&"","")) -> 9 Old Mill Rd, Riverton | J31: =IF($B31="","",IF($C31<>"",$C31,IFERROR(INDEX(Clients!$E$5:$E$204,MATCH($B31,Clients!$A$5:$A$204,0))&"",""))) -> Window Cleaning | K31: =IF($B31="","",IF($F31<>"",$F31,IFERROR(IF(AND(INDEX(Clients!$F$5:$F$204,MATCH($B31,Clients!$A$5:$A$204,0))&""<>"",OR($C31="",$C31=INDEX(Clients!$E$5:$E$204,MATCH($B31,Clients!$A$5:$A$204,0)))),INDEX(Clients!$F$5:$F$204,MATCH($B31,Clients!$A$5:$A$204,0)),INDEX(Settings!$E$5:$E$19,MATCH($J31,Settings!$D$5:$D$19,0))),0))) -> 95 | L31: =IF($B31="","",$K31*IF($D31="",1,$D31)+$E31) -> 95 | M31: =IF($B31="","",ROUND($L31*Settings!$B$9,2)) -> 5.7 | N31: =IF($B31="","",$L31+$M31) -> 100.7 | O31: =IF($Q31="","",Settings!$B$13&TEXT(ROWS($A$5:$A31),"0000")) -> INV-0027 | P31: =IF($O31="","",IFERROR(INDEX(Invoices!$I$5:$I$504,MATCH($O31,Invoices!$A$5:$A$504,0)),"")) -> Overdue | Q31: =IF(AND($A31<>"",$B31<>"",$G31="Completed"),COUNTIFS($A$5:$A31,"<>",$B$5:$B31,"<>",$G$5:$G31,"Completed"),"") -> 26
A32: 46287 | B32: Hannah Whitfield | G32: Completed | I32: =IF($B32="","",IFERROR(INDEX(Clients!$D$5:$D$204,MATCH($B32,Clients!$A$5:$A$204,0))&"","")) -> 412 Maple Ridge Dr, Springfield | J32: =IF($B32="","",IF($C32<>"",$C32,IFERROR(INDEX(Clients!$E$5:$E$204,MATCH($B32,Clients!$A$5:$A$204,0))&"",""))) -> Recurring Every 2 Weeks | K32: =IF($B32="","",IF($F32<>"",$F32,IFERROR(IF(AND(INDEX(Clients!$F$5:$F$204,MATCH($B32,Clients!$A$5:$A$204,0))&""<>"",OR($C32="",$C32=INDEX(Clients!$E$5:$E$204,MATCH($B32,Clients!$A$5:$A$204,0)))),INDEX(Clients!$F$5:$F$204,MATCH($B32,Clients!$A$5:$A$204,0)),INDEX(Settings!$E$5:$E$19,MATCH($J32,Settings!$D$5:$D$19,0))),0))) -> 110 | L32: =IF($B32="","",$K32*IF($D32="",1,$D32)+$E32) -> 110 | M32: =IF($B32="","",ROUND($L32*Settings!$B$9,2)) -> 6.6 | N32: =IF($B32="","",$L32+$M32) -> 116.6 | O32: =IF($Q32="","",Settings!$B$13&TEXT(ROWS($A$5:$A32),"0000")) -> INV-0028 | P32: =IF($O32="","",IFERROR(INDEX(Invoices!$I$5:$I$504,MATCH($O32,Invoices!$A$5:$A$504,0)),"")) -> Unpaid | Q32: =IF(AND($A32<>"",$B32<>"",$G32="Completed"),COUNTIFS($A$5:$A32,"<>",$B$5:$B32,"<>",$G$5:$G32,"Completed"),"") -> 27
A33: 46294 | B33: Marcus & Elena Ortiz | G33: Scheduled | I33: =IF($B33="","",IFERROR(INDEX(Clients!$D$5:$D$204,MATCH($B33,Clients!$A$5:$A$204,0))&"","")) -> 88 Birchwood Ln, Springfield | J33: =IF($B33="","",IF($C33<>"",$C33,IFERROR(INDEX(Clients!$E$5:$E$204,MATCH($B33,Clients!$A$5:$A$204,0))&"",""))) -> Recurring Weekly | K33: =IF($B33="","",IF($F33<>"",$F33,IFERROR(IF(AND(INDEX(Clients!$F$5:$F$204,MATCH($B33,Clients!$A$5:$A$204,0))&""<>"",OR($C33="",$C33=INDEX(Clients!$E$5:$E$204,MATCH($B33,Clients!$A$5:$A$204,0)))),INDEX(Clients!$F$5:$F$204,MATCH($B33,Clients!$A$5:$A$204,0)),INDEX(Settings!$E$5:$E$19,MATCH($J33,Settings!$D$5:$D$19,0))),0))) -> 90 | L33: =IF($B33="","",$K33*IF($D33="",1,$D33)+$E33) -> 90 | M33: =IF($B33="","",ROUND($L33*Settings!$B$9,2)) -> 5.4 | N33: =IF($B33="","",$L33+$M33) -> 95.4 | O33: =IF($Q33="","",Settings!$B$13&TEXT(ROWS($A$5:$A33),"0000")) | P33: =IF($O33="","",IFERROR(INDEX(Invoices!$I$5:$I$504,MATCH($O33,Invoices!$A$5:$A$504,0)),"")) | Q33: =IF(AND($A33<>"",$B33<>"",$G33="Completed"),COUNTIFS($A$5:$A33,"<>",$B$5:$B33,"<>",$G$5:$G33,"Completed"),"")
A34: 46295 | B34: Danielle Brooks | G34: Scheduled | I34: =IF($B34="","",IFERROR(INDEX(Clients!$D$5:$D$204,MATCH($B34,Clients!$A$5:$A$204,0))&"","")) -> 1742 Sunset Ave, Springfield | J34: =IF($B34="","",IF($C34<>"",$C34,IFERROR(INDEX(Clients!$E$5:$E$204,MATCH($B34,Clients!$A$5:$A$204,0))&"",""))) -> Standard Clean | K34: =IF($B34="","",IF($F34<>"",$F34,IFERROR(IF(AND(INDEX(Clients!$F$5:$F$204,MATCH($B34,Clients!$A$5:$A$204,0))&""<>"",OR($C34="",$C34=INDEX(Clients!$E$5:$E$204,MATCH($B34,Clients!$A$5:$A$204,0)))),INDEX(Clients!$F$5:$F$204,MATCH($B34,Clients!$A$5:$A$204,0)),INDEX(Settings!$E$5:$E$19,MATCH($J34,Settings!$D$5:$D$19,0))),0))) -> 120 | L34: =IF($B34="","",$K34*IF($D34="",1,$D34)+$E34) -> 120 | M34: =IF($B34="","",ROUND($L34*Settings!$B$9,2)) -> 7.2 | N34: =IF($B34="","",$L34+$M34) -> 127.2 | O34: =IF($Q34="","",Settings!$B$13&TEXT(ROWS($A$5:$A34),"0000")) | P34: =IF($O34="","",IFERROR(INDEX(Invoices!$I$5:$I$504,MATCH($O34,Invoices!$A$5:$A$504,0)),"")) | Q34: =IF(AND($A34<>"",$B34<>"",$G34="Completed"),COUNTIFS($A$5:$A34,"<>",$B$5:$B34,"<>",$G$5:$G34,"Completed"),"")
I35: =IF($B35="","",IFERROR(INDEX(Clients!$D$5:$D$204,MATCH($B35,Clients!$A$5:$A$204,0))&"","")) | J35: =IF($B35="","",IF($C35<>"",$C35,IFERROR(INDEX(Clients!$E$5:$E$204,MATCH($B35,Clients!$A$5:$A$204,0))&"",""))) | K35: =IF($B35="","",IF($F35<>"",$F35,IFERROR(IF(AND(INDEX(Clients!$F$5:$F$204,MATCH($B35,Clients!$A$5:$A$204,0))&""<>"",OR($C35="",$C35=INDEX(Clients!$E$5:$E$204,MATCH($B35,Clients!$A$5:$A$204,0)))),INDEX(Clients!$F$5:$F$204,MATCH($B35,Clients!$A$5:$A$204,0)),INDEX(Settings!$E$5:$E$19,MATCH($J35,Settings!$D$5:$D$19,0))),0))) | L35: =IF($B35="","",$K35*IF($D35="",1,$D35)+$E35) | M35: =IF($B35="","",ROUND($L35*Settings!$B$9,2)) | N35: =IF($B35="","",$L35+$M35) | O35: =IF($Q35="","",Settings!$B$13&TEXT(ROWS($A$5:$A35),"0000")) | P35: =IF($O35="","",IFERROR(INDEX(Invoices!$I$5:$I$504,MATCH($O35,Invoices!$A$5:$A$504,0)),"")) | Q35: =IF(AND($A35<>"",$B35<>"",$G35="Completed"),COUNTIFS($A$5:$A35,"<>",$B$5:$B35,"<>",$G$5:$G35,"Completed"),"")
I36: =IF($B36="","",IFERROR(INDEX(Clients!$D$5:$D$204,MATCH($B36,Clients!$A$5:$A$204,0))&"","")) | J36: =IF($B36="","",IF($C36<>"",$C36,IFERROR(INDEX(Clients!$E$5:$E$204,MATCH($B36,Clients!$A$5:$A$204,0))&"",""))) | K36: =IF($B36="","",IF($F36<>"",$F36,IFERROR(IF(AND(INDEX(Clients!$F$5:$F$204,MATCH($B36,Clients!$A$5:$A$204,0))&""<>"",OR($C36="",$C36=INDEX(Clients!$E$5:$E$204,MATCH($B36,Clients!$A$5:$A$204,0)))),INDEX(Clients!$F$5:$F$204,MATCH($B36,Clients!$A$5:$A$204,0)),INDEX(Settings!$E$5:$E$19,MATCH($J36,Settings!$D$5:$D$19,0))),0))) | L36: =IF($B36="","",$K36*IF($D36="",1,$D36)+$E36) | M36: =IF($B36="","",ROUND($L36*Settings!$B$9,2)) | N36: =IF($B36="","",$L36+$M36) | O36: =IF($Q36="","",Settings!$B$13&TEXT(ROWS($A$5:$A36),"0000")) | P36: =IF($O36="","",IFERROR(INDEX(Invoices!$I$5:$I$504,MATCH($O36,Invoices!$A$5:$A$504,0)),"")) | Q36: =IF(AND($A36<>"",$B36<>"",$G36="Completed"),COUNTIFS($A$5:$A36,"<>",$B$5:$B36,"<>",$G$5:$G36,"Completed"),"")
I37: =IF($B37="","",IFERROR(INDEX(Clients!$D$5:$D$204,MATCH($B37,Clients!$A$5:$A$204,0))&"","")) | J37: =IF($B37="","",IF($C37<>"",$C37,IFERROR(INDEX(Clients!$E$5:$E$204,MATCH($B37,Clients!$A$5:$A$204,0))&"",""))) | K37: =IF($B37="","",IF($F37<>"",$F37,IFERROR(IF(AND(INDEX(Clients!$F$5:$F$204,MATCH($B37,Clients!$A$5:$A$204,0))&""<>"",OR($C37="",$C37=INDEX(Clients!$E$5:$E$204,MATCH($B37,Clients!$A$5:$A$204,0)))),INDEX(Clients!$F$5:$F$204,MATCH($B37,Clients!$A$5:$A$204,0)),INDEX(Settings!$E$5:$E$19,MATCH($J37,Settings!$D$5:$D$19,0))),0))) | L37: =IF($B37="","",$K37*IF($D37="",1,$D37)+$E37) | M37: =IF($B37="","",ROUND($L37*Settings!$B$9,2)) | N37: =IF($B37="","",$L37+$M37) | O37: =IF($Q37="","",Settings!$B$13&TEXT(ROWS($A$5:$A37),"0000")) | P37: =IF($O37="","",IFERROR(INDEX(Invoices!$I$5:$I$504,MATCH($O37,Invoices!$A$5:$A$504,0)),"")) | Q37: =IF(AND($A37<>"",$B37<>"",$G37="Completed"),COUNTIFS($A$5:$A37,"<>",$B$5:$B37,"<>",$G$5:$G37,"Completed"),"")
I38: =IF($B38="","",IFERROR(INDEX(Clients!$D$5:$D$204,MATCH($B38,Clients!$A$5:$A$204,0))&"","")) | J38: =IF($B38="","",IF($C38<>"",$C38,IFERROR(INDEX(Clients!$E$5:$E$204,MATCH($B38,Clients!$A$5:$A$204,0))&"",""))) | K38: =IF($B38="","",IF($F38<>"",$F38,IFERROR(IF(AND(INDEX(Clients!$F$5:$F$204,MATCH($B38,Clients!$A$5:$A$204,0))&""<>"",OR($C38="",$C38=INDEX(Clients!$E$5:$E$204,MATCH($B38,Clients!$A$5:$A$204,0)))),INDEX(Clients!$F$5:$F$204,MATCH($B38,Clients!$A$5:$A$204,0)),INDEX(Settings!$E$5:$E$19,MATCH($J38,Settings!$D$5:$D$19,0))),0))) | L38: =IF($B38="","",$K38*IF($D38="",1,$D38)+$E38) | M38: =IF($B38="","",ROUND($L38*Settings!$B$9,2)) | N38: =IF($B38="","",$L38+$M38) | O38: =IF($Q38="","",Settings!$B$13&TEXT(ROWS($A$5:$A38),"0000")) | P38: =IF($O38="","",IFERROR(INDEX(Invoices!$I$5:$I$504,MATCH($O38,Invoices!$A$5:$A$504,0)),"")) | Q38: =IF(AND($A38<>"",$B38<>"",$G38="Completed"),COUNTIFS($A$5:$A38,"<>",$B$5:$B38,"<>",$G$5:$G38,"Completed"),"")
I39: =IF($B39="","",IFERROR(INDEX(Clients!$D$5:$D$204,MATCH($B39,Clients!$A$5:$A$204,0))&"","")) | J39: =IF($B39="","",IF($C39<>"",$C39,IFERROR(INDEX(Clients!$E$5:$E$204,MATCH($B39,Clients!$A$5:$A$204,0))&"",""))) | K39: =IF($B39="","",IF($F39<>"",$F39,IFERROR(IF(AND(INDEX(Clients!$F$5:$F$204,MATCH($B39,Clients!$A$5:$A$204,0))&""<>"",OR($C39="",$C39=INDEX(Clients!$E$5:$E$204,MATCH($B39,Clients!$A$5:$A$204,0)))),INDEX(Clients!$F$5:$F$204,MATCH($B39,Clients!$A$5:$A$204,0)),INDEX(Settings!$E$5:$E$19,MATCH($J39,Settings!$D$5:$D$19,0))),0))) | L39: =IF($B39="","",$K39*IF($D39="",1,$D39)+$E39) | M39: =IF($B39="","",ROUND($L39*Settings!$B$9,2)) | N39: =IF($B39="","",$L39+$M39) | O39: =IF($Q39="","",Settings!$B$13&TEXT(ROWS($A$5:$A39),"0000")) | P39: =IF($O39="","",IFERROR(INDEX(Invoices!$I$5:$I$504,MATCH($O39,Invoices!$A$5:$A$504,0)),"")) | Q39: =IF(AND($A39<>"",$B39<>"",$G39="Completed"),COUNTIFS($A$5:$A39,"<>",$B$5:$B39,"<>",$G$5:$G39,"Completed"),"")
I40: =IF($B40="","",IFERROR(INDEX(Clients!$D$5:$D$204,MATCH($B40,Clients!$A$5:$A$204,0))&"","")) | J40: =IF($B40="","",IF($C40<>"",$C40,IFERROR(INDEX(Clients!$E$5:$E$204,MATCH($B40,Clients!$A$5:$A$204,0))&"",""))) | K40: =IF($B40="","",IF($F40<>"",$F40,IFERROR(IF(AND(INDEX(Clients!$F$5:$F$204,MATCH($B40,Clients!$A$5:$A$204,0))&""<>"",OR($C40="",$C40=INDEX(Clients!$E$5:$E$204,MATCH($B40,Clients!$A$5:$A$204,0)))),INDEX(Clients!$F$5:$F$204,MATCH($B40,Clients!$A$5:$A$204,0)),INDEX(Settings!$E$5:$E$19,MATCH($J40,Settings!$D$5:$D$19,0))),0))) | L40: =IF($B40="","",$K40*IF($D40="",1,$D40)+$E40) | M40: =IF($B40="","",ROUND($L40*Settings!$B$9,2)) | N40: =IF($B40="","",$L40+$M40) | O40: =IF($Q40="","",Settings!$B$13&TEXT(ROWS($A$5:$A40),"0000")) | P40: =IF($O40="","",IFERROR(INDEX(Invoices!$I$5:$I$504,MATCH($O40,Invoices!$A$5:$A$504,0)),"")) | Q40: =IF(AND($A40<>"",$B40<>"",$G40="Completed"),COUNTIFS($A$5:$A40,"<>",$B$5:$B40,"<>",$G$5:$G40,"Completed"),"")
I41: =IF($B41="","",IFERROR(INDEX(Clients!$D$5:$D$204,MATCH($B41,Clients!$A$5:$A$204,0))&"","")) | J41: =IF($B41="","",IF($C41<>"",$C41,IFERROR(INDEX(Clients!$E$5:$E$204,MATCH($B41,Clients!$A$5:$A$204,0))&"",""))) | K41: =IF($B41="","",IF($F41<>"",$F41,IFERROR(IF(AND(INDEX(Clients!$F$5:$F$204,MATCH($B41,Clients!$A$5:$A$204,0))&""<>"",OR($C41="",$C41=INDEX(Clients!$E$5:$E$204,MATCH($B41,Clients!$A$5:$A$204,0)))),INDEX(Clients!$F$5:$F$204,MATCH($B41,Clients!$A$5:$A$204,0)),INDEX(Settings!$E$5:$E$19,MATCH($J41,Settings!$D$5:$D$19,0))),0))) | L41: =IF($B41="","",$K41*IF($D41="",1,$D41)+$E41) | M41: =IF($B41="","",ROUND($L41*Settings!$B$9,2)) | N41: =IF($B41="","",$L41+$M41) | O41: =IF($Q41="","",Settings!$B$13&TEXT(ROWS($A$5:$A41),"0000")) | P41: =IF($O41="","",IFERROR(INDEX(Invoices!$I$5:$I$504,MATCH($O41,Invoices!$A$5:$A$504,0)),"")) | Q41: =IF(AND($A41<>"",$B41<>"",$G41="Completed"),COUNTIFS($A$5:$A41,"<>",$B$5:$B41,"<>",$G$5:$G41,"Completed"),"")
I42: =IF($B42="","",IFERROR(INDEX(Clients!$D$5:$D$204,MATCH($B42,Clients!$A$5:$A$204,0))&"","")) | J42: =IF($B42="","",IF($C42<>"",$C42,IFERROR(INDEX(Clients!$E$5:$E$204,MATCH($B42,Clients!$A$5:$A$204,0))&"",""))) | K42: =IF($B42="","",IF($F42<>"",$F42,IFERROR(IF(AND(INDEX(Clients!$F$5:$F$204,MATCH($B42,Clients!$A$5:$A$204,0))&""<>"",OR($C42="",$C42=INDEX(Clients!$E$5:$E$204,MATCH($B42,Clients!$A$5:$A$204,0)))),INDEX(Clients!$F$5:$F$204,MATCH($B42,Clients!$A$5:$A$204,0)),INDEX(Settings!$E$5:$E$19,MATCH($J42,Settings!$D$5:$D$19,0))),0))) | L42: =IF($B42="","",$K42*IF($D42="",1,$D42)+$E42) | M42: =IF($B42="","",ROUND($L42*Settings!$B$9,2)) | N42: =IF($B42="","",$L42+$M42) | O42: =IF($Q42="","",Settings!$B$13&TEXT(ROWS($A$5:$A42),"0000")) | P42: =IF($O42="","",IFERROR(INDEX(Invoices!$I$5:$I$504,MATCH($O42,Invoices!$A$5:$A$504,0)),"")) | Q42: =IF(AND($A42<>"",$B42<>"",$G42="Completed"),COUNTIFS($A$5:$A42,"<>",$B$5:$B42,"<>",$G$5:$G42,"Completed"),"")
I43: =IF($B43="","",IFERROR(INDEX(Clients!$D$5:$D$204,MATCH($B43,Clients!$A$5:$A$204,0))&"","")) | J43: =IF($B43="","",IF($C43<>"",$C43,IFERROR(INDEX(Clients!$E$5:$E$204,MATCH($B43,Clients!$A$5:$A$204,0))&"",""))) | K43: =IF($B43="","",IF($F43<>"",$F43,IFERROR(IF(AND(INDEX(Clients!$F$5:$F$204,MATCH($B43,Clients!$A$5:$A$204,0))&""<>"",OR($C43="",$C43=INDEX(Clients!$E$5:$E$204,MATCH($B43,Clients!$A$5:$A$204,0)))),INDEX(Clients!$F$5:$F$204,MATCH($B43,Clients!$A$5:$A$204,0)),INDEX(Settings!$E$5:$E$19,MATCH($J43,Settings!$D$5:$D$19,0))),0))) | L43: =IF($B43="","",$K43*IF($D43="",1,$D43)+$E43) | M43: =IF($B43="","",ROUND($L43*Settings!$B$9,2)) | N43: =IF($B43="","",$L43+$M43) | O43: =IF($Q43="","",Settings!$B$13&TEXT(ROWS($A$5:$A43),"0000")) | P43: =IF($O43="","",IFERROR(INDEX(Invoices!$I$5:$I$504,MATCH($O43,Invoices!$A$5:$A$504,0)),"")) | Q43: =IF(AND($A43<>"",$B43<>"",$G43="Completed"),COUNTIFS($A$5:$A43,"<>",$B$5:$B43,"<>",$G$5:$G43,"Completed"),"")
I44: =IF($B44="","",IFERROR(INDEX(Clients!$D$5:$D$204,MATCH($B44,Clients!$A$5:$A$204,0))&"","")) | J44: =IF($B44="","",IF($C44<>"",$C44,IFERROR(INDEX(Clients!$E$5:$E$204,MATCH($B44,Clients!$A$5:$A$204,0))&"",""))) | K44: =IF($B44="","",IF($F44<>"",$F44,IFERROR(IF(AND(INDEX(Clients!$F$5:$F$204,MATCH($B44,Clients!$A$5:$A$204,0))&""<>"",OR($C44="",$C44=INDEX(Clients!$E$5:$E$204,MATCH($B44,Clients!$A$5:$A$204,0)))),INDEX(Clients!$F$5:$F$204,MATCH($B44,Clients!$A$5:$A$204,0)),INDEX(Settings!$E$5:$E$19,MATCH($J44,Settings!$D$5:$D$19,0))),0))) | L44: =IF($B44="","",$K44*IF($D44="",1,$D44)+$E44) | M44: =IF($B44="","",ROUND($L44*Settings!$B$9,2)) | N44: =IF($B44="","",$L44+$M44) | O44: =IF($Q44="","",Settings!$B$13&TEXT(ROWS($A$5:$A44),"0000")) | P44: =IF($O44="","",IFERROR(INDEX(Invoices!$I$5:$I$504,MATCH($O44,Invoices!$A$5:$A$504,0)),"")) | Q44: =IF(AND($A44<>"",$B44<>"",$G44="Completed"),COUNTIFS($A$5:$A44,"<>",$B$5:$B44,"<>",$G$5:$G44,"Completed"),"")
I45: =IF($B45="","",IFERROR(INDEX(Clients!$D$5:$D$204,MATCH($B45,Clients!$A$5:$A$204,0))&"","")) | J45: =IF($B45="","",IF($C45<>"",$C45,IFERROR(INDEX(Clients!$E$5:$E$204,MATCH($B45,Clients!$A$5:$A$204,0))&"",""))) | K45: =IF($B45="","",IF($F45<>"",$F45,IFERROR(IF(AND(INDEX(Clients!$F$5:$F$204,MATCH($B45,Clients!$A$5:$A$204,0))&""<>"",OR($C45="",$C45=INDEX(Clients!$E$5:$E$204,MATCH($B45,Clients!$A$5:$A$204,0)))),INDEX(Clients!$F$5:$F$204,MATCH($B45,Clients!$A$5:$A$204,0)),INDEX(Settings!$E$5:$E$19,MATCH($J45,Settings!$D$5:$D$19,0))),0))) | L45: =IF($B45="","",$K45*IF($D45="",1,$D45)+$E45) | M45: =IF($B45="","",ROUND($L45*Settings!$B$9,2)) | N45: =IF($B45="","",$L45+$M45) | O45: =IF($Q45="","",Settings!$B$13&TEXT(ROWS($A$5:$A45),"0000")) | P45: =IF($O45="","",IFERROR(INDEX(Invoices!$I$5:$I$504,MATCH($O45,Invoices!$A$5:$A$504,0)),"")) | Q45: =IF(AND($A45<>"",$B45<>"",$G45="Completed"),COUNTIFS($A$5:$A45,"<>",$B$5:$B45,"<>",$G$5:$G45,"Completed"),"")
I46: =IF($B46="","",IFERROR(INDEX(Clients!$D$5:$D$204,MATCH($B46,Clients!$A$5:$A$204,0))&"","")) | J46: =IF($B46="","",IF($C46<>"",$C46,IFERROR(INDEX(Clients!$E$5:$E$204,MATCH($B46,Clients!$A$5:$A$204,0))&"",""))) | K46: =IF($B46="","",IF($F46<>"",$F46,IFERROR(IF(AND(INDEX(Clients!$F$5:$F$204,MATCH($B46,Clients!$A$5:$A$204,0))&""<>"",OR($C46="",$C46=INDEX(Clients!$E$5:$E$204,MATCH($B46,Clients!$A$5:$A$204,0)))),INDEX(Clients!$F$5:$F$204,MATCH($B46,Clients!$A$5:$A$204,0)),INDEX(Settings!$E$5:$E$19,MATCH($J46,Settings!$D$5:$D$19,0))),0))) | L46: =IF($B46="","",$K46*IF($D46="",1,$D46)+$E46) | M46: =IF($B46="","",ROUND($L46*Settings!$B$9,2)) | N46: =IF($B46="","",$L46+$M46) | O46: =IF($Q46="","",Settings!$B$13&TEXT(ROWS($A$5:$A46),"0000")) | P46: =IF($O46="","",IFERROR(INDEX(Invoices!$I$5:$I$504,MATCH($O46,Invoices!$A$5:$A$504,0)),"")) | Q46: =IF(AND($A46<>"",$B46<>"",$G46="Completed"),COUNTIFS($A$5:$A46,"<>",$B$5:$B46,"<>",$G$5:$G46,"Completed"),"")
... I504: =IF($B504="","",IFERROR(INDEX(Clients!$D$5:$D$204,MATCH($B504,Clients!$A$5:$A$204,0))&"","")) | J504: =IF($B504="","",IF($C504<>"",$C504,IFERROR(INDEX(Clients!$E$5:$E$204,MATCH($B504,Clients!$A$5:$A$204,0))&"",""))) | K504: =IF($B504="","",IF($F504<>"",$F504,IFERROR(IF(AND(INDEX(Clients!$F$5:$F$204,MATCH($B504,Clients!$A$5:$A$204,0))&""<>"",OR($C504="",$C504=INDEX(Clients!$E$5:$E$204,MATCH($B504,Clients!$A$5:$A$204,0)))),INDEX(Clients!$F$5:$F$204,MATCH($B504,Clients!$A$5:$A$204,0)),INDEX(Settings!$E$5:$E$19,MATCH($J504,Settings!$D$5:$D$19,0))),0))) | L504: =IF($B504="","",$K504*IF($D504="",1,$D504)+$E504) | M504: =IF($B504="","",ROUND($L504*Settings!$B$9,2)) | N504: =IF($B504="","",$L504+$M504) | O504: =IF($Q504="","",Settings!$B$13&TEXT(ROWS($A$5:$A504),"0000")) | P504: =IF($O504="","",IFERROR(INDEX(Invoices!$I$5:$I$504,MATCH($O504,Invoices!$A$5:$A$504,0)),"")) | Q504: =IF(AND($A504<>"",$B504<>"",$G504="Completed"),COUNTIFS($A$5:$A504,"<>",$B$5:$B504,"<>",$G$5:$G504,"Completed"),"")

Sheet Invoices
A1: =Settings!$B$5&" - Invoices & Payments" -> Sparkle & Shine Cleaning Co. - Invoices & Payments
A2: Total billed | B2: =SUM(E5:E504) -> 4179.05 | C2: Collected | D2: =SUM(F5:F504) -> 3122.95 | E2: Outstanding | F2: =SUM(G5:G504) -> 1056.1 | G2: Overdue invoices | H2: =COUNTIFS(I5:I504,"Overdue") -> 5
A3: Left: every Completed job becomes an invoice automatically (don't type here). Right: log each payment you receive.
A4: Invoice # | B4: Invoice date | C4: Client | D4: Service | E4: ="Amount due ("&Settings!$B$10&")" -> Amount due ($) | F4: ="Paid ("&Settings!$B$10&")" -> Paid ($) | G4: ="Balance ("&Settings!$B$10&")" -> Balance ($) | H4: Due date | I4: Status | J4: Days overdue | K4: Job line (helper) | M4: Payment date | N4: Invoice # | O4: Paid with | P4: ="Amount ("&Settings!$B$10&")" -> Amount ($) | Q4: Client
A5: =IF($K5="","",INDEX(Jobs!$O$5:$O$504,$K5)) -> INV-0001 | B5: =IF($K5="","",INDEX(Jobs!$A$5:$A$504,$K5)) -> 46205 | C5: =IF($K5="","",INDEX(Jobs!$B$5:$B$504,$K5)) -> Hannah Whitfield | D5: =IF($K5="","",INDEX(Jobs!$J$5:$J$504,$K5)) -> Recurring Every 2 Weeks | E5: =IF($K5="","",INDEX(Jobs!$N$5:$N$504,$K5)) -> 116.6 | F5: =IF($A5="","",SUMIFS($P$5:$P$1004,$N$5:$N$1004,$A5)) -> 116.6 | G5: =IF($A5="","",$E5-$F5) -> 0 | H5: =IF($A5="","",$B5+Settings!$B$11) -> 46219 | I5: =IF($A5="","",IF($G5<=0,"Paid",IF(TODAY()>$H5,"Overdue",IF($F5>0,"Partial","Unpaid")))) -> Paid | J5: =IF($A5="","",IF(AND($G5>0,TODAY()>$H5),TODAY()-$H5,"")) | K5: =IFERROR(MATCH(ROWS($K$5:$K5),Jobs!$Q$5:$Q$504,0),"") -> 1 | M5: 46208 | N5: INV-0001 | O5: Check | P5: 116.6 | Q5: =IF($N5="","",IFERROR(INDEX($C$5:$C$504,MATCH($N5,$A$5:$A$504,0)),"Invoice not found")) -> Hannah Whitfield
A6: =IF($K6="","",INDEX(Jobs!$O$5:$O$504,$K6)) -> INV-0002 | B6: =IF($K6="","",INDEX(Jobs!$A$5:$A$504,$K6)) -> 46206 | C6: =IF($K6="","",INDEX(Jobs!$B$5:$B$504,$K6)) -> Brightpath Dental Office | D6: =IF($K6="","",INDEX(Jobs!$J$5:$J$504,$K6)) -> Office Clean (hourly) | E6: =IF($K6="","",INDEX(Jobs!$N$5:$N$504,$K6)) -> 143.1 | F6: =IF($A6="","",SUMIFS($P$5:$P$1004,$N$5:$N$1004,$A6)) -> 143.1 | G6: =IF($A6="","",$E6-$F6) -> 0 | H6: =IF($A6="","",$B6+Settings!$B$11) -> 46220 | I6: =IF($A6="","",IF($G6<=0,"Paid",IF(TODAY()>$H6,"Overdue",IF($F6>0,"Partial","Unpaid")))) -> Paid | J6: =IF($A6="","",IF(AND($G6>0,TODAY()>$H6),TODAY()-$H6,"")) | K6: =IFERROR(MATCH(ROWS($K$5:$K6),Jobs!$Q$5:$Q$504,0),"") -> 2 | M6: 46210 | N6: INV-0002 | O6: Card | P6: 143.1 | Q6: =IF($N6="","",IFERROR(INDEX($C$5:$C$504,MATCH($N6,$A$5:$A$504,0)),"Invoice not found")) -> Brightpath Dental Office
A7: =IF($K7="","",INDEX(Jobs!$O$5:$O$504,$K7)) -> INV-0003 | B7: =IF($K7="","",INDEX(Jobs!$A$5:$A$504,$K7)) -> 46209 | C7: =IF($K7="","",INDEX(Jobs!$B$5:$B$504,$K7)) -> Marcus & Elena Ortiz | D7: =IF($K7="","",INDEX(Jobs!$J$5:$J$504,$K7)) -> Recurring Weekly | E7: =IF($K7="","",INDEX(Jobs!$N$5:$N$504,$K7)) -> 95.4 | F7: =IF($A7="","",SUMIFS($P$5:$P$1004,$N$5:$N$1004,$A7)) -> 95.4 | G7: =IF($A7="","",$E7-$F7) -> 0 | H7: =IF($A7="","",$B7+Settings!$B$11) -> 46223 | I7: =IF($A7="","",IF($G7<=0,"Paid",IF(TODAY()>$H7,"Overdue",IF($F7>0,"Partial","Unpaid")))) -> Paid | J7: =IF($A7="","",IF(AND($G7>0,TODAY()>$H7),TODAY()-$H7,"")) | K7: =IFERROR(MATCH(ROWS($K$5:$K7),Jobs!$Q$5:$Q$504,0),"") -> 3 | M7: 46214 | N7: INV-0003 | O7: Bank Transfer | P7: 95.4 | Q7: =IF($N7="","",IFERROR(INDEX($C$5:$C$504,MATCH($N7,$A$5:$A$504,0)),"Invoice not found")) -> Marcus & Elena Ortiz
A8: =IF($K8="","",INDEX(Jobs!$O$5:$O$504,$K8)) -> INV-0004 | B8: =IF($K8="","",INDEX(Jobs!$A$5:$A$504,$K8)) -> 46211 | C8: =IF($K8="","",INDEX(Jobs!$B$5:$B$504,$K8)) -> Priya Raman | D8: =IF($K8="","",INDEX(Jobs!$J$5:$J$504,$K8)) -> Deep Clean | E8: =IF($K8="","",INDEX(Jobs!$N$5:$N$504,$K8)) -> 259.7 | F8: =IF($A8="","",SUMIFS($P$5:$P$1004,$N$5:$N$1004,$A8)) -> 259.7 | G8: =IF($A8="","",$E8-$F8) -> 0 | H8: =IF($A8="","",$B8+Settings!$B$11) -> 46225 | I8: =IF($A8="","",IF($G8<=0,"Paid",IF(TODAY()>$H8,"Overdue",IF($F8>0,"Partial","Unpaid")))) -> Paid | J8: =IF($A8="","",IF(AND($G8>0,TODAY()>$H8),TODAY()-$H8,"")) | K8: =IFERROR(MATCH(ROWS($K$5:$K8),Jobs!$Q$5:$Q$504,0),"") -> 4 | M8: 46217 | N8: INV-0004 | O8: Cash | P8: 259.7 | Q8: =IF($N8="","",IFERROR(INDEX($C$5:$C$504,MATCH($N8,$A$5:$A$504,0)),"Invoice not found")) -> Priya Raman
A9: =IF($K9="","",INDEX(Jobs!$O$5:$O$504,$K9)) -> INV-0005 | B9: =IF($K9="","",INDEX(Jobs!$A$5:$A$504,$K9)) -> 46213 | C9: =IF($K9="","",INDEX(Jobs!$B$5:$B$504,$K9)) -> Brightpath Dental Office | D9: =IF($K9="","",INDEX(Jobs!$J$5:$J$504,$K9)) -> Office Clean (hourly) | E9: =IF($K9="","",INDEX(Jobs!$N$5:$N$504,$K9)) -> 143.1 | F9: =IF($A9="","",SUMIFS($P$5:$P$1004,$N$5:$N$1004,$A9)) -> 143.1 | G9: =IF($A9="","",$E9-$F9) -> 0 | H9: =IF($A9="","",$B9+Settings!$B$11) -> 46227 | I9: =IF($A9="","",IF($G9<=0,"Paid",IF(TODAY()>$H9,"Overdue",IF($F9>0,"Partial","Unpaid")))) -> Paid | J9: =IF($A9="","",IF(AND($G9>0,TODAY()>$H9),TODAY()-$H9,"")) | K9: =IFERROR(MATCH(ROWS($K$5:$K9),Jobs!$Q$5:$Q$504,0),"") -> 5 | M9: 46220 | N9: INV-0005 | O9: Check | P9: 143.1 | Q9: =IF($N9="","",IFERROR(INDEX($C$5:$C$504,MATCH($N9,$A$5:$A$504,0)),"Invoice not found")) -> Brightpath Dental Office
A10: =IF($K10="","",INDEX(Jobs!$O$5:$O$504,$K10)) -> INV-0006 | B10: =IF($K10="","",INDEX(Jobs!$A$5:$A$504,$K10)) -> 46216 | C10: =IF($K10="","",INDEX(Jobs!$B$5:$B$504,$K10)) -> Marcus & Elena Ortiz | D10: =IF($K10="","",INDEX(Jobs!$J$5:$J$504,$K10)) -> Recurring Weekly | E10: =IF($K10="","",INDEX(Jobs!$N$5:$N$504,$K10)) -> 95.4 | F10: =IF($A10="","",SUMIFS($P$5:$P$1004,$N$5:$N$1004,$A10)) -> 95.4 | G10: =IF($A10="","",$E10-$F10) -> 0 | H10: =IF($A10="","",$B10+Settings!$B$11) -> 46230 | I10: =IF($A10="","",IF($G10<=0,"Paid",IF(TODAY()>$H10,"Overdue",IF($F10>0,"Partial","Unpaid")))) -> Paid | J10: =IF($A10="","",IF(AND($G10>0,TODAY()>$H10),TODAY()-$H10,"")) | K10: =IFERROR(MATCH(ROWS($K$5:$K10),Jobs!$Q$5:$Q$504,0),"") -> 6 | M10: 46224 | N10: INV-0006 | O10: Card | P10: 95.4 | Q10: =IF($N10="","",IFERROR(INDEX($C$5:$C$504,MATCH($N10,$A$5:$A$504,0)),"Invoice not found")) -> Marcus & Elena Ortiz
A11: =IF($K11="","",INDEX(Jobs!$O$5:$O$504,$K11)) -> INV-0007 | B11: =IF($K11="","",INDEX(Jobs!$A$5:$A$504,$K11)) -> 46219 | C11: =IF($K11="","",INDEX(Jobs!$B$5:$B$504,$K11)) -> Hannah Whitfield | D11: =IF($K11="","",INDEX(Jobs!$J$5:$J$504,$K11)) -> Recurring Every 2 Weeks | E11: =IF($K11="","",INDEX(Jobs!$N$5:$N$504,$K11)) -> 116.6 | F11: =IF($A11="","",SUMIFS($P$5:$P$1004,$N$5:$N$1004,$A11)) -> 116.6 | G11: =IF($A11="","",$E11-$F11) -> 0 | H11: =IF($A11="","",$B11+Settings!$B$11) -> 46233 | I11: =IF($A11="","",IF($G11<=0,"Paid",IF(TODAY()>$H11,"Overdue",IF($F11>0,"Partial","Unpaid")))) -> Paid | J11: =IF($A11="","",IF(AND($G11>0,TODAY()>$H11),TODAY()-$H11,"")) | K11: =IFERROR(MATCH(ROWS($K$5:$K11),Jobs!$Q$5:$Q$504,0),"") -> 7 | M11: 46228 | N11: INV-0007 | O11: Bank Transfer | P11: 116.6 | Q11: =IF($N11="","",IFERROR(INDEX($C$5:$C$504,MATCH($N11,$A$5:$A$504,0)),"Invoice not found")) -> Hannah Whitfield
A12: =IF($K12="","",INDEX(Jobs!$O$5:$O$504,$K12)) -> INV-0008 | B12: =IF($K12="","",INDEX(Jobs!$A$5:$A$504,$K12)) -> 46223 | C12: =IF($K12="","",INDEX(Jobs!$B$5:$B$504,$K12)) -> Greenleaf Property Mgmt | D12: =IF($K12="","",INDEX(Jobs!$J$5:$J$504,$K12)) -> Move-In / Move-Out | E12: =IF($K12="","",INDEX(Jobs!$N$5:$N$504,$K12)) -> 318 | F12: =IF($A12="","",SUMIFS($P$5:$P$1004,$N$5:$N$1004,$A12)) -> 318 | G12: =IF($A12="","",$E12-$F12) -> 0 | H12: =IF($A12="","",$B12+Settings!$B$11) -> 46237 | I12: =IF($A12="","",IF($G12<=0,"Paid",IF(TODAY()>$H12,"Overdue",IF($F12>0,"Partial","Unpaid")))) -> Paid | J12: =IF($A12="","",IF(AND($G12>0,TODAY()>$H12),TODAY()-$H12,"")) | K12: =IFERROR(MATCH(ROWS($K$5:$K12),Jobs!$Q$5:$Q$504,0),"") -> 8 | M12: 46233 | N12: INV-0008 | O12: Cash | P12: 318 | Q12: =IF($N12="","",IFERROR(INDEX($C$5:$C$504,MATCH($N12,$A$5:$A$504,0)),"Invoice not found")) -> Greenleaf Property Mgmt
A13: =IF($K13="","",INDEX(Jobs!$O$5:$O$504,$K13)) -> INV-0009 | B13: =IF($K13="","",INDEX(Jobs!$A$5:$A$504,$K13)) -> 46227 | C13: =IF($K13="","",INDEX(Jobs!$B$5:$B$504,$K13)) -> Tom Kessler | D13: =IF($K13="","",INDEX(Jobs!$J$5:$J$504,$K13)) -> Standard Clean | E13: =IF($K13="","",INDEX(Jobs!$N$5:$N$504,$K13)) -> 127.2 | F13: =IF($A13="","",SUMIFS($P$5:$P$1004,$N$5:$N$1004,$A13)) -> 0 | G13: =IF($A13="","",$E13-$F13) -> 127.2 | H13: =IF($A13="","",$B13+Settings!$B$11) -> 46241 | I13: =IF($A13="","",IF($G13<=0,"Paid",IF(TODAY()>$H13,"Overdue",IF($F13>0,"Partial","Unpaid")))) -> Overdue | J13: =IF($A13="","",IF(AND($G13>0,TODAY()>$H13),TODAY()-$H13,"")) -> 56 | K13: =IFERROR(MATCH(ROWS($K$5:$K13),Jobs!$Q$5:$Q$504,0),"") -> 9 | M13: 46234 | N13: INV-0010 | O13: Card | P13: 106 | Q13: =IF($N13="","",IFERROR(INDEX($C$5:$C$504,MATCH($N13,$A$5:$A$504,0)),"Invoice not found")) -> Riverside Yoga Studio
A14: =IF($K14="","",INDEX(Jobs!$O$5:$O$504,$K14)) -> INV-0010 | B14: =IF($K14="","",INDEX(Jobs!$A$5:$A$504,$K14)) -> 46231 | C14: =IF($K14="","",INDEX(Jobs!$B$5:$B$504,$K14)) -> Riverside Yoga Studio | D14: =IF($K14="","",INDEX(Jobs!$J$5:$J$504,$K14)) -> Office Clean (hourly) | E14: =IF($K14="","",INDEX(Jobs!$N$5:$N$504,$K14)) -> 106 | F14: =IF($A14="","",SUMIFS($P$5:$P$1004,$N$5:$N$1004,$A14)) -> 106 | G14: =IF($A14="","",$E14-$F14) -> 0 | H14: =IF($A14="","",$B14+Settings!$B$11) -> 46245 | I14: =IF($A14="","",IF($G14<=0,"Paid",IF(TODAY()>$H14,"Overdue",IF($F14>0,"Partial","Unpaid")))) -> Paid | J14: =IF($A14="","",IF(AND($G14>0,TODAY()>$H14),TODAY()-$H14,"")) | K14: =IFERROR(MATCH(ROWS($K$5:$K14),Jobs!$Q$5:$Q$504,0),"") -> 10 | M14: 46241 | N14: INV-0011 | O14: Bank Transfer | P14: 95.4 | Q14: =IF($N14="","",IFERROR(INDEX($C$5:$C$504,MATCH($N14,$A$5:$A$504,0)),"Invoice not found")) -> Marcus & Elena Ortiz
A15: =IF($K15="","",INDEX(Jobs!$O$5:$O$504,$K15)) -> INV-0011 | B15: =IF($K15="","",INDEX(Jobs!$A$5:$A$504,$K15)) -> 46237 | C15: =IF($K15="","",INDEX(Jobs!$B$5:$B$504,$K15)) -> Marcus & Elena Ortiz | D15: =IF($K15="","",INDEX(Jobs!$J$5:$J$504,$K15)) -> Recurring Weekly | E15: =IF($K15="","",INDEX(Jobs!$N$5:$N$504,$K15)) -> 95.4 | F15: =IF($A15="","",SUMIFS($P$5:$P$1004,$N$5:$N$1004,$A15)) -> 95.4 | G15: =IF($A15="","",$E15-$F15) -> 0 | H15: =IF($A15="","",$B15+Settings!$B$11) -> 46251 | I15: =IF($A15="","",IF($G15<=0,"Paid",IF(TODAY()>$H15,"Overdue",IF($F15>0,"Partial","Unpaid")))) -> Paid | J15: =IF($A15="","",IF(AND($G15>0,TODAY()>$H15),TODAY()-$H15,"")) | K15: =IFERROR(MATCH(ROWS($K$5:$K15),Jobs!$Q$5:$Q$504,0),"") -> 11 | M15: 46243 | N15: INV-0012 | O15: Cash | P15: 106 | Q15: =IF($N15="","",IFERROR(INDEX($C$5:$C$504,MATCH($N15,$A$5:$A$504,0)),"Invoice not found")) -> Riverside Yoga Studio
A16: =IF($K16="","",INDEX(Jobs!$O$5:$O$504,$K16)) -> INV-0012 | B16: =IF($K16="","",INDEX(Jobs!$A$5:$A$504,$K16)) -> 46238 | C16: =IF($K16="","",INDEX(Jobs!$B$5:$B$504,$K16)) -> Riverside Yoga Studio | D16: =IF($K16="","",INDEX(Jobs!$J$5:$J$504,$K16)) -> Office Clean (hourly) | E16: =IF($K16="","",INDEX(Jobs!$N$5:$N$504,$K16)) -> 106 | F16: =IF($A16="","",SUMIFS($P$5:$P$1004,$N$5:$N$1004,$A16)) -> 106 | G16: =IF($A16="","",$E16-$F16) -> 0 | H16: =IF($A16="","",$B16+Settings!$B$11) -> 46252 | I16: =IF($A16="","",IF($G16<=0,"Paid",IF(TODAY()>$H16,"Overdue",IF($F16>0,"Partial","Unpaid")))) -> Paid | J16: =IF($A16="","",IF(AND($G16>0,TODAY()>$H16),TODAY()-$H16,"")) | K16: =IFERROR(MATCH(ROWS($K$5:$K16),Jobs!$Q$5:$Q$504,0),"") -> 12 | M16: 46246 | N16: INV-0013 | O16: Check | P16: 233.2 | Q16: =IF($N16="","",IFERROR(INDEX($C$5:$C$504,MATCH($N16,$A$5:$A$504,0)),"Invoice not found")) -> Danielle Brooks
... A26: =IF($K26="","",INDEX(Jobs!$O$5:$O$504,$K26)) -> INV-0023 | B26: =IF($K26="","",INDEX(Jobs!$A$5:$A$504,$K26)) -> 46273 | C26: =IF($K26="","",INDEX(Jobs!$B$5:$B$504,$K26)) -> Hannah Whitfield | D26: =IF($K26="","",INDEX(Jobs!$J$5:$J$504,$K26)) -> Recurring Every 2 Weeks | E26: =IF($K26="","",INDEX(Jobs!$N$5:$N$504,$K26)) -> 116.6 | F26: =IF($A26="","",SUMIFS($P$5:$P$1004,$N$5:$N$1004,$A26)) -> 116.6 | G26: =IF($A26="","",$E26-$F26) -> 0 | H26: =IF($A26="","",$B26+Settings!$B$11) -> 46287 | I26: =IF($A26="","",IF($G26<=0,"Paid",IF(TODAY()>$H26,"Overdue",IF($F26>0,"Partial","Unpaid")))) -> Paid | J26: =IF($A26="","",IF(AND($G26>0,TODAY()>$H26),TODAY()-$H26,"")) | K26: =IFERROR(MATCH(ROWS($K$5:$K26),Jobs!$Q$5:$Q$504,0),"") -> 23 | M26: 46283 | N26: INV-0024 | O26: Cash | P26: 106 | Q26: =IF($N26="","",IFERROR(INDEX($C$5:$C$504,MATCH($N26,$A$5:$A$504,0)),"Invoice not found")) -> Riverside Yoga Studio
A27: =IF($K27="","",INDEX(Jobs!$O$5:$O$504,$K27)) -> INV-0024 | B27: =IF($K27="","",INDEX(Jobs!$A$5:$A$504,$K27)) -> 46275 | C27: =IF($K27="","",INDEX(Jobs!$B$5:$B$504,$K27)) -> Riverside Yoga Studio | D27: =IF($K27="","",INDEX(Jobs!$J$5:$J$504,$K27)) -> Office Clean (hourly) | E27: =IF($K27="","",INDEX(Jobs!$N$5:$N$504,$K27)) -> 106 | F27: =IF($A27="","",SUMIFS($P$5:$P$1004,$N$5:$N$1004,$A27)) -> 106 | G27: =IF($A27="","",$E27-$F27) -> 0 | H27: =IF($A27="","",$B27+Settings!$B$11) -> 46289 | I27: =IF($A27="","",IF($G27<=0,"Paid",IF(TODAY()>$H27,"Overdue",IF($F27>0,"Partial","Unpaid")))) -> Paid | J27: =IF($A27="","",IF(AND($G27>0,TODAY()>$H27),TODAY()-$H27,"")) | K27: =IFERROR(MATCH(ROWS($K$5:$K27),Jobs!$Q$5:$Q$504,0),"") -> 24 | Q27: =IF($N27="","",IFERROR(INDEX($C$5:$C$504,MATCH($N27,$A$5:$A$504,0)),"Invoice not found"))
A28: =IF($K28="","",INDEX(Jobs!$O$5:$O$504,$K28)) -> INV-0025 | B28: =IF($K28="","",INDEX(Jobs!$A$5:$A$504,$K28)) -> 46277 | C28: =IF($K28="","",INDEX(Jobs!$B$5:$B$504,$K28)) -> Greenleaf Property Mgmt | D28: =IF($K28="","",INDEX(Jobs!$J$5:$J$504,$K28)) -> Move-In / Move-Out | E28: =IF($K28="","",INDEX(Jobs!$N$5:$N$504,$K28)) -> 318 | F28: =IF($A28="","",SUMIFS($P$5:$P$1004,$N$5:$N$1004,$A28)) -> 0 | G28: =IF($A28="","",$E28-$F28) -> 318 | H28: =IF($A28="","",$B28+Settings!$B$11) -> 46291 | I28: =IF($A28="","",IF($G28<=0,"Paid",IF(TODAY()>$H28,"Overdue",IF($F28>0,"Partial","Unpaid")))) -> Overdue | J28: =IF($A28="","",IF(AND($G28>0,TODAY()>$H28),TODAY()-$H28,"")) -> 6 | K28: =IFERROR(MATCH(ROWS($K$5:$K28),Jobs!$Q$5:$Q$504,0),"") -> 25 | Q28: =IF($N28="","",IFERROR(INDEX($C$5:$C$504,MATCH($N28,$A$5:$A$504,0)),"Invoice not found"))
A29: =IF($K29="","",INDEX(Jobs!$O$5:$O$504,$K29)) -> INV-0026 | B29: =IF($K29="","",INDEX(Jobs!$A$5:$A$504,$K29)) -> 46280 | C29: =IF($K29="","",INDEX(Jobs!$B$5:$B$504,$K29)) -> Priya Raman | D29: =IF($K29="","",INDEX(Jobs!$J$5:$J$504,$K29)) -> Deep Clean | E29: =IF($K29="","",INDEX(Jobs!$N$5:$N$504,$K29)) -> 233.2 | F29: =IF($A29="","",SUMIFS($P$5:$P$1004,$N$5:$N$1004,$A29)) -> 0 | G29: =IF($A29="","",$E29-$F29) -> 233.2 | H29: =IF($A29="","",$B29+Settings!$B$11) -> 46294 | I29: =IF($A29="","",IF($G29<=0,"Paid",IF(TODAY()>$H29,"Overdue",IF($F29>0,"Partial","Unpaid")))) -> Overdue | J29: =IF($A29="","",IF(AND($G29>0,TODAY()>$H29),TODAY()-$H29,"")) -> 3 | K29: =IFERROR(MATCH(ROWS($K$5:$K29),Jobs!$Q$5:$Q$504,0),"") -> 26 | Q29: =IF($N29="","",IFERROR(INDEX($C$5:$C$504,MATCH($N29,$A$5:$A$504,0)),"Invoice not found"))
A30: =IF($K30="","",INDEX(Jobs!$O$5:$O$504,$K30)) -> INV-0027 | B30: =IF($K30="","",INDEX(Jobs!$A$5:$A$504,$K30)) -> 46282 | C30: =IF($K30="","",INDEX(Jobs!$B$5:$B$504,$K30)) -> Tom Kessler | D30: =IF($K30="","",INDEX(Jobs!$J$5:$J$504,$K30)) -> Window Cleaning | E30: =IF($K30="","",INDEX(Jobs!$N$5:$N$504,$K30)) -> 100.7 | F30: =IF($A30="","",SUMIFS($P$5:$P$1004,$N$5:$N$1004,$A30)) -> 0 | G30: =IF($A30="","",$E30-$F30) -> 100.7 | H30: =IF($A30="","",$B30+Settings!$B$11) -> 46296 | I30: =IF($A30="","",IF($G30<=0,"Paid",IF(TODAY()>$H30,"Overdue",IF($F30>0,"Partial","Unpaid")))) -> Overdue | J30: =IF($A30="","",IF(AND($G30>0,TODAY()>$H30),TODAY()-$H30,"")) -> 1 | K30: =IFERROR(MATCH(ROWS($K$5:$K30),Jobs!$Q$5:$Q$504,0),"") -> 27 | Q30: =IF($N30="","",IFERROR(INDEX($C$5:$C$504,MATCH($N30,$A$5:$A$504,0)),"Invoice not found"))
A31: =IF($K31="","",INDEX(Jobs!$O$5:$O$504,$K31)) -> INV-0028 | B31: =IF($K31="","",INDEX(Jobs!$A$5:$A$504,$K31)) -> 46287 | C31: =IF($K31="","",INDEX(Jobs!$B$5:$B$504,$K31)) -> Hannah Whitfield | D31: =IF($K31="","",INDEX(Jobs!$J$5:$J$504,$K31)) -> Recurring Every 2 Weeks | E31: =IF($K31="","",INDEX(Jobs!$N$5:$N$504,$K31)) -> 116.6 | F31: =IF($A31="","",SUMIFS($P$5:$P$1004,$N$5:$N$1004,$A31)) -> 0 | G31: =IF($A31="","",$E31-$F31) -> 116.6 | H31: =IF($A31="","",$B31+Settings!$B$11) -> 46301 | I31: =IF($A31="","",IF($G31<=0,"Paid",IF(TODAY()>$H31,"Overdue",IF($F31>0,"Partial","Unpaid")))) -> Unpaid | J31: =IF($A31="","",IF(AND($G31>0,TODAY()>$H31),TODAY()-$H31,"")) | K31: =IFERROR(MATCH(ROWS($K$5:$K31),Jobs!$Q$5:$Q$504,0),"") -> 28 | Q31: =IF($N31="","",IFERROR(INDEX($C$5:$C$504,MATCH($N31,$A$5:$A$504,0)),"Invoice not found"))
A32: =IF($K32="","",INDEX(Jobs!$O$5:$O$504,$K32)) | B32: =IF($K32="","",INDEX(Jobs!$A$5:$A$504,$K32)) | C32: =IF($K32="","",INDEX(Jobs!$B$5:$B$504,$K32)) | D32: =IF($K32="","",INDEX(Jobs!$J$5:$J$504,$K32)) | E32: =IF($K32="","",INDEX(Jobs!$N$5:$N$504,$K32)) | F32: =IF($A32="","",SUMIFS($P$5:$P$1004,$N$5:$N$1004,$A32)) | G32: =IF($A32="","",$E32-$F32) | H32: =IF($A32="","",$B32+Settings!$B$11) | I32: =IF($A32="","",IF($G32<=0,"Paid",IF(TODAY()>$H32,"Overdue",IF($F32>0,"Partial","Unpaid")))) | J32: =IF($A32="","",IF(AND($G32>0,TODAY()>$H32),TODAY()-$H32,"")) | K32: =IFERROR(MATCH(ROWS($K$5:$K32),Jobs!$Q$5:$Q$504,0),"") | Q32: =IF($N32="","",IFERROR(INDEX($C$5:$C$504,MATCH($N32,$A$5:$A$504,0)),"Invoice not found"))
A33: =IF($K33="","",INDEX(Jobs!$O$5:$O$504,$K33)) | B33: =IF($K33="","",INDEX(Jobs!$A$5:$A$504,$K33)) | C33: =IF($K33="","",INDEX(Jobs!$B$5:$B$504,$K33)) | D33: =IF($K33="","",INDEX(Jobs!$J$5:$J$504,$K33)) | E33: =IF($K33="","",INDEX(Jobs!$N$5:$N$504,$K33)) | F33: =IF($A33="","",SUMIFS($P$5:$P$1004,$N$5:$N$1004,$A33)) | G33: =IF($A33="","",$E33-$F33) | H33: =IF($A33="","",$B33+Settings!$B$11) | I33: =IF($A33="","",IF($G33<=0,"Paid",IF(TODAY()>$H33,"Overdue",IF($F33>0,"Partial","Unpaid")))) | J33: =IF($A33="","",IF(AND($G33>0,TODAY()>$H33),TODAY()-$H33,"")) | K33: =IFERROR(MATCH(ROWS($K$5:$K33),Jobs!$Q$5:$Q$504,0),"") | Q33: =IF($N33="","",IFERROR(INDEX($C$5:$C$504,MATCH($N33,$A$5:$A$504,0)),"Invoice not found"))
A34: =IF($K34="","",INDEX(Jobs!$O$5:$O$504,$K34)) | B34: =IF($K34="","",INDEX(Jobs!$A$5:$A$504,$K34)) | C34: =IF($K34="","",INDEX(Jobs!$B$5:$B$504,$K34)) | D34: =IF($K34="","",INDEX(Jobs!$J$5:$J$504,$K34)) | E34: =IF($K34="","",INDEX(Jobs!$N$5:$N$504,$K34)) | F34: =IF($A34="","",SUMIFS($P$5:$P$1004,$N$5:$N$1004,$A34)) | G34: =IF($A34="","",$E34-$F34) | H34: =IF($A34="","",$B34+Settings!$B$11) | I34: =IF($A34="","",IF($G34<=0,"Paid",IF(TODAY()>$H34,"Overdue",IF($F34>0,"Partial","Unpaid")))) | J34: =IF($A34="","",IF(AND($G34>0,TODAY()>$H34),TODAY()-$H34,"")) | K34: =IFERROR(MATCH(ROWS($K$5:$K34),Jobs!$Q$5:$Q$504,0),"") | Q34: =IF($N34="","",IFERROR(INDEX($C$5:$C$504,MATCH($N34,$A$5:$A$504,0)),"Invoice not found"))
A35: =IF($K35="","",INDEX(Jobs!$O$5:$O$504,$K35)) | B35: =IF($K35="","",INDEX(Jobs!$A$5:$A$504,$K35)) | C35: =IF($K35="","",INDEX(Jobs!$B$5:$B$504,$K35)) | D35: =IF($K35="","",INDEX(Jobs!$J$5:$J$504,$K35)) | E35: =IF($K35="","",INDEX(Jobs!$N$5:$N$504,$K35)) | F35: =IF($A35="","",SUMIFS($P$5:$P$1004,$N$5:$N$1004,$A35)) | G35: =IF($A35="","",$E35-$F35) | H35: =IF($A35="","",$B35+Settings!$B$11) | I35: =IF($A35="","",IF($G35<=0,"Paid",IF(TODAY()>$H35,"Overdue",IF($F35>0,"Partial","Unpaid")))) | J35: =IF($A35="","",IF(AND($G35>0,TODAY()>$H35),TODAY()-$H35,"")) | K35: =IFERROR(MATCH(ROWS($K$5:$K35),Jobs!$Q$5:$Q$504,0),"") | Q35: =IF($N35="","",IFERROR(INDEX($C$5:$C$504,MATCH($N35,$A$5:$A$504,0)),"Invoice not found"))
A36: =IF($K36="","",INDEX(Jobs!$O$5:$O$504,$K36)) | B36: =IF($K36="","",INDEX(Jobs!$A$5:$A$504,$K36)) | C36: =IF($K36="","",INDEX(Jobs!$B$5:$B$504,$K36)) | D36: =IF($K36="","",INDEX(Jobs!$J$5:$J$504,$K36)) | E36: =IF($K36="","",INDEX(Jobs!$N$5:$N$504,$K36)) | F36: =IF($A36="","",SUMIFS($P$5:$P$1004,$N$5:$N$1004,$A36)) | G36: =IF($A36="","",$E36-$F36) | H36: =IF($A36="","",$B36+Settings!$B$11) | I36: =IF($A36="","",IF($G36<=0,"Paid",IF(TODAY()>$H36,"Overdue",IF($F36>0,"Partial","Unpaid")))) | J36: =IF($A36="","",IF(AND($G36>0,TODAY()>$H36),TODAY()-$H36,"")) | K36: =IFERROR(MATCH(ROWS($K$5:$K36),Jobs!$Q$5:$Q$504,0),"") | Q36: =IF($N36="","",IFERROR(INDEX($C$5:$C$504,MATCH($N36,$A$5:$A$504,0)),"Invoice not found"))
A37: =IF($K37="","",INDEX(Jobs!$O$5:$O$504,$K37)) | B37: =IF($K37="","",INDEX(Jobs!$A$5:$A$504,$K37)) | C37: =IF($K37="","",INDEX(Jobs!$B$5:$B$504,$K37)) | D37: =IF($K37="","",INDEX(Jobs!$J$5:$J$504,$K37)) | E37: =IF($K37="","",INDEX(Jobs!$N$5:$N$504,$K37)) | F37: =IF($A37="","",SUMIFS($P$5:$P$1004,$N$5:$N$1004,$A37)) | G37: =IF($A37="","",$E37-$F37) | H37: =IF($A37="","",$B37+Settings!$B$11) | I37: =IF($A37="","",IF($G37<=0,"Paid",IF(TODAY()>$H37,"Overdue",IF($F37>0,"Partial","Unpaid")))) | J37: =IF($A37="","",IF(AND($G37>0,TODAY()>$H37),TODAY()-$H37,"")) | K37: =IFERROR(MATCH(ROWS($K$5:$K37),Jobs!$Q$5:$Q$504,0),"") | Q37: =IF($N37="","",IFERROR(INDEX($C$5:$C$504,MATCH($N37,$A$5:$A$504,0)),"Invoice not found"))
A38: =IF($K38="","",INDEX(Jobs!$O$5:$O$504,$K38)) | B38: =IF($K38="","",INDEX(Jobs!$A$5:$A$504,$K38)) | C38: =IF($K38="","",INDEX(Jobs!$B$5:$B$504,$K38)) | D38: =IF($K38="","",INDEX(Jobs!$J$5:$J$504,$K38)) | E38: =IF($K38="","",INDEX(Jobs!$N$5:$N$504,$K38)) | F38: =IF($A38="","",SUMIFS($P$5:$P$1004,$N$5:$N$1004,$A38)) | G38: =IF($A38="","",$E38-$F38) | H38: =IF($A38="","",$B38+Settings!$B$11) | I38: =IF($A38="","",IF($G38<=0,"Paid",IF(TODAY()>$H38,"Overdue",IF($F38>0,"Partial","Unpaid")))) | J38: =IF($A38="","",IF(AND($G38>0,TODAY()>$H38),TODAY()-$H38,"")) | K38: =IFERROR(MATCH(ROWS($K$5:$K38),Jobs!$Q$5:$Q$504,0),"") | Q38: =IF($N38="","",IFERROR(INDEX($C$5:$C$504,MATCH($N38,$A$5:$A$504,0)),"Invoice not found"))
... A504: =IF($K504="","",INDEX(Jobs!$O$5:$O$504,$K504)) | B504: =IF($K504="","",INDEX(Jobs!$A$5:$A$504,$K504)) | C504: =IF($K504="","",INDEX(Jobs!$B$5:$B$504,$K504)) | D504: =IF($K504="","",INDEX(Jobs!$J$5:$J$504,$K504)) | E504: =IF($K504="","",INDEX(Jobs!$N$5:$N$504,$K504)) | F504: =IF($A504="","",SUMIFS($P$5:$P$1004,$N$5:$N$1004,$A504)) | G504: =IF($A504="","",$E504-$F504) | H504: =IF($A504="","",$B504+Settings!$B$11) | I504: =IF($A504="","",IF($G504<=0,"Paid",IF(TODAY()>$H504,"Overdue",IF($F504>0,"Partial","Unpaid")))) | J504: =IF($A504="","",IF(AND($G504>0,TODAY()>$H504),TODAY()-$H504,"")) | K504: =IFERROR(MATCH(ROWS($K$5:$K504),Jobs!$Q$5:$Q$504,0),"") | Q504: =IF($N504="","",IFERROR(INDEX($C$5:$C$504,MATCH($N504,$A$5:$A$504,0)),"Invoice not found"))
Q505: =IF($N505="","",IFERROR(INDEX($C$5:$C$504,MATCH($N505,$A$5:$A$504,0)),"Invoice not found"))
Q506: =IF($N506="","",IFERROR(INDEX($C$5:$C$504,MATCH($N506,$A$5:$A$504,0)),"Invoice not found"))
Q507: =IF($N507="","",IFERROR(INDEX($C$5:$C$504,MATCH($N507,$A$5:$A$504,0)),"Invoice not found"))
Q508: =IF($N508="","",IFERROR(INDEX($C$5:$C$504,MATCH($N508,$A$5:$A$504,0)),"Invoice not found"))
Q509: =IF($N509="","",IFERROR(INDEX($C$5:$C$504,MATCH($N509,$A$5:$A$504,0)),"Invoice not found"))
Q510: =IF($N510="","",IFERROR(INDEX($C$5:$C$504,MATCH($N510,$A$5:$A$504,0)),"Invoice not found"))
Q511: =IF($N511="","",IFERROR(INDEX($C$5:$C$504,MATCH($N511,$A$5:$A$504,0)),"Invoice not found"))
Q512: =IF($N512="","",IFERROR(INDEX($C$5:$C$504,MATCH($N512,$A$5:$A$504,0)),"Invoice not found"))
Q513: =IF($N513="","",IFERROR(INDEX($C$5:$C$504,MATCH($N513,$A$5:$A$504,0)),"Invoice not found"))
Q514: =IF($N514="","",IFERROR(INDEX($C$5:$C$504,MATCH($N514,$A$5:$A$504,0)),"Invoice not found"))
Q515: =IF($N515="","",IFERROR(INDEX($C$5:$C$504,MATCH($N515,$A$5:$A$504,0)),"Invoice not found"))
Q516: =IF($N516="","",IFERROR(INDEX($C$5:$C$504,MATCH($N516,$A$5:$A$504,0)),"Invoice not found"))
... Q1004: =IF($N1004="","",IFERROR(INDEX($C$5:$C$504,MATCH($N1004,$A$5:$A$504,0)),"Invoice not found"))

Sheet Expenses
A1: =Settings!$B$5&" - Expenses" -> Sparkle & Shine Cleaning Co. - Expenses
A2: Total on this list | B2: =SUM(D5:D504) -> 1298.69
A3: One row per business expense. Categories come from the Settings tab.
A4: Date | B4: Category | C4: Description / vendor | D4: ="Amount ("&Settings!$B$10&")" -> Amount ($) | E4: Paid with | F4: Notes
A5: 46204 | B5: Cleaning Supplies | C5: Bulk cleaners and microfiber cloths | D5: 186.4 | E5: Card
A6: 46208 | B6: Insurance | C6: General liability - monthly | D6: 89 | E6: Bank Transfer
A7: 46218 | B7: Marketing & Advertising | C7: Door hangers (500) | D7: 64.99 | E7: Card
A8: 46234 | B8: Fuel & Mileage | C8: Fuel - July | D8: 142.75 | E8: Card
A9: 46239 | B9: Insurance | C9: General liability - monthly | D9: 89 | E9: Bank Transfer
A10: 46246 | B10: Equipment | C10: HEPA canister vacuum | D10: 329 | E10: Card | F10: Keep receipt for taxes
A11: 46265 | B11: Fuel & Mileage | C11: Fuel - August | D11: 151.2 | E11: Card
A12: 46270 | B12: Insurance | C12: General liability - monthly | D12: 89 | E12: Bank Transfer
A13: 46274 | B13: Phone & Software | C13: Scheduling app + business phone line | D13: 45 | E13: Card
A14: 46285 | B14: Cleaning Supplies | C14: Restock - glass cleaner, mop heads | D14: 112.35 | E14: Card

Sheet Monthly P&L
A1: =Settings!$B$5&" - Monthly Profit & Loss "&Settings!$B$12 -> Sparkle & Shine Cleaning Co. - Monthly Profit & Loss 2026
A2: Revenue = Completed jobs by job date (before tax). Cash collected = payments by payment date. Change the year on Settings.
A4: Month | B4: Jobs completed | C4: ="Revenue (before tax) ("&Settings!$B$10&")" -> Revenue (before tax) ($) | D4: ="Sales tax collected ("&Settings!$B$10&")" -> Sales tax collected ($) | E4: ="Expenses ("&Settings!$B$10&")" -> Expenses ($) | F4: ="Net profit ("&Settings!$B$10&")" -> Net profit ($) | G4: Profit margin | H4: ="Cash collected ("&Settings!$B$10&")" -> Cash collected ($)
A5: =DATE(Settings!$B$12,1,1) -> 46023 | B5: =COUNTIFS(Jobs!$G$5:$G$504,"Completed",Jobs!$A$5:$A$504,">="&$A5,Jobs!$A$5:$A$504,"<="&EOMONTH($A5,0)) -> 0 | C5: =SUMIFS(Jobs!$L$5:$L$504,Jobs!$G$5:$G$504,"Completed",Jobs!$A$5:$A$504,">="&$A5,Jobs!$A$5:$A$504,"<="&EOMONTH($A5,0)) -> 0 | D5: =SUMIFS(Jobs!$M$5:$M$504,Jobs!$G$5:$G$504,"Completed",Jobs!$A$5:$A$504,">="&$A5,Jobs!$A$5:$A$504,"<="&EOMONTH($A5,0)) -> 0 | E5: =SUMIFS(Expenses!$D$5:$D$504,Expenses!$A$5:$A$504,">="&$A5,Expenses!$A$5:$A$504,"<="&EOMONTH($A5,0)) -> 0 | F5: =$C5-$E5 -> 0 | G5: =IF($C5=0,"",$F5/$C5) | H5: =SUMIFS(Invoices!$P$5:$P$1004,Invoices!$M$5:$M$1004,">="&$A5,Invoices!$M$5:$M$1004,"<="&EOMONTH($A5,0)) -> 0
A6: =DATE(Settings!$B$12,2,1) -> 46054 | B6: =COUNTIFS(Jobs!$G$5:$G$504,"Completed",Jobs!$A$5:$A$504,">="&$A6,Jobs!$A$5:$A$504,"<="&EOMONTH($A6,0)) -> 0 | C6: =SUMIFS(Jobs!$L$5:$L$504,Jobs!$G$5:$G$504,"Completed",Jobs!$A$5:$A$504,">="&$A6,Jobs!$A$5:$A$504,"<="&EOMONTH($A6,0)) -> 0 | D6: =SUMIFS(Jobs!$M$5:$M$504,Jobs!$G$5:$G$504,"Completed",Jobs!$A$5:$A$504,">="&$A6,Jobs!$A$5:$A$504,"<="&EOMONTH($A6,0)) -> 0 | E6: =SUMIFS(Expenses!$D$5:$D$504,Expenses!$A$5:$A$504,">="&$A6,Expenses!$A$5:$A$504,"<="&EOMONTH($A6,0)) -> 0 | F6: =$C6-$E6 -> 0 | G6: =IF($C6=0,"",$F6/$C6) | H6: =SUMIFS(Invoices!$P$5:$P$1004,Invoices!$M$5:$M$1004,">="&$A6,Invoices!$M$5:$M$1004,"<="&EOMONTH($A6,0)) -> 0
A7: =DATE(Settings!$B$12,3,1) -> 46082 | B7: =COUNTIFS(Jobs!$G$5:$G$504,"Completed",Jobs!$A$5:$A$504,">="&$A7,Jobs!$A$5:$A$504,"<="&EOMONTH($A7,0)) -> 0 | C7: =SUMIFS(Jobs!$L$5:$L$504,Jobs!$G$5:$G$504,"Completed",Jobs!$A$5:$A$504,">="&$A7,Jobs!$A$5:$A$504,"<="&EOMONTH($A7,0)) -> 0 | D7: =SUMIFS(Jobs!$M$5:$M$504,Jobs!$G$5:$G$504,"Completed",Jobs!$A$5:$A$504,">="&$A7,Jobs!$A$5:$A$504,"<="&EOMONTH($A7,0)) -> 0 | E7: =SUMIFS(Expenses!$D$5:$D$504,Expenses!$A$5:$A$504,">="&$A7,Expenses!$A$5:$A$504,"<="&EOMONTH($A7,0)) -> 0 | F7: =$C7-$E7 -> 0 | G7: =IF($C7=0,"",$F7/$C7) | H7: =SUMIFS(Invoices!$P$5:$P$1004,Invoices!$M$5:$M$1004,">="&$A7,Invoices!$M$5:$M$1004,"<="&EOMONTH($A7,0)) -> 0
A8: =DATE(Settings!$B$12,4,1) -> 46113 | B8: =COUNTIFS(Jobs!$G$5:$G$504,"Completed",Jobs!$A$5:$A$504,">="&$A8,Jobs!$A$5:$A$504,"<="&EOMONTH($A8,0)) -> 0 | C8: =SUMIFS(Jobs!$L$5:$L$504,Jobs!$G$5:$G$504,"Completed",Jobs!$A$5:$A$504,">="&$A8,Jobs!$A$5:$A$504,"<="&EOMONTH($A8,0)) -> 0 | D8: =SUMIFS(Jobs!$M$5:$M$504,Jobs!$G$5:$G$504,"Completed",Jobs!$A$5:$A$504,">="&$A8,Jobs!$A$5:$A$504,"<="&EOMONTH($A8,0)) -> 0 | E8: =SUMIFS(Expenses!$D$5:$D$504,Expenses!$A$5:$A$504,">="&$A8,Expenses!$A$5:$A$504,"<="&EOMONTH($A8,0)) -> 0 | F8: =$C8-$E8 -> 0 | G8: =IF($C8=0,"",$F8/$C8) | H8: =SUMIFS(Invoices!$P$5:$P$1004,Invoices!$M$5:$M$1004,">="&$A8,Invoices!$M$5:$M$1004,"<="&EOMONTH($A8,0)) -> 0
A9: =DATE(Settings!$B$12,5,1) -> 46143 | B9: =COUNTIFS(Jobs!$G$5:$G$504,"Completed",Jobs!$A$5:$A$504,">="&$A9,Jobs!$A$5:$A$504,"<="&EOMONTH($A9,0)) -> 0 | C9: =SUMIFS(Jobs!$L$5:$L$504,Jobs!$G$5:$G$504,"Completed",Jobs!$A$5:$A$504,">="&$A9,Jobs!$A$5:$A$504,"<="&EOMONTH($A9,0)) -> 0 | D9: =SUMIFS(Jobs!$M$5:$M$504,Jobs!$G$5:$G$504,"Completed",Jobs!$A$5:$A$504,">="&$A9,Jobs!$A$5:$A$504,"<="&EOMONTH($A9,0)) -> 0 | E9: =SUMIFS(Expenses!$D$5:$D$504,Expenses!$A$5:$A$504,">="&$A9,Expenses!$A$5:$A$504,"<="&EOMONTH($A9,0)) -> 0 | F9: =$C9-$E9 -> 0 | G9: =IF($C9=0,"",$F9/$C9) | H9: =SUMIFS(Invoices!$P$5:$P$1004,Invoices!$M$5:$M$1004,">="&$A9,Invoices!$M$5:$M$1004,"<="&EOMONTH($A9,0)) -> 0
A10: =DATE(Settings!$B$12,6,1) -> 46174 | B10: =COUNTIFS(Jobs!$G$5:$G$504,"Completed",Jobs!$A$5:$A$504,">="&$A10,Jobs!$A$5:$A$504,"<="&EOMONTH($A10,0)) -> 0 | C10: =SUMIFS(Jobs!$L$5:$L$504,Jobs!$G$5:$G$504,"Completed",Jobs!$A$5:$A$504,">="&$A10,Jobs!$A$5:$A$504,"<="&EOMONTH($A10,0)) -> 0 | D10: =SUMIFS(Jobs!$M$5:$M$504,Jobs!$G$5:$G$504,"Completed",Jobs!$A$5:$A$504,">="&$A10,Jobs!$A$5:$A$504,"<="&EOMONTH($A10,0)) -> 0 | E10: =SUMIFS(Expenses!$D$5:$D$504,Expenses!$A$5:$A$504,">="&$A10,Expenses!$A$5:$A$504,"<="&EOMONTH($A10,0)) -> 0 | F10: =$C10-$E10 -> 0 | G10: =IF($C10=0,"",$F10/$C10) | H10: =SUMIFS(Invoices!$P$5:$P$1004,Invoices!$M$5:$M$1004,">="&$A10,Invoices!$M$5:$M$1004,"<="&EOMONTH($A10,0)) -> 0
A11: =DATE(Settings!$B$12,7,1) -> 46204 | B11: =COUNTIFS(Jobs!$G$5:$G$504,"Completed",Jobs!$A$5:$A$504,">="&$A11,Jobs!$A$5:$A$504,"<="&EOMONTH($A11,0)) -> 10 | C11: =SUMIFS(Jobs!$L$5:$L$504,Jobs!$G$5:$G$504,"Completed",Jobs!$A$5:$A$504,">="&$A11,Jobs!$A$5:$A$504,"<="&EOMONTH($A11,0)) -> 1435 | D11: =SUMIFS(Jobs!$M$5:$M$504,Jobs!$G$5:$G$504,"Completed",Jobs!$A$5:$A$504,">="&$A11,Jobs!$A$5:$A$504,"<="&EOMONTH($A11,0)) -> 86.1 | E11: =SUMIFS(Expenses!$D$5:$D$504,Expenses!$A$5:$A$504,">="&$A11,Expenses!$A$5:$A$504,"<="&EOMONTH($A11,0)) -> 483.14 | F11: =$C11-$E11 -> 951.86 | G11: =IF($C11=0,"",$F11/$C11) -> 0.66331707 | H11: =SUMIFS(Invoices!$P$5:$P$1004,Invoices!$M$5:$M$1004,">="&$A11,Invoices!$M$5:$M$1004,"<="&EOMONTH($A11,0)) -> 1393.9
A12: =DATE(Settings!$B$12,8,1) -> 46235 | B12: =COUNTIFS(Jobs!$G$5:$G$504,"Completed",Jobs!$A$5:$A$504,">="&$A12,Jobs!$A$5:$A$504,"<="&EOMONTH($A12,0)) -> 9 | C12: =SUMIFS(Jobs!$L$5:$L$504,Jobs!$G$5:$G$504,"Completed",Jobs!$A$5:$A$504,">="&$A12,Jobs!$A$5:$A$504,"<="&EOMONTH($A12,0)) -> 1325 | D12: =SUMIFS(Jobs!$M$5:$M$504,Jobs!$G$5:$G$504,"Completed",Jobs!$A$5:$A$504,">="&$A12,Jobs!$A$5:$A$504,"<="&EOMONTH($A12,0)) -> 79.5 | E12: =SUMIFS(Expenses!$D$5:$D$504,Expenses!$A$5:$A$504,">="&$A12,Expenses!$A$5:$A$504,"<="&EOMONTH($A12,0)) -> 569.2 | F12: =$C12-$E12 -> 755.8 | G12: =IF($C12=0,"",$F12/$C12) -> 0.57041509 | H12: =SUMIFS(Invoices!$P$5:$P$1004,Invoices!$M$5:$M$1004,">="&$A12,Invoices!$M$5:$M$1004,"<="&EOMONTH($A12,0)) -> 1244.1
A13: =DATE(Settings!$B$12,9,1) -> 46266 | B13: =COUNTIFS(Jobs!$G$5:$G$504,"Completed",Jobs!$A$5:$A$504,">="&$A13,Jobs!$A$5:$A$504,"<="&EOMONTH($A13,0)) -> 8 | C13: =SUMIFS(Jobs!$L$5:$L$504,Jobs!$G$5:$G$504,"Completed",Jobs!$A$5:$A$504,">="&$A13,Jobs!$A$5:$A$504,"<="&EOMONTH($A13,0)) -> 1182.5 | D13: =SUMIFS(Jobs!$M$5:$M$504,Jobs!$G$5:$G$504,"Completed",Jobs!$A$5:$A$504,">="&$A13,Jobs!$A$5:$A$504,"<="&EOMONTH($A13,0)) -> 70.95 | E13: =SUMIFS(Expenses!$D$5:$D$504,Expenses!$A$5:$A$504,">="&$A13,Expenses!$A$5:$A$504,"<="&EOMONTH($A13,0)) -> 246.35 | F13: =$C13-$E13 -> 936.15 | G13: =IF($C13=0,"",$F13/$C13) -> 0.79167019 | H13: =SUMIFS(Invoices!$P$5:$P$1004,Invoices!$M$5:$M$1004,">="&$A13,Invoices!$M$5:$M$1004,"<="&EOMONTH($A13,0)) -> 484.95
A14: =DATE(Settings!$B$12,10,1) -> 46296 | B14: =COUNTIFS(Jobs!$G$5:$G$504,"Completed",Jobs!$A$5:$A$504,">="&$A14,Jobs!$A$5:$A$504,"<="&EOMONTH($A14,0)) -> 0 | C14: =SUMIFS(Jobs!$L$5:$L$504,Jobs!$G$5:$G$504,"Completed",Jobs!$A$5:$A$504,">="&$A14,Jobs!$A$5:$A$504,"<="&EOMONTH($A14,0)) -> 0 | D14: =SUMIFS(Jobs!$M$5:$M$504,Jobs!$G$5:$G$504,"Completed",Jobs!$A$5:$A$504,">="&$A14,Jobs!$A$5:$A$504,"<="&EOMONTH($A14,0)) -> 0 | E14: =SUMIFS(Expenses!$D$5:$D$504,Expenses!$A$5:$A$504,">="&$A14,Expenses!$A$5:$A$504,"<="&EOMONTH($A14,0)) -> 0 | F14: =$C14-$E14 -> 0 | G14: =IF($C14=0,"",$F14/$C14) | H14: =SUMIFS(Invoices!$P$5:$P$1004,Invoices!$M$5:$M$1004,">="&$A14,Invoices!$M$5:$M$1004,"<="&EOMONTH($A14,0)) -> 0
A15: =DATE(Settings!$B$12,11,1) -> 46327 | B15: =COUNTIFS(Jobs!$G$5:$G$504,"Completed",Jobs!$A$5:$A$504,">="&$A15,Jobs!$A$5:$A$504,"<="&EOMONTH($A15,0)) -> 0 | C15: =SUMIFS(Jobs!$L$5:$L$504,Jobs!$G$5:$G$504,"Completed",Jobs!$A$5:$A$504,">="&$A15,Jobs!$A$5:$A$504,"<="&EOMONTH($A15,0)) -> 0 | D15: =SUMIFS(Jobs!$M$5:$M$504,Jobs!$G$5:$G$504,"Completed",Jobs!$A$5:$A$504,">="&$A15,Jobs!$A$5:$A$504,"<="&EOMONTH($A15,0)) -> 0 | E15: =SUMIFS(Expenses!$D$5:$D$504,Expenses!$A$5:$A$504,">="&$A15,Expenses!$A$5:$A$504,"<="&EOMONTH($A15,0)) -> 0 | F15: =$C15-$E15 -> 0 | G15: =IF($C15=0,"",$F15/$C15) | H15: =SUMIFS(Invoices!$P$5:$P$1004,Invoices!$M$5:$M$1004,">="&$A15,Invoices!$M$5:$M$1004,"<="&EOMONTH($A15,0)) -> 0
A16: =DATE(Settings!$B$12,12,1) -> 46357 | B16: =COUNTIFS(Jobs!$G$5:$G$504,"Completed",Jobs!$A$5:$A$504,">="&$A16,Jobs!$A$5:$A$504,"<="&EOMONTH($A16,0)) -> 0 | C16: =SUMIFS(Jobs!$L$5:$L$504,Jobs!$G$5:$G$504,"Completed",Jobs!$A$5:$A$504,">="&$A16,Jobs!$A$5:$A$504,"<="&EOMONTH($A16,0)) -> 0 | D16: =SUMIFS(Jobs!$M$5:$M$504,Jobs!$G$5:$G$504,"Completed",Jobs!$A$5:$A$504,">="&$A16,Jobs!$A$5:$A$504,"<="&EOMONTH($A16,0)) -> 0 | E16: =SUMIFS(Expenses!$D$5:$D$504,Expenses!$A$5:$A$504,">="&$A16,Expenses!$A$5:$A$504,"<="&EOMONTH($A16,0)) -> 0 | F16: =$C16-$E16 -> 0 | G16: =IF($C16=0,"",$F16/$C16) | H16: =SUMIFS(Invoices!$P$5:$P$1004,Invoices!$M$5:$M$1004,">="&$A16,Invoices!$M$5:$M$1004,"<="&EOMONTH($A16,0)) -> 0
A17: Year total | B17: =SUM(B5:B16) -> 27 | C17: =SUM(C5:C16) -> 3942.5 | D17: =SUM(D5:D16) -> 236.55 | E17: =SUM(E5:E16) -> 1298.69 | F17: =SUM(F5:F16) -> 2643.81 | G17: =IF($C17=0,"",$F17/$C17) -> 0.67059226 | H17: =SUM(H5:H16) -> 3122.95
A19: Expenses by category
A20: Category | B20: Jan | C20: Feb | D20: Mar | E20: Apr | F20: May | G20: Jun | H20: Jul | I20: Aug | J20: Sep | K20: Oct | L20: Nov | M20: Dec | N20: Year total
A21: =IF(Settings!$H$5="","",Settings!$H$5) -> Cleaning Supplies | B21: =IF($A21="","",SUMIFS(Expenses!$D$5:$D$504,Expenses!$B$5:$B$504,$A21,Expenses!$A$5:$A$504,">="&DATE(Settings!$B$12,1,1),Expenses!$A$5:$A$504,"<="&EOMONTH(DATE(Settings!$B$12,1,1),0))) -> 0 | C21: =IF($A21="","",SUMIFS(Expenses!$D$5:$D$504,Expenses!$B$5:$B$504,$A21,Expenses!$A$5:$A$504,">="&DATE(Settings!$B$12,2,1),Expenses!$A$5:$A$504,"<="&EOMONTH(DATE(Settings!$B$12,2,1),0))) -> 0 | D21: =IF($A21="","",SUMIFS(Expenses!$D$5:$D$504,Expenses!$B$5:$B$504,$A21,Expenses!$A$5:$A$504,">="&DATE(Settings!$B$12,3,1),Expenses!$A$5:$A$504,"<="&EOMONTH(DATE(Settings!$B$12,3,1),0))) -> 0 | E21: =IF($A21="","",SUMIFS(Expenses!$D$5:$D$504,Expenses!$B$5:$B$504,$A21,Expenses!$A$5:$A$504,">="&DATE(Settings!$B$12,4,1),Expenses!$A$5:$A$504,"<="&EOMONTH(DATE(Settings!$B$12,4,1),0))) -> 0 | F21: =IF($A21="","",SUMIFS(Expenses!$D$5:$D$504,Expenses!$B$5:$B$504,$A21,Expenses!$A$5:$A$504,">="&DATE(Settings!$B$12,5,1),Expenses!$A$5:$A$504,"<="&EOMONTH(DATE(Settings!$B$12,5,1),0))) -> 0 | G21: =IF($A21="","",SUMIFS(Expenses!$D$5:$D$504,Expenses!$B$5:$B$504,$A21,Expenses!$A$5:$A$504,">="&DATE(Settings!$B$12,6,1),Expenses!$A$5:$A$504,"<="&EOMONTH(DATE(Settings!$B$12,6,1),0))) -> 0 | H21: =IF($A21="","",SUMIFS(Expenses!$D$5:$D$504,Expenses!$B$5:$B$504,$A21,Expenses!$A$5:$A$504,">="&DATE(Settings!$B$12,7,1),Expenses!$A$5:$A$504,"<="&EOMONTH(DATE(Settings!$B$12,7,1),0))) -> 186.4 | I21: =IF($A21="","",SUMIFS(Expenses!$D$5:$D$504,Expenses!$B$5:$B$504,$A21,Expenses!$A$5:$A$504,">="&DATE(Settings!$B$12,8,1),Expenses!$A$5:$A$504,"<="&EOMONTH(DATE(Settings!$B$12,8,1),0))) -> 0 | J21: =IF($A21="","",SUMIFS(Expenses!$D$5:$D$504,Expenses!$B$5:$B$504,$A21,Expenses!$A$5:$A$504,">="&DATE(Settings!$B$12,9,1),Expenses!$A$5:$A$504,"<="&EOMONTH(DATE(Settings!$B$12,9,1),0))) -> 112.35 | K21: =IF($A21="","",SUMIFS(Expenses!$D$5:$D$504,Expenses!$B$5:$B$504,$A21,Expenses!$A$5:$A$504,">="&DATE(Settings!$B$12,10,1),Expenses!$A$5:$A$504,"<="&EOMONTH(DATE(Settings!$B$12,10,1),0))) -> 0 | L21: =IF($A21="","",SUMIFS(Expenses!$D$5:$D$504,Expenses!$B$5:$B$504,$A21,Expenses!$A$5:$A$504,">="&DATE(Settings!$B$12,11,1),Expenses!$A$5:$A$504,"<="&EOMONTH(DATE(Settings!$B$12,11,1),0))) -> 0 | M21: =IF($A21="","",SUMIFS(Expenses!$D$5:$D$504,Expenses!$B$5:$B$504,$A21,Expenses!$A$5:$A$504,">="&DATE(Settings!$B$12,12,1),Expenses!$A$5:$A$504,"<="&EOMONTH(DATE(Settings!$B$12,12,1),0))) -> 0 | N21: =IF($A21="","",SUM(B21:M21)) -> 298.75
A22: =IF(Settings!$H$6="","",Settings!$H$6) -> Equipment | B22: =IF($A22="","",SUMIFS(Expenses!$D$5:$D$504,Expenses!$B$5:$B$504,$A22,Expenses!$A$5:$A$504,">="&DATE(Settings!$B$12,1,1),Expenses!$A$5:$A$504,"<="&EOMONTH(DATE(Settings!$B$12,1,1),0))) -> 0 | C22: =IF($A22="","",SUMIFS(Expenses!$D$5:$D$504,Expenses!$B$5:$B$504,$A22,Expenses!$A$5:$A$504,">="&DATE(Settings!$B$12,2,1),Expenses!$A$5:$A$504,"<="&EOMONTH(DATE(Settings!$B$12,2,1),0))) -> 0 | D22: =IF($A22="","",SUMIFS(Expenses!$D$5:$D$504,Expenses!$B$5:$B$504,$A22,Expenses!$A$5:$A$504,">="&DATE(Settings!$B$12,3,1),Expenses!$A$5:$A$504,"<="&EOMONTH(DATE(Settings!$B$12,3,1),0))) -> 0 | E22: =IF($A22="","",SUMIFS(Expenses!$D$5:$D$504,Expenses!$B$5:$B$504,$A22,Expenses!$A$5:$A$504,">="&DATE(Settings!$B$12,4,1),Expenses!$A$5:$A$504,"<="&EOMONTH(DATE(Settings!$B$12,4,1),0))) -> 0 | F22: =IF($A22="","",SUMIFS(Expenses!$D$5:$D$504,Expenses!$B$5:$B$504,$A22,Expenses!$A$5:$A$504,">="&DATE(Settings!$B$12,5,1),Expenses!$A$5:$A$504,"<="&EOMONTH(DATE(Settings!$B$12,5,1),0))) -> 0 | G22: =IF($A22="","",SUMIFS(Expenses!$D$5:$D$504,Expenses!$B$5:$B$504,$A22,Expenses!$A$5:$A$504,">="&DATE(Settings!$B$12,6,1),Expenses!$A$5:$A$504,"<="&EOMONTH(DATE(Settings!$B$12,6,1),0))) -> 0 | H22: =IF($A22="","",SUMIFS(Expenses!$D$5:$D$504,Expenses!$B$5:$B$504,$A22,Expenses!$A$5:$A$504,">="&DATE(Settings!$B$12,7,1),Expenses!$A$5:$A$504,"<="&EOMONTH(DATE(Settings!$B$12,7,1),0))) -> 0 | I22: =IF($A22="","",SUMIFS(Expenses!$D$5:$D$504,Expenses!$B$5:$B$504,$A22,Expenses!$A$5:$A$504,">="&DATE(Settings!$B$12,8,1),Expenses!$A$5:$A$504,"<="&EOMONTH(DATE(Settings!$B$12,8,1),0))) -> 329 | J22: =IF($A22="","",SUMIFS(Expenses!$D$5:$D$504,Expenses!$B$5:$B$504,$A22,Expenses!$A$5:$A$504,">="&DATE(Settings!$B$12,9,1),Expenses!$A$5:$A$504,"<="&EOMONTH(DATE(Settings!$B$12,9,1),0))) -> 0 | K22: =IF($A22="","",SUMIFS(Expenses!$D$5:$D$504,Expenses!$B$5:$B$504,$A22,Expenses!$A$5:$A$504,">="&DATE(Settings!$B$12,10,1),Expenses!$A$5:$A$504,"<="&EOMONTH(DATE(Settings!$B$12,10,1),0))) -> 0 | L22: =IF($A22="","",SUMIFS(Expenses!$D$5:$D$504,Expenses!$B$5:$B$504,$A22,Expenses!$A$5:$A$504,">="&DATE(Settings!$B$12,11,1),Expenses!$A$5:$A$504,"<="&EOMONTH(DATE(Settings!$B$12,11,1),0))) -> 0 | M22: =IF($A22="","",SUMIFS(Expenses!$D$5:$D$504,Expenses!$B$5:$B$504,$A22,Expenses!$A$5:$A$504,">="&DATE(Settings!$B$12,12,1),Expenses!$A$5:$A$504,"<="&EOMONTH(DATE(Settings!$B$12,12,1),0))) -> 0 | N22: =IF($A22="","",SUM(B22:M22)) -> 329
A23: =IF(Settings!$H$7="","",Settings!$H$7) -> Fuel & Mileage | B23: =IF($A23="","",SUMIFS(Expenses!$D$5:$D$504,Expenses!$B$5:$B$504,$A23,Expenses!$A$5:$A$504,">="&DATE(Settings!$B$12,1,1),Expenses!$A$5:$A$504,"<="&EOMONTH(DATE(Settings!$B$12,1,1),0))) -> 0 | C23: =IF($A23="","",SUMIFS(Expenses!$D$5:$D$504,Expenses!$B$5:$B$504,$A23,Expenses!$A$5:$A$504,">="&DATE(Settings!$B$12,2,1),Expenses!$A$5:$A$504,"<="&EOMONTH(DATE(Settings!$B$12,2,1),0))) -> 0 | D23: =IF($A23="","",SUMIFS(Expenses!$D$5:$D$504,Expenses!$B$5:$B$504,$A23,Expenses!$A$5:$A$504,">="&DATE(Settings!$B$12,3,1),Expenses!$A$5:$A$504,"<="&EOMONTH(DATE(Settings!$B$12,3,1),0))) -> 0 | E23: =IF($A23="","",SUMIFS(Expenses!$D$5:$D$504,Expenses!$B$5:$B$504,$A23,Expenses!$A$5:$A$504,">="&DATE(Settings!$B$12,4,1),Expenses!$A$5:$A$504,"<="&EOMONTH(DATE(Settings!$B$12,4,1),0))) -> 0 | F23: =IF($A23="","",SUMIFS(Expenses!$D$5:$D$504,Expenses!$B$5:$B$504,$A23,Expenses!$A$5:$A$504,">="&DATE(Settings!$B$12,5,1),Expenses!$A$5:$A$504,"<="&EOMONTH(DATE(Settings!$B$12,5,1),0))) -> 0 | G23: =IF($A23="","",SUMIFS(Expenses!$D$5:$D$504,Expenses!$B$5:$B$504,$A23,Expenses!$A$5:$A$504,">="&DATE(Settings!$B$12,6,1),Expenses!$A$5:$A$504,"<="&EOMONTH(DATE(Settings!$B$12,6,1),0))) -> 0 | H23: =IF($A23="","",SUMIFS(Expenses!$D$5:$D$504,Expenses!$B$5:$B$504,$A23,Expenses!$A$5:$A$504,">="&DATE(Settings!$B$12,7,1),Expenses!$A$5:$A$504,"<="&EOMONTH(DATE(Settings!$B$12,7,1),0))) -> 142.75 | I23: =IF($A23="","",SUMIFS(Expenses!$D$5:$D$504,Expenses!$B$5:$B$504,$A23,Expenses!$A$5:$A$504,">="&DATE(Settings!$B$12,8,1),Expenses!$A$5:$A$504,"<="&EOMONTH(DATE(Settings!$B$12,8,1),0))) -> 151.2 | J23: =IF($A23="","",SUMIFS(Expenses!$D$5:$D$504,Expenses!$B$5:$B$504,$A23,Expenses!$A$5:$A$504,">="&DATE(Settings!$B$12,9,1),Expenses!$A$5:$A$504,"<="&EOMONTH(DATE(Settings!$B$12,9,1),0))) -> 0 | K23: =IF($A23="","",SUMIFS(Expenses!$D$5:$D$504,Expenses!$B$5:$B$504,$A23,Expenses!$A$5:$A$504,">="&DATE(Settings!$B$12,10,1),Expenses!$A$5:$A$504,"<="&EOMONTH(DATE(Settings!$B$12,10,1),0))) -> 0 | L23: =IF($A23="","",SUMIFS(Expenses!$D$5:$D$504,Expenses!$B$5:$B$504,$A23,Expenses!$A$5:$A$504,">="&DATE(Settings!$B$12,11,1),Expenses!$A$5:$A$504,"<="&EOMONTH(DATE(Settings!$B$12,11,1),0))) -> 0 | M23: =IF($A23="","",SUMIFS(Expenses!$D$5:$D$504,Expenses!$B$5:$B$504,$A23,Expenses!$A$5:$A$504,">="&DATE(Settings!$B$12,12,1),Expenses!$A$5:$A$504,"<="&EOMONTH(DATE(Settings!$B$12,12,1),0))) -> 0 | N23: =IF($A23="","",SUM(B23:M23)) -> 293.95
A24: =IF(Settings!$H$8="","",Settings!$H$8) -> Wages & Contractors | B24: =IF($A24="","",SUMIFS(Expenses!$D$5:$D$504,Expenses!$B$5:$B$504,$A24,Expenses!$A$5:$A$504,">="&DATE(Settings!$B$12,1,1),Expenses!$A$5:$A$504,"<="&EOMONTH(DATE(Settings!$B$12,1,1),0))) -> 0 | C24: =IF($A24="","",SUMIFS(Expenses!$D$5:$D$504,Expenses!$B$5:$B$504,$A24,Expenses!$A$5:$A$504,">="&DATE(Settings!$B$12,2,1),Expenses!$A$5:$A$504,"<="&EOMONTH(DATE(Settings!$B$12,2,1),0))) -> 0 | D24: =IF($A24="","",SUMIFS(Expenses!$D$5:$D$504,Expenses!$B$5:$B$504,$A24,Expenses!$A$5:$A$504,">="&DATE(Settings!$B$12,3,1),Expenses!$A$5:$A$504,"<="&EOMONTH(DATE(Settings!$B$12,3,1),0))) -> 0 | E24: =IF($A24="","",SUMIFS(Expenses!$D$5:$D$504,Expenses!$B$5:$B$504,$A24,Expenses!$A$5:$A$504,">="&DATE(Settings!$B$12,4,1),Expenses!$A$5:$A$504,"<="&EOMONTH(DATE(Settings!$B$12,4,1),0))) -> 0 | F24: =IF($A24="","",SUMIFS(Expenses!$D$5:$D$504,Expenses!$B$5:$B$504,$A24,Expenses!$A$5:$A$504,">="&DATE(Settings!$B$12,5,1),Expenses!$A$5:$A$504,"<="&EOMONTH(DATE(Settings!$B$12,5,1),0))) -> 0 | G24: =IF($A24="","",SUMIFS(Expenses!$D$5:$D$504,Expenses!$B$5:$B$504,$A24,Expenses!$A$5:$A$504,">="&DATE(Settings!$B$12,6,1),Expenses!$A$5:$A$504,"<="&EOMONTH(DATE(Settings!$B$12,6,1),0))) -> 0 | H24: =IF($A24="","",SUMIFS(Expenses!$D$5:$D$504,Expenses!$B$5:$B$504,$A24,Expenses!$A$5:$A$504,">="&DATE(Settings!$B$12,7,1),Expenses!$A$5:$A$504,"<="&EOMONTH(DATE(Settings!$B$12,7,1),0))) -> 0 | I24: =IF($A24="","",SUMIFS(Expenses!$D$5:$D$504,Expenses!$B$5:$B$504,$A24,Expenses!$A$5:$A$504,">="&DATE(Settings!$B$12,8,1),Expenses!$A$5:$A$504,"<="&EOMONTH(DATE(Settings!$B$12,8,1),0))) -> 0 | J24: =IF($A24="","",SUMIFS(Expenses!$D$5:$D$504,Expenses!$B$5:$B$504,$A24,Expenses!$A$5:$A$504,">="&DATE(Settings!$B$12,9,1),Expenses!$A$5:$A$504,"<="&EOMONTH(DATE(Settings!$B$12,9,1),0))) -> 0 | K24: =IF($A24="","",SUMIFS(Expenses!$D$5:$D$504,Expenses!$B$5:$B$504,$A24,Expenses!$A$5:$A$504,">="&DATE(Settings!$B$12,10,1),Expenses!$A$5:$A$504,"<="&EOMONTH(DATE(Settings!$B$12,10,1),0))) -> 0 | L24: =IF($A24="","",SUMIFS(Expenses!$D$5:$D$504,Expenses!$B$5:$B$504,$A24,Expenses!$A$5:$A$504,">="&DATE(Settings!$B$12,11,1),Expenses!$A$5:$A$504,"<="&EOMONTH(DATE(Settings!$B$12,11,1),0))) -> 0 | M24: =IF($A24="","",SUMIFS(Expenses!$D$5:$D$504,Expenses!$B$5:$B$504,$A24,Expenses!$A$5:$A$504,">="&DATE(Settings!$B$12,12,1),Expenses!$A$5:$A$504,"<="&EOMONTH(DATE(Settings!$B$12,12,1),0))) -> 0 | N24: =IF($A24="","",SUM(B24:M24)) -> 0
A25: =IF(Settings!$H$9="","",Settings!$H$9) -> Insurance | B25: =IF($A25="","",SUMIFS(Expenses!$D$5:$D$504,Expenses!$B$5:$B$504,$A25,Expenses!$A$5:$A$504,">="&DATE(Settings!$B$12,1,1),Expenses!$A$5:$A$504,"<="&EOMONTH(DATE(Settings!$B$12,1,1),0))) -> 0 | C25: =IF($A25="","",SUMIFS(Expenses!$D$5:$D$504,Expenses!$B$5:$B$504,$A25,Expenses!$A$5:$A$504,">="&DATE(Settings!$B$12,2,1),Expenses!$A$5:$A$504,"<="&EOMONTH(DATE(Settings!$B$12,2,1),0))) -> 0 | D25: =IF($A25="","",SUMIFS(Expenses!$D$5:$D$504,Expenses!$B$5:$B$504,$A25,Expenses!$A$5:$A$504,">="&DATE(Settings!$B$12,3,1),Expenses!$A$5:$A$504,"<="&EOMONTH(DATE(Settings!$B$12,3,1),0))) -> 0 | E25: =IF($A25="","",SUMIFS(Expenses!$D$5:$D$504,Expenses!$B$5:$B$504,$A25,Expenses!$A$5:$A$504,">="&DATE(Settings!$B$12,4,1),Expenses!$A$5:$A$504,"<="&EOMONTH(DATE(Settings!$B$12,4,1),0))) -> 0 | F25: =IF($A25="","",SUMIFS(Expenses!$D$5:$D$504,Expenses!$B$5:$B$504,$A25,Expenses!$A$5:$A$504,">="&DATE(Settings!$B$12,5,1),Expenses!$A$5:$A$504,"<="&EOMONTH(DATE(Settings!$B$12,5,1),0))) -> 0 | G25: =IF($A25="","",SUMIFS(Expenses!$D$5:$D$504,Expenses!$B$5:$B$504,$A25,Expenses!$A$5:$A$504,">="&DATE(Settings!$B$12,6,1),Expenses!$A$5:$A$504,"<="&EOMONTH(DATE(Settings!$B$12,6,1),0))) -> 0 | H25: =IF($A25="","",SUMIFS(Expenses!$D$5:$D$504,Expenses!$B$5:$B$504,$A25,Expenses!$A$5:$A$504,">="&DATE(Settings!$B$12,7,1),Expenses!$A$5:$A$504,"<="&EOMONTH(DATE(Settings!$B$12,7,1),0))) -> 89 | I25: =IF($A25="","",SUMIFS(Expenses!$D$5:$D$504,Expenses!$B$5:$B$504,$A25,Expenses!$A$5:$A$504,">="&DATE(Settings!$B$12,8,1),Expenses!$A$5:$A$504,"<="&EOMONTH(DATE(Settings!$B$12,8,1),0))) -> 89 | J25: =IF($A25="","",SUMIFS(Expenses!$D$5:$D$504,Expenses!$B$5:$B$504,$A25,Expenses!$A$5:$A$504,">="&DATE(Settings!$B$12,9,1),Expenses!$A$5:$A$504,"<="&EOMONTH(DATE(Settings!$B$12,9,1),0))) -> 89 | K25: =IF($A25="","",SUMIFS(Expenses!$D$5:$D$504,Expenses!$B$5:$B$504,$A25,Expenses!$A$5:$A$504,">="&DATE(Settings!$B$12,10,1),Expenses!$A$5:$A$504,"<="&EOMONTH(DATE(Settings!$B$12,10,1),0))) -> 0 | L25: =IF($A25="","",SUMIFS(Expenses!$D$5:$D$504,Expenses!$B$5:$B$504,$A25,Expenses!$A$5:$A$504,">="&DATE(Settings!$B$12,11,1),Expenses!$A$5:$A$504,"<="&EOMONTH(DATE(Settings!$B$12,11,1),0))) -> 0 | M25: =IF($A25="","",SUMIFS(Expenses!$D$5:$D$504,Expenses!$B$5:$B$504,$A25,Expenses!$A$5:$A$504,">="&DATE(Settings!$B$12,12,1),Expenses!$A$5:$A$504,"<="&EOMONTH(DATE(Settings!$B$12,12,1),0))) -> 0 | N25: =IF($A25="","",SUM(B25:M25)) -> 267
A26: =IF(Settings!$H$10="","",Settings!$H$10) -> Marketing & Advertising | B26: =IF($A26="","",SUMIFS(Expenses!$D$5:$D$504,Expenses!$B$5:$B$504,$A26,Expenses!$A$5:$A$504,">="&DATE(Settings!$B$12,1,1),Expenses!$A$5:$A$504,"<="&EOMONTH(DATE(Settings!$B$12,1,1),0))) -> 0 | C26: =IF($A26="","",SUMIFS(Expenses!$D$5:$D$504,Expenses!$B$5:$B$504,$A26,Expenses!$A$5:$A$504,">="&DATE(Settings!$B$12,2,1),Expenses!$A$5:$A$504,"<="&EOMONTH(DATE(Settings!$B$12,2,1),0))) -> 0 | D26: =IF($A26="","",SUMIFS(Expenses!$D$5:$D$504,Expenses!$B$5:$B$504,$A26,Expenses!$A$5:$A$504,">="&DATE(Settings!$B$12,3,1),Expenses!$A$5:$A$504,"<="&EOMONTH(DATE(Settings!$B$12,3,1),0))) -> 0 | E26: =IF($A26="","",SUMIFS(Expenses!$D$5:$D$504,Expenses!$B$5:$B$504,$A26,Expenses!$A$5:$A$504,">="&DATE(Settings!$B$12,4,1),Expenses!$A$5:$A$504,"<="&EOMONTH(DATE(Settings!$B$12,4,1),0))) -> 0 | F26: =IF($A26="","",SUMIFS(Expenses!$D$5:$D$504,Expenses!$B$5:$B$504,$A26,Expenses!$A$5:$A$504,">="&DATE(Settings!$B$12,5,1),Expenses!$A$5:$A$504,"<="&EOMONTH(DATE(Settings!$B$12,5,1),0))) -> 0 | G26: =IF($A26="","",SUMIFS(Expenses!$D$5:$D$504,Expenses!$B$5:$B$504,$A26,Expenses!$A$5:$A$504,">="&DATE(Settings!$B$12,6,1),Expenses!$A$5:$A$504,"<="&EOMONTH(DATE(Settings!$B$12,6,1),0))) -> 0 | H26: =IF($A26="","",SUMIFS(Expenses!$D$5:$D$504,Expenses!$B$5:$B$504,$A26,Expenses!$A$5:$A$504,">="&DATE(Settings!$B$12,7,1),Expenses!$A$5:$A$504,"<="&EOMONTH(DATE(Settings!$B$12,7,1),0))) -> 64.99 | I26: =IF($A26="","",SUMIFS(Expenses!$D$5:$D$504,Expenses!$B$5:$B$504,$A26,Expenses!$A$5:$A$504,">="&DATE(Settings!$B$12,8,1),Expenses!$A$5:$A$504,"<="&EOMONTH(DATE(Settings!$B$12,8,1),0))) -> 0 | J26: =IF($A26="","",SUMIFS(Expenses!$D$5:$D$504,Expenses!$B$5:$B$504,$A26,Expenses!$A$5:$A$504,">="&DATE(Settings!$B$12,9,1),Expenses!$A$5:$A$504,"<="&EOMONTH(DATE(Settings!$B$12,9,1),0))) -> 0 | K26: =IF($A26="","",SUMIFS(Expenses!$D$5:$D$504,Expenses!$B$5:$B$504,$A26,Expenses!$A$5:$A$504,">="&DATE(Settings!$B$12,10,1),Expenses!$A$5:$A$504,"<="&EOMONTH(DATE(Settings!$B$12,10,1),0))) -> 0 | L26: =IF($A26="","",SUMIFS(Expenses!$D$5:$D$504,Expenses!$B$5:$B$504,$A26,Expenses!$A$5:$A$504,">="&DATE(Settings!$B$12,11,1),Expenses!$A$5:$A$504,"<="&EOMONTH(DATE(Settings!$B$12,11,1),0))) -> 0 | M26: =IF($A26="","",SUMIFS(Expenses!$D$5:$D$504,Expenses!$B$5:$B$504,$A26,Expenses!$A$5:$A$504,">="&DATE(Settings!$B$12,12,1),Expenses!$A$5:$A$504,"<="&EOMONTH(DATE(Settings!$B$12,12,1),0))) -> 0 | N26: =IF($A26="","",SUM(B26:M26)) -> 64.99
A27: =IF(Settings!$H$11="","",Settings!$H$11) -> Phone & Software | B27: =IF($A27="","",SUMIFS(Expenses!$D$5:$D$504,Expenses!$B$5:$B$504,$A27,Expenses!$A$5:$A$504,">="&DATE(Settings!$B$12,1,1),Expenses!$A$5:$A$504,"<="&EOMONTH(DATE(Settings!$B$12,1,1),0))) -> 0 | C27: =IF($A27="","",SUMIFS(Expenses!$D$5:$D$504,Expenses!$B$5:$B$504,$A27,Expenses!$A$5:$A$504,">="&DATE(Settings!$B$12,2,1),Expenses!$A$5:$A$504,"<="&EOMONTH(DATE(Settings!$B$12,2,1),0))) -> 0 | D27: =IF($A27="","",SUMIFS(Expenses!$D$5:$D$504,Expenses!$B$5:$B$504,$A27,Expenses!$A$5:$A$504,">="&DATE(Settings!$B$12,3,1),Expenses!$A$5:$A$504,"<="&EOMONTH(DATE(Settings!$B$12,3,1),0))) -> 0 | E27: =IF($A27="","",SUMIFS(Expenses!$D$5:$D$504,Expenses!$B$5:$B$504,$A27,Expenses!$A$5:$A$504,">="&DATE(Settings!$B$12,4,1),Expenses!$A$5:$A$504,"<="&EOMONTH(DATE(Settings!$B$12,4,1),0))) -> 0 | F27: =IF($A27="","",SUMIFS(Expenses!$D$5:$D$504,Expenses!$B$5:$B$504,$A27,Expenses!$A$5:$A$504,">="&DATE(Settings!$B$12,5,1),Expenses!$A$5:$A$504,"<="&EOMONTH(DATE(Settings!$B$12,5,1),0))) -> 0 | G27: =IF($A27="","",SUMIFS(Expenses!$D$5:$D$504,Expenses!$B$5:$B$504,$A27,Expenses!$A$5:$A$504,">="&DATE(Settings!$B$12,6,1),Expenses!$A$5:$A$504,"<="&EOMONTH(DATE(Settings!$B$12,6,1),0))) -> 0 | H27: =IF($A27="","",SUMIFS(Expenses!$D$5:$D$504,Expenses!$B$5:$B$504,$A27,Expenses!$A$5:$A$504,">="&DATE(Settings!$B$12,7,1),Expenses!$A$5:$A$504,"<="&EOMONTH(DATE(Settings!$B$12,7,1),0))) -> 0 | I27: =IF($A27="","",SUMIFS(Expenses!$D$5:$D$504,Expenses!$B$5:$B$504,$A27,Expenses!$A$5:$A$504,">="&DATE(Settings!$B$12,8,1),Expenses!$A$5:$A$504,"<="&EOMONTH(DATE(Settings!$B$12,8,1),0))) -> 0 | J27: =IF($A27="","",SUMIFS(Expenses!$D$5:$D$504,Expenses!$B$5:$B$504,$A27,Expenses!$A$5:$A$504,">="&DATE(Settings!$B$12,9,1),Expenses!$A$5:$A$504,"<="&EOMONTH(DATE(Settings!$B$12,9,1),0))) -> 45 | K27: =IF($A27="","",SUMIFS(Expenses!$D$5:$D$504,Expenses!$B$5:$B$504,$A27,Expenses!$A$5:$A$504,">="&DATE(Settings!$B$12,10,1),Expenses!$A$5:$A$504,"<="&EOMONTH(DATE(Settings!$B$12,10,1),0))) -> 0 | L27: =IF($A27="","",SUMIFS(Expenses!$D$5:$D$504,Expenses!$B$5:$B$504,$A27,Expenses!$A$5:$A$504,">="&DATE(Settings!$B$12,11,1),Expenses!$A$5:$A$504,"<="&EOMONTH(DATE(Settings!$B$12,11,1),0))) -> 0 | M27: =IF($A27="","",SUMIFS(Expenses!$D$5:$D$504,Expenses!$B$5:$B$504,$A27,Expenses!$A$5:$A$504,">="&DATE(Settings!$B$12,12,1),Expenses!$A$5:$A$504,"<="&EOMONTH(DATE(Settings!$B$12,12,1),0))) -> 0 | N27: =IF($A27="","",SUM(B27:M27)) -> 45
A28: =IF(Settings!$H$12="","",Settings!$H$12) -> Vehicle Maintenance | B28: =IF($A28="","",SUMIFS(Expenses!$D$5:$D$504,Expenses!$B$5:$B$504,$A28,Expenses!$A$5:$A$504,">="&DATE(Settings!$B$12,1,1),Expenses!$A$5:$A$504,"<="&EOMONTH(DATE(Settings!$B$12,1,1),0))) -> 0 | C28: =IF($A28="","",SUMIFS(Expenses!$D$5:$D$504,Expenses!$B$5:$B$504,$A28,Expenses!$A$5:$A$504,">="&DATE(Settings!$B$12,2,1),Expenses!$A$5:$A$504,"<="&EOMONTH(DATE(Settings!$B$12,2,1),0))) -> 0 | D28: =IF($A28="","",SUMIFS(Expenses!$D$5:$D$504,Expenses!$B$5:$B$504,$A28,Expenses!$A$5:$A$504,">="&DATE(Settings!$B$12,3,1),Expenses!$A$5:$A$504,"<="&EOMONTH(DATE(Settings!$B$12,3,1),0))) -> 0 | E28: =IF($A28="","",SUMIFS(Expenses!$D$5:$D$504,Expenses!$B$5:$B$504,$A28,Expenses!$A$5:$A$504,">="&DATE(Settings!$B$12,4,1),Expenses!$A$5:$A$504,"<="&EOMONTH(DATE(Settings!$B$12,4,1),0))) -> 0 | F28: =IF($A28="","",SUMIFS(Expenses!$D$5:$D$504,Expenses!$B$5:$B$504,$A28,Expenses!$A$5:$A$504,">="&DATE(Settings!$B$12,5,1),Expenses!$A$5:$A$504,"<="&EOMONTH(DATE(Settings!$B$12,5,1),0))) -> 0 | G28: =IF($A28="","",SUMIFS(Expenses!$D$5:$D$504,Expenses!$B$5:$B$504,$A28,Expenses!$A$5:$A$504,">="&DATE(Settings!$B$12,6,1),Expenses!$A$5:$A$504,"<="&EOMONTH(DATE(Settings!$B$12,6,1),0))) -> 0 | H28: =IF($A28="","",SUMIFS(Expenses!$D$5:$D$504,Expenses!$B$5:$B$504,$A28,Expenses!$A$5:$A$504,">="&DATE(Settings!$B$12,7,1),Expenses!$A$5:$A$504,"<="&EOMONTH(DATE(Settings!$B$12,7,1),0))) -> 0 | I28: =IF($A28="","",SUMIFS(Expenses!$D$5:$D$504,Expenses!$B$5:$B$504,$A28,Expenses!$A$5:$A$504,">="&DATE(Settings!$B$12,8,1),Expenses!$A$5:$A$504,"<="&EOMONTH(DATE(Settings!$B$12,8,1),0))) -> 0 | J28: =IF($A28="","",SUMIFS(Expenses!$D$5:$D$504,Expenses!$B$5:$B$504,$A28,Expenses!$A$5:$A$504,">="&DATE(Settings!$B$12,9,1),Expenses!$A$5:$A$504,"<="&EOMONTH(DATE(Settings!$B$12,9,1),0))) -> 0 | K28: =IF($A28="","",SUMIFS(Expenses!$D$5:$D$504,Expenses!$B$5:$B$504,$A28,Expenses!$A$5:$A$504,">="&DATE(Settings!$B$12,10,1),Expenses!$A$5:$A$504,"<="&EOMONTH(DATE(Settings!$B$12,10,1),0))) -> 0 | L28: =IF($A28="","",SUMIFS(Expenses!$D$5:$D$504,Expenses!$B$5:$B$504,$A28,Expenses!$A$5:$A$504,">="&DATE(Settings!$B$12,11,1),Expenses!$A$5:$A$504,"<="&EOMONTH(DATE(Settings!$B$12,11,1),0))) -> 0 | M28: =IF($A28="","",SUMIFS(Expenses!$D$5:$D$504,Expenses!$B$5:$B$504,$A28,Expenses!$A$5:$A$504,">="&DATE(Settings!$B$12,12,1),Expenses!$A$5:$A$504,"<="&EOMONTH(DATE(Settings!$B$12,12,1),0))) -> 0 | N28: =IF($A28="","",SUM(B28:M28)) -> 0
A29: =IF(Settings!$H$13="","",Settings!$H$13) -> Licenses & Fees | B29: =IF($A29="","",SUMIFS(Expenses!$D$5:$D$504,Expenses!$B$5:$B$504,$A29,Expenses!$A$5:$A$504,">="&DATE(Settings!$B$12,1,1),Expenses!$A$5:$A$504,"<="&EOMONTH(DATE(Settings!$B$12,1,1),0))) -> 0 | C29: =IF($A29="","",SUMIFS(Expenses!$D$5:$D$504,Expenses!$B$5:$B$504,$A29,Expenses!$A$5:$A$504,">="&DATE(Settings!$B$12,2,1),Expenses!$A$5:$A$504,"<="&EOMONTH(DATE(Settings!$B$12,2,1),0))) -> 0 | D29: =IF($A29="","",SUMIFS(Expenses!$D$5:$D$504,Expenses!$B$5:$B$504,$A29,Expenses!$A$5:$A$504,">="&DATE(Settings!$B$12,3,1),Expenses!$A$5:$A$504,"<="&EOMONTH(DATE(Settings!$B$12,3,1),0))) -> 0 | E29: =IF($A29="","",SUMIFS(Expenses!$D$5:$D$504,Expenses!$B$5:$B$504,$A29,Expenses!$A$5:$A$504,">="&DATE(Settings!$B$12,4,1),Expenses!$A$5:$A$504,"<="&EOMONTH(DATE(Settings!$B$12,4,1),0))) -> 0 | F29: =IF($A29="","",SUMIFS(Expenses!$D$5:$D$504,Expenses!$B$5:$B$504,$A29,Expenses!$A$5:$A$504,">="&DATE(Settings!$B$12,5,1),Expenses!$A$5:$A$504,"<="&EOMONTH(DATE(Settings!$B$12,5,1),0))) -> 0 | G29: =IF($A29="","",SUMIFS(Expenses!$D$5:$D$504,Expenses!$B$5:$B$504,$A29,Expenses!$A$5:$A$504,">="&DATE(Settings!$B$12,6,1),Expenses!$A$5:$A$504,"<="&EOMONTH(DATE(Settings!$B$12,6,1),0))) -> 0 | H29: =IF($A29="","",SUMIFS(Expenses!$D$5:$D$504,Expenses!$B$5:$B$504,$A29,Expenses!$A$5:$A$504,">="&DATE(Settings!$B$12,7,1),Expenses!$A$5:$A$504,"<="&EOMONTH(DATE(Settings!$B$12,7,1),0))) -> 0 | I29: =IF($A29="","",SUMIFS(Expenses!$D$5:$D$504,Expenses!$B$5:$B$504,$A29,Expenses!$A$5:$A$504,">="&DATE(Settings!$B$12,8,1),Expenses!$A$5:$A$504,"<="&EOMONTH(DATE(Settings!$B$12,8,1),0))) -> 0 | J29: =IF($A29="","",SUMIFS(Expenses!$D$5:$D$504,Expenses!$B$5:$B$504,$A29,Expenses!$A$5:$A$504,">="&DATE(Settings!$B$12,9,1),Expenses!$A$5:$A$504,"<="&EOMONTH(DATE(Settings!$B$12,9,1),0))) -> 0 | K29: =IF($A29="","",SUMIFS(Expenses!$D$5:$D$504,Expenses!$B$5:$B$504,$A29,Expenses!$A$5:$A$504,">="&DATE(Settings!$B$12,10,1),Expenses!$A$5:$A$504,"<="&EOMONTH(DATE(Settings!$B$12,10,1),0))) -> 0 | L29: =IF($A29="","",SUMIFS(Expenses!$D$5:$D$504,Expenses!$B$5:$B$504,$A29,Expenses!$A$5:$A$504,">="&DATE(Settings!$B$12,11,1),Expenses!$A$5:$A$504,"<="&EOMONTH(DATE(Settings!$B$12,11,1),0))) -> 0 | M29: =IF($A29="","",SUMIFS(Expenses!$D$5:$D$504,Expenses!$B$5:$B$504,$A29,Expenses!$A$5:$A$504,">="&DATE(Settings!$B$12,12,1),Expenses!$A$5:$A$504,"<="&EOMONTH(DATE(Settings!$B$12,12,1),0))) -> 0 | N29: =IF($A29="","",SUM(B29:M29)) -> 0
A30: =IF(Settings!$H$14="","",Settings!$H$14) -> Other | B30: =IF($A30="","",SUMIFS(Expenses!$D$5:$D$504,Expenses!$B$5:$B$504,$A30,Expenses!$A$5:$A$504,">="&DATE(Settings!$B$12,1,1),Expenses!$A$5:$A$504,"<="&EOMONTH(DATE(Settings!$B$12,1,1),0))) -> 0 | C30: =IF($A30="","",SUMIFS(Expenses!$D$5:$D$504,Expenses!$B$5:$B$504,$A30,Expenses!$A$5:$A$504,">="&DATE(Settings!$B$12,2,1),Expenses!$A$5:$A$504,"<="&EOMONTH(DATE(Settings!$B$12,2,1),0))) -> 0 | D30: =IF($A30="","",SUMIFS(Expenses!$D$5:$D$504,Expenses!$B$5:$B$504,$A30,Expenses!$A$5:$A$504,">="&DATE(Settings!$B$12,3,1),Expenses!$A$5:$A$504,"<="&EOMONTH(DATE(Settings!$B$12,3,1),0))) -> 0 | E30: =IF($A30="","",SUMIFS(Expenses!$D$5:$D$504,Expenses!$B$5:$B$504,$A30,Expenses!$A$5:$A$504,">="&DATE(Settings!$B$12,4,1),Expenses!$A$5:$A$504,"<="&EOMONTH(DATE(Settings!$B$12,4,1),0))) -> 0 | F30: =IF($A30="","",SUMIFS(Expenses!$D$5:$D$504,Expenses!$B$5:$B$504,$A30,Expenses!$A$5:$A$504,">="&DATE(Settings!$B$12,5,1),Expenses!$A$5:$A$504,"<="&EOMONTH(DATE(Settings!$B$12,5,1),0))) -> 0 | G30: =IF($A30="","",SUMIFS(Expenses!$D$5:$D$504,Expenses!$B$5:$B$504,$A30,Expenses!$A$5:$A$504,">="&DATE(Settings!$B$12,6,1),Expenses!$A$5:$A$504,"<="&EOMONTH(DATE(Settings!$B$12,6,1),0))) -> 0 | H30: =IF($A30="","",SUMIFS(Expenses!$D$5:$D$504,Expenses!$B$5:$B$504,$A30,Expenses!$A$5:$A$504,">="&DATE(Settings!$B$12,7,1),Expenses!$A$5:$A$504,"<="&EOMONTH(DATE(Settings!$B$12,7,1),0))) -> 0 | I30: =IF($A30="","",SUMIFS(Expenses!$D$5:$D$504,Expenses!$B$5:$B$504,$A30,Expenses!$A$5:$A$504,">="&DATE(Settings!$B$12,8,1),Expenses!$A$5:$A$504,"<="&EOMONTH(DATE(Settings!$B$12,8,1),0))) -> 0 | J30: =IF($A30="","",SUMIFS(Expenses!$D$5:$D$504,Expenses!$B$5:$B$504,$A30,Expenses!$A$5:$A$504,">="&DATE(Settings!$B$12,9,1),Expenses!$A$5:$A$504,"<="&EOMONTH(DATE(Settings!$B$12,9,1),0))) -> 0 | K30: =IF($A30="","",SUMIFS(Expenses!$D$5:$D$504,Expenses!$B$5:$B$504,$A30,Expenses!$A$5:$A$504,">="&DATE(Settings!$B$12,10,1),Expenses!$A$5:$A$504,"<="&EOMONTH(DATE(Settings!$B$12,10,1),0))) -> 0 | L30: =IF($A30="","",SUMIFS(Expenses!$D$5:$D$504,Expenses!$B$5:$B$504,$A30,Expenses!$A$5:$A$504,">="&DATE(Settings!$B$12,11,1),Expenses!$A$5:$A$504,"<="&EOMONTH(DATE(Settings!$B$12,11,1),0))) -> 0 | M30: =IF($A30="","",SUMIFS(Expenses!$D$5:$D$504,Expenses!$B$5:$B$504,$A30,Expenses!$A$5:$A$504,">="&DATE(Settings!$B$12,12,1),Expenses!$A$5:$A$504,"<="&EOMONTH(DATE(Settings!$B$12,12,1),0))) -> 0 | N30: =IF($A30="","",SUM(B30:M30)) -> 0
A31: =IF(Settings!$H$15="","",Settings!$H$15) | B31: =IF($A31="","",SUMIFS(Expenses!$D$5:$D$504,Expenses!$B$5:$B$504,$A31,Expenses!$A$5:$A$504,">="&DATE(Settings!$B$12,1,1),Expenses!$A$5:$A$504,"<="&EOMONTH(DATE(Settings!$B$12,1,1),0))) | C31: =IF($A31="","",SUMIFS(Expenses!$D$5:$D$504,Expenses!$B$5:$B$504,$A31,Expenses!$A$5:$A$504,">="&DATE(Settings!$B$12,2,1),Expenses!$A$5:$A$504,"<="&EOMONTH(DATE(Settings!$B$12,2,1),0))) | D31: =IF($A31="","",SUMIFS(Expenses!$D$5:$D$504,Expenses!$B$5:$B$504,$A31,Expenses!$A$5:$A$504,">="&DATE(Settings!$B$12,3,1),Expenses!$A$5:$A$504,"<="&EOMONTH(DATE(Settings!$B$12,3,1),0))) | E31: =IF($A31="","",SUMIFS(Expenses!$D$5:$D$504,Expenses!$B$5:$B$504,$A31,Expenses!$A$5:$A$504,">="&DATE(Settings!$B$12,4,1),Expenses!$A$5:$A$504,"<="&EOMONTH(DATE(Settings!$B$12,4,1),0))) | F31: =IF($A31="","",SUMIFS(Expenses!$D$5:$D$504,Expenses!$B$5:$B$504,$A31,Expenses!$A$5:$A$504,">="&DATE(Settings!$B$12,5,1),Expenses!$A$5:$A$504,"<="&EOMONTH(DATE(Settings!$B$12,5,1),0))) | G31: =IF($A31="","",SUMIFS(Expenses!$D$5:$D$504,Expenses!$B$5:$B$504,$A31,Expenses!$A$5:$A$504,">="&DATE(Settings!$B$12,6,1),Expenses!$A$5:$A$504,"<="&EOMONTH(DATE(Settings!$B$12,6,1),0))) | H31: =IF($A31="","",SUMIFS(Expenses!$D$5:$D$504,Expenses!$B$5:$B$504,$A31,Expenses!$A$5:$A$504,">="&DATE(Settings!$B$12,7,1),Expenses!$A$5:$A$504,"<="&EOMONTH(DATE(Settings!$B$12,7,1),0))) | I31: =IF($A31="","",SUMIFS(Expenses!$D$5:$D$504,Expenses!$B$5:$B$504,$A31,Expenses!$A$5:$A$504,">="&DATE(Settings!$B$12,8,1),Expenses!$A$5:$A$504,"<="&EOMONTH(DATE(Settings!$B$12,8,1),0))) | J31: =IF($A31="","",SUMIFS(Expenses!$D$5:$D$504,Expenses!$B$5:$B$504,$A31,Expenses!$A$5:$A$504,">="&DATE(Settings!$B$12,9,1),Expenses!$A$5:$A$504,"<="&EOMONTH(DATE(Settings!$B$12,9,1),0))) | K31: =IF($A31="","",SUMIFS(Expenses!$D$5:$D$504,Expenses!$B$5:$B$504,$A31,Expenses!$A$5:$A$504,">="&DATE(Settings!$B$12,10,1),Expenses!$A$5:$A$504,"<="&EOMONTH(DATE(Settings!$B$12,10,1),0))) | L31: =IF($A31="","",SUMIFS(Expenses!$D$5:$D$504,Expenses!$B$5:$B$504,$A31,Expenses!$A$5:$A$504,">="&DATE(Settings!$B$12,11,1),Expenses!$A$5:$A$504,"<="&EOMONTH(DATE(Settings!$B$12,11,1),0))) | M31: =IF($A31="","",SUMIFS(Expenses!$D$5:$D$504,Expenses!$B$5:$B$504,$A31,Expenses!$A$5:$A$504,">="&DATE(Settings!$B$12,12,1),Expenses!$A$5:$A$504,"<="&EOMONTH(DATE(Settings!$B$12,12,1),0))) | N31: =IF($A31="","",SUM(B31:M31))
A32: =IF(Settings!$H$16="","",Settings!$H$16) | B32: =IF($A32="","",SUMIFS(Expenses!$D$5:$D$504,Expenses!$B$5:$B$504,$A32,Expenses!$A$5:$A$504,">="&DATE(Settings!$B$12,1,1),Expenses!$A$5:$A$504,"<="&EOMONTH(DATE(Settings!$B$12,1,1),0))) | C32: =IF($A32="","",SUMIFS(Expenses!$D$5:$D$504,Expenses!$B$5:$B$504,$A32,Expenses!$A$5:$A$504,">="&DATE(Settings!$B$12,2,1),Expenses!$A$5:$A$504,"<="&EOMONTH(DATE(Settings!$B$12,2,1),0))) | D32: =IF($A32="","",SUMIFS(Expenses!$D$5:$D$504,Expenses!$B$5:$B$504,$A32,Expenses!$A$5:$A$504,">="&DATE(Settings!$B$12,3,1),Expenses!$A$5:$A$504,"<="&EOMONTH(DATE(Settings!$B$12,3,1),0))) | E32: =IF($A32="","",SUMIFS(Expenses!$D$5:$D$504,Expenses!$B$5:$B$504,$A32,Expenses!$A$5:$A$504,">="&DATE(Settings!$B$12,4,1),Expenses!$A$5:$A$504,"<="&EOMONTH(DATE(Settings!$B$12,4,1),0))) | F32: =IF($A32="","",SUMIFS(Expenses!$D$5:$D$504,Expenses!$B$5:$B$504,$A32,Expenses!$A$5:$A$504,">="&DATE(Settings!$B$12,5,1),Expenses!$A$5:$A$504,"<="&EOMONTH(DATE(Settings!$B$12,5,1),0))) | G32: =IF($A32="","",SUMIFS(Expenses!$D$5:$D$504,Expenses!$B$5:$B$504,$A32,Expenses!$A$5:$A$504,">="&DATE(Settings!$B$12,6,1),Expenses!$A$5:$A$504,"<="&EOMONTH(DATE(Settings!$B$12,6,1),0))) | H32: =IF($A32="","",SUMIFS(Expenses!$D$5:$D$504,Expenses!$B$5:$B$504,$A32,Expenses!$A$5:$A$504,">="&DATE(Settings!$B$12,7,1),Expenses!$A$5:$A$504,"<="&EOMONTH(DATE(Settings!$B$12,7,1),0))) | I32: =IF($A32="","",SUMIFS(Expenses!$D$5:$D$504,Expenses!$B$5:$B$504,$A32,Expenses!$A$5:$A$504,">="&DATE(Settings!$B$12,8,1),Expenses!$A$5:$A$504,"<="&EOMONTH(DATE(Settings!$B$12,8,1),0))) | J32: =IF($A32="","",SUMIFS(Expenses!$D$5:$D$504,Expenses!$B$5:$B$504,$A32,Expenses!$A$5:$A$504,">="&DATE(Settings!$B$12,9,1),Expenses!$A$5:$A$504,"<="&EOMONTH(DATE(Settings!$B$12,9,1),0))) | K32: =IF($A32="","",SUMIFS(Expenses!$D$5:$D$504,Expenses!$B$5:$B$504,$A32,Expenses!$A$5:$A$504,">="&DATE(Settings!$B$12,10,1),Expenses!$A$5:$A$504,"<="&EOMONTH(DATE(Settings!$B$12,10,1),0))) | L32: =IF($A32="","",SUMIFS(Expenses!$D$5:$D$504,Expenses!$B$5:$B$504,$A32,Expenses!$A$5:$A$504,">="&DATE(Settings!$B$12,11,1),Expenses!$A$5:$A$504,"<="&EOMONTH(DATE(Settings!$B$12,11,1),0))) | M32: =IF($A32="","",SUMIFS(Expenses!$D$5:$D$504,Expenses!$B$5:$B$504,$A32,Expenses!$A$5:$A$504,">="&DATE(Settings!$B$12,12,1),Expenses!$A$5:$A$504,"<="&EOMONTH(DATE(Settings!$B$12,12,1),0))) | N32: =IF($A32="","",SUM(B32:M32))
A33: =IF(Settings!$H$17="","",Settings!$H$17) | B33: =IF($A33="","",SUMIFS(Expenses!$D$5:$D$504,Expenses!$B$5:$B$504,$A33,Expenses!$A$5:$A$504,">="&DATE(Settings!$B$12,1,1),Expenses!$A$5:$A$504,"<="&EOMONTH(DATE(Settings!$B$12,1,1),0))) | C33: =IF($A33="","",SUMIFS(Expenses!$D$5:$D$504,Expenses!$B$5:$B$504,$A33,Expenses!$A$5:$A$504,">="&DATE(Settings!$B$12,2,1),Expenses!$A$5:$A$504,"<="&EOMONTH(DATE(Settings!$B$12,2,1),0))) | D33: =IF($A33="","",SUMIFS(Expenses!$D$5:$D$504,Expenses!$B$5:$B$504,$A33,Expenses!$A$5:$A$504,">="&DATE(Settings!$B$12,3,1),Expenses!$A$5:$A$504,"<="&EOMONTH(DATE(Settings!$B$12,3,1),0))) | E33: =IF($A33="","",SUMIFS(Expenses!$D$5:$D$504,Expenses!$B$5:$B$504,$A33,Expenses!$A$5:$A$504,">="&DATE(Settings!$B$12,4,1),Expenses!$A$5:$A$504,"<="&EOMONTH(DATE(Settings!$B$12,4,1),0))) | F33: =IF($A33="","",SUMIFS(Expenses!$D$5:$D$504,Expenses!$B$5:$B$504,$A33,Expenses!$A$5:$A$504,">="&DATE(Settings!$B$12,5,1),Expenses!$A$5:$A$504,"<="&EOMONTH(DATE(Settings!$B$12,5,1),0))) | G33: =IF($A33="","",SUMIFS(Expenses!$D$5:$D$504,Expenses!$B$5:$B$504,$A33,Expenses!$A$5:$A$504,">="&DATE(Settings!$B$12,6,1),Expenses!$A$5:$A$504,"<="&EOMONTH(DATE(Settings!$B$12,6,1),0))) | H33: =IF($A33="","",SUMIFS(Expenses!$D$5:$D$504,Expenses!$B$5:$B$504,$A33,Expenses!$A$5:$A$504,">="&DATE(Settings!$B$12,7,1),Expenses!$A$5:$A$504,"<="&EOMONTH(DATE(Settings!$B$12,7,1),0))) | I33: =IF($A33="","",SUMIFS(Expenses!$D$5:$D$504,Expenses!$B$5:$B$504,$A33,Expenses!$A$5:$A$504,">="&DATE(Settings!$B$12,8,1),Expenses!$A$5:$A$504,"<="&EOMONTH(DATE(Settings!$B$12,8,1),0))) | J33: =IF($A33="","",SUMIFS(Expenses!$D$5:$D$504,Expenses!$B$5:$B$504,$A33,Expenses!$A$5:$A$504,">="&DATE(Settings!$B$12,9,1),Expenses!$A$5:$A$504,"<="&EOMONTH(DATE(Settings!$B$12,9,1),0))) | K33: =IF($A33="","",SUMIFS(Expenses!$D$5:$D$504,Expenses!$B$5:$B$504,$A33,Expenses!$A$5:$A$504,">="&DATE(Settings!$B$12,10,1),Expenses!$A$5:$A$504,"<="&EOMONTH(DATE(Settings!$B$12,10,1),0))) | L33: =IF($A33="","",SUMIFS(Expenses!$D$5:$D$504,Expenses!$B$5:$B$504,$A33,Expenses!$A$5:$A$504,">="&DATE(Settings!$B$12,11,1),Expenses!$A$5:$A$504,"<="&EOMONTH(DATE(Settings!$B$12,11,1),0))) | M33: =IF($A33="","",SUMIFS(Expenses!$D$5:$D$504,Expenses!$B$5:$B$504,$A33,Expenses!$A$5:$A$504,">="&DATE(Settings!$B$12,12,1),Expenses!$A$5:$A$504,"<="&EOMONTH(DATE(Settings!$B$12,12,1),0))) | N33: =IF($A33="","",SUM(B33:M33))
A34: =IF(Settings!$H$18="","",Settings!$H$18) | B34: =IF($A34="","",SUMIFS(Expenses!$D$5:$D$504,Expenses!$B$5:$B$504,$A34,Expenses!$A$5:$A$504,">="&DATE(Settings!$B$12,1,1),Expenses!$A$5:$A$504,"<="&EOMONTH(DATE(Settings!$B$12,1,1),0))) | C34: =IF($A34="","",SUMIFS(Expenses!$D$5:$D$504,Expenses!$B$5:$B$504,$A34,Expenses!$A$5:$A$504,">="&DATE(Settings!$B$12,2,1),Expenses!$A$5:$A$504,"<="&EOMONTH(DATE(Settings!$B$12,2,1),0))) | D34: =IF($A34="","",SUMIFS(Expenses!$D$5:$D$504,Expenses!$B$5:$B$504,$A34,Expenses!$A$5:$A$504,">="&DATE(Settings!$B$12,3,1),Expenses!$A$5:$A$504,"<="&EOMONTH(DATE(Settings!$B$12,3,1),0))) | E34: =IF($A34="","",SUMIFS(Expenses!$D$5:$D$504,Expenses!$B$5:$B$504,$A34,Expenses!$A$5:$A$504,">="&DATE(Settings!$B$12,4,1),Expenses!$A$5:$A$504,"<="&EOMONTH(DATE(Settings!$B$12,4,1),0))) | F34: =IF($A34="","",SUMIFS(Expenses!$D$5:$D$504,Expenses!$B$5:$B$504,$A34,Expenses!$A$5:$A$504,">="&DATE(Settings!$B$12,5,1),Expenses!$A$5:$A$504,"<="&EOMONTH(DATE(Settings!$B$12,5,1),0))) | G34: =IF($A34="","",SUMIFS(Expenses!$D$5:$D$504,Expenses!$B$5:$B$504,$A34,Expenses!$A$5:$A$504,">="&DATE(Settings!$B$12,6,1),Expenses!$A$5:$A$504,"<="&EOMONTH(DATE(Settings!$B$12,6,1),0))) | H34: =IF($A34="","",SUMIFS(Expenses!$D$5:$D$504,Expenses!$B$5:$B$504,$A34,Expenses!$A$5:$A$504,">="&DATE(Settings!$B$12,7,1),Expenses!$A$5:$A$504,"<="&EOMONTH(DATE(Settings!$B$12,7,1),0))) | I34: =IF($A34="","",SUMIFS(Expenses!$D$5:$D$504,Expenses!$B$5:$B$504,$A34,Expenses!$A$5:$A$504,">="&DATE(Settings!$B$12,8,1),Expenses!$A$5:$A$504,"<="&EOMONTH(DATE(Settings!$B$12,8,1),0))) | J34: =IF($A34="","",SUMIFS(Expenses!$D$5:$D$504,Expenses!$B$5:$B$504,$A34,Expenses!$A$5:$A$504,">="&DATE(Settings!$B$12,9,1),Expenses!$A$5:$A$504,"<="&EOMONTH(DATE(Settings!$B$12,9,1),0))) | K34: =IF($A34="","",SUMIFS(Expenses!$D$5:$D$504,Expenses!$B$5:$B$504,$A34,Expenses!$A$5:$A$504,">="&DATE(Settings!$B$12,10,1),Expenses!$A$5:$A$504,"<="&EOMONTH(DATE(Settings!$B$12,10,1),0))) | L34: =IF($A34="","",SUMIFS(Expenses!$D$5:$D$504,Expenses!$B$5:$B$504,$A34,Expenses!$A$5:$A$504,">="&DATE(Settings!$B$12,11,1),Expenses!$A$5:$A$504,"<="&EOMONTH(DATE(Settings!$B$12,11,1),0))) | M34: =IF($A34="","",SUMIFS(Expenses!$D$5:$D$504,Expenses!$B$5:$B$504,$A34,Expenses!$A$5:$A$504,">="&DATE(Settings!$B$12,12,1),Expenses!$A$5:$A$504,"<="&EOMONTH(DATE(Settings!$B$12,12,1),0))) | N34: =IF($A34="","",SUM(B34:M34))
A35: =IF(Settings!$H$19="","",Settings!$H$19) | B35: =IF($A35="","",SUMIFS(Expenses!$D$5:$D$504,Expenses!$B$5:$B$504,$A35,Expenses!$A$5:$A$504,">="&DATE(Settings!$B$12,1,1),Expenses!$A$5:$A$504,"<="&EOMONTH(DATE(Settings!$B$12,1,1),0))) | C35: =IF($A35="","",SUMIFS(Expenses!$D$5:$D$504,Expenses!$B$5:$B$504,$A35,Expenses!$A$5:$A$504,">="&DATE(Settings!$B$12,2,1),Expenses!$A$5:$A$504,"<="&EOMONTH(DATE(Settings!$B$12,2,1),0))) | D35: =IF($A35="","",SUMIFS(Expenses!$D$5:$D$504,Expenses!$B$5:$B$504,$A35,Expenses!$A$5:$A$504,">="&DATE(Settings!$B$12,3,1),Expenses!$A$5:$A$504,"<="&EOMONTH(DATE(Settings!$B$12,3,1),0))) | E35: =IF($A35="","",SUMIFS(Expenses!$D$5:$D$504,Expenses!$B$5:$B$504,$A35,Expenses!$A$5:$A$504,">="&DATE(Settings!$B$12,4,1),Expenses!$A$5:$A$504,"<="&EOMONTH(DATE(Settings!$B$12,4,1),0))) | F35: =IF($A35="","",SUMIFS(Expenses!$D$5:$D$504,Expenses!$B$5:$B$504,$A35,Expenses!$A$5:$A$504,">="&DATE(Settings!$B$12,5,1),Expenses!$A$5:$A$504,"<="&EOMONTH(DATE(Settings!$B$12,5,1),0))) | G35: =IF($A35="","",SUMIFS(Expenses!$D$5:$D$504,Expenses!$B$5:$B$504,$A35,Expenses!$A$5:$A$504,">="&DATE(Settings!$B$12,6,1),Expenses!$A$5:$A$504,"<="&EOMONTH(DATE(Settings!$B$12,6,1),0))) | H35: =IF($A35="","",SUMIFS(Expenses!$D$5:$D$504,Expenses!$B$5:$B$504,$A35,Expenses!$A$5:$A$504,">="&DATE(Settings!$B$12,7,1),Expenses!$A$5:$A$504,"<="&EOMONTH(DATE(Settings!$B$12,7,1),0))) | I35: =IF($A35="","",SUMIFS(Expenses!$D$5:$D$504,Expenses!$B$5:$B$504,$A35,Expenses!$A$5:$A$504,">="&DATE(Settings!$B$12,8,1),Expenses!$A$5:$A$504,"<="&EOMONTH(DATE(Settings!$B$12,8,1),0))) | J35: =IF($A35="","",SUMIFS(Expenses!$D$5:$D$504,Expenses!$B$5:$B$504,$A35,Expenses!$A$5:$A$504,">="&DATE(Settings!$B$12,9,1),Expenses!$A$5:$A$504,"<="&EOMONTH(DATE(Settings!$B$12,9,1),0))) | K35: =IF($A35="","",SUMIFS(Expenses!$D$5:$D$504,Expenses!$B$5:$B$504,$A35,Expenses!$A$5:$A$504,">="&DATE(Settings!$B$12,10,1),Expenses!$A$5:$A$504,"<="&EOMONTH(DATE(Settings!$B$12,10,1),0))) | L35: =IF($A35="","",SUMIFS(Expenses!$D$5:$D$504,Expenses!$B$5:$B$504,$A35,Expenses!$A$5:$A$504,">="&DATE(Settings!$B$12,11,1),Expenses!$A$5:$A$504,"<="&EOMONTH(DATE(Settings!$B$12,11,1),0))) | M35: =IF($A35="","",SUMIFS(Expenses!$D$5:$D$504,Expenses!$B$5:$B$504,$A35,Expenses!$A$5:$A$504,">="&DATE(Settings!$B$12,12,1),Expenses!$A$5:$A$504,"<="&EOMONTH(DATE(Settings!$B$12,12,1),0))) | N35: =IF($A35="","",SUM(B35:M35))
A36: Total | B36: =SUM(B21:B35) -> 0 | C36: =SUM(C21:C35) -> 0 | D36: =SUM(D21:D35) -> 0 | E36: =SUM(E21:E35) -> 0 | F36: =SUM(F21:F35) -> 0 | G36: =SUM(G21:G35) -> 0 | H36: =SUM(H21:H35) -> 483.14 | I36: =SUM(I21:I35) -> 569.2 | ... N36: =SUM(N21:N35) -> 1298.69
A37: If this total is lower than Expenses above, some expenses have a blank or unlisted category.
